Workbook
Name __: #REF!
Name __1_2000년입출고: #REF!
Name __KEY2: #REF!
Name _0: #REF!
Name _1: #REF!
Name _1_2000년입출고: #REF!
Name _10H_0Print_Area: #REF!
Name _13R_0PA: #REF!
Name _16U_0PA: #REF!
Name _2: #REF!
Name _2C_0PA: #REF!
Name _3: #REF!
Name _3H_0PA: #REF!
Name _4: #REF!
Name _4C_0PA: #REF!
Name _4H_0Print_Area: #REF!
Name _6R_0PA: #REF!
Name _7H_0PA: #REF!
Name _7U_0PA: #REF!
Name _Fill: #REF!
Name _Key2: #REF!
Name _Sort: #REF!
Name A: #REF!
Name AAA: #REF!
Name Acquisition_Costs: #REF!
Name Adjusted_Basis: #REF!
Name Bal_EOY1_Mtg_1: #REF!
Name Bal_EOY1_Mtg_2: #REF!
Name Bal_EOY2_Mtg_1: #REF!
Name Bal_EOY2_Mtg_2: #REF!
Name Bal_EOY3_Mtg_1: #REF!
Name Bal_EOY3_Mtg_2: #REF!
Name Bal_EOY4_Mtg_1: #REF!
Name Bal_EOY4_Mtg_2: #REF!
Name Bal_EOY5_Mtg_1: #REF!
Name Bal_EOY5_Mtg_2: #REF!
Name BS: #REF!
Name BTL: #REF!
Name CFBT_APOD: #REF!
Name data: #REF!
Name Date: #REF!
Name dfakdf: #REF!
Name Down_Payment: #REF!
Name ERI_APOD: #REF!
Name file: #REF!
Name FKFK: #REF!
Name GOI: #REF!
Name GOI_APOD: #REF!
Name Initial_Investment: #REF!
Name INPUT: #REF!
Name Land_summary: 토지조서!$A$140:$AA$150
Name Leasing_Commissions: #REF!
Name Loan_Points: #REF!
Name Location: #REF!
Name mii: #REF!
Name ML: #REF!
Name Name: #REF!
Name NOI_APOD: #REF!
Name OP_EXP_APOD: #REF!
Name OTHER_APOD: #REF!

Sheet 건축개요
A1: 사 업 명
A4: ■ 건축개요
A5: 공 사 명 | C5: 래미안목동아델리체
A6: 대지위치 | C6: 서울 양천구 신정동 1326
A7: 지역지구 | C7: 도시지역, 제2종일반주거지역
A8: 공사종별 | C8: 아파트 | I8: =I9/$F$9 -> 0
A9: 대지면적 | C9: =F9-I9-L9 -> 60663.8 | D9: =C9*0.3025 -> 18350.8 | E9: 매입면적: | F9: 60663.8 | G9: =F9*0.3025 -> 18350.8 | H9: 기부채납면적 : | I9: 0 | J9: =I9*0.3025 -> 0
A10: 용 도 | C10: 공동주택, 근생시설
A11: 건축면적 | C11: 13572.54 | D11: =C11*0.3025 -> 4105.6934
A12: 건 폐 율 | C12: =C11/C9 -> 0.22373376 | D12: (법정 : | E12: 22.37 | F12: %)
A13: 연 면 적 | C13: =E24 -> 155753.45 | D13: =C13*0.3025 -> 47115.419
A14: 용 적 율 | C14: =E24/C9 -> 2.5674859 | D14: (법정 : | E14: 257.55 | F14: %)
A15: 규 모 | C15: 지상 : 27층 | D15: 지하 : 3층
A16: 구 조 | C16: RC구조
A17: 주차대수
C18: 지상 : | D18: 11 | E18: 지하 : | F18: 2015
A21: ■ 층별 면적표 | F21: ( 단위 : ㎡/평 )
A22: 구분 | C22: 아파트 | D22: 근생시설 | E22: 계 | F22: 비 고
A24: 지상층 | C24: 153042.91 | D24: 2710.54 | E24: =SUM(C24:D24) -> 155753.45 | F24: =E24/C9 -> 2.5674859
C25: =C24*0.3025 -> 46295.48 | D25: =D24*0.3025 -> 819.93835 | E25: =SUM(C25:D25) -> 47115.419
A26: 지하층 | C26: 87376.25 | D26: 583.72 | E26: =SUM(C26:D26) -> 87959.97 | F26: =E26/$C$9 -> 1.4499581
C27: =C26*0.3025 -> 26431.316 | D27: =D26*0.3025 -> 176.5753 | E27: =SUM(C27:D27) -> 26607.891 | F27: =ROUNDUP(F26/80%,0) -> 2
A28: 소 계 | C28: =C24+C26 -> 240419.16 | D28: =D24+D26 -> 3294.26 | E28: =SUM(C28:D28) -> 243713.42
C29: =C28*0.3025 -> 72726.796 | D29: =D28*0.3025 -> 996.51365 | E29: =SUM(C29:D29) -> 73723.31
A30: 비 율 | C30: =C28/$E$28 -> 0.98648306 | D30: =D28/$E$28 -> 0.013516941 | E30: =E28/$E$28 -> 1
A33: ■ 용도별 면적표
A34: 구 분 | D34: 전용면적(㎡/평) | F34: 공용면적(㎡/평) | H34: 공급면적(㎡/평) | J34: 기타공용면적(㎡/평) | L34: 계약면적(㎡/평) | N34: 비율
A35: =C22 -> 아파트 | D35: =D57+D72+D81 -> 113066.45 | E35: =D35*0.3025 -> 34202.601 | F35: =F57+F72+F81 -> 39970.05 | G35: =F35*0.3025 -> 12090.94 | H35: =D35+F35 -> 153036.5 | I35: =H35*0.3025 -> 46293.541 | J35: =C26=J57+J72+J81 -> FALSE | K35: =J35*0.3025 -> 0 | L35: =H35+J35 -> 153036.5 | M35: =L35*0.3025 -> 46293.541 | N35: =L35/$L$37 -> 0.98259652
A36: =D22 -> 근생시설 | D36: =D89 -> 2710.54 | E36: =D36*0.3025 -> 819.93835 | F36: =F89 -> 0 | G36: =F36*0.3025 -> 0 | H36: =D36+F36 -> 2710.54 | I36: =H36*0.3025 -> 819.93835 | K36: =J36*0.3025 -> 0 | L36: =H36+J36 -> 2710.54 | M36: =L36*0.3025 -> 819.93835 | N36: =L36/$L$37 -> 0.017403477
A37: 합 계 | D37: =SUM(D35:D36) -> 115776.99 | E37: =D37*0.3025 -> 35022.539 | F37: =SUM(F35:F36) -> 39970.05 | G37: =F37*0.3025 -> 12090.94 | H37: =SUM(H35:H36) -> 155747.04 | I37: =H37*0.3025 -> 47113.48 | J37: =SUM(J35:J36) -> 0 | K37: =J37*0.3025 -> 0 | L37: =SUM(L35:L36) -> 155747.04 | M37: =L37*0.3025 -> 47113.48 | N37: =L37/$L$37 -> 1
A40: ■ | B40: 일반분양 | C40: 면적표
A41: 구분 | B41: 평형 | C41: 세대수 | D41: 전용면적(m2/평) | F41: 공용면적(m2/평) | H41: 공급면적(m2/평) | J41: 기타공용면적(m2/평) | L41: 계약면적(m2/평) | N41: 비고
A42: A | B42: =E42 -> 18.09555 | C42: 142 | D42: 59.82 | E42: =D42*0.3025 -> 18.09555 | F42: 23.84 | G42: =F42*0.3025 -> 7.2116 | H42: =D42+F42 -> 83.66 | I42: =H42*0.3025 -> 25.30715 | J42: 53.36 | K42: =J42*0.3025 -> 16.1414 | L42: =H42+J42 -> 137.02 | M42: =L42*0.3025 -> 41.44855
A43: B | B43: =E43 -> 18.14395 | C43: 19 | D43: 59.98 | E43: =D43*0.3025 -> 18.14395 | F43: 23.25 | G43: =F43*0.3025 -> 7.033125 | H43: =D43+F43 -> 83.23 | I43: =H43*0.3025 -> 25.177075 | J43: 44.57 | K43: =J43*0.3025 -> 13.482425 | L43: =H43+J43 -> 127.8 | M43: =L43*0.3025 -> 38.6595
A44: C | B44: =E44 -> 18.09555 | C44: 20 | D44: 59.82 | E44: =D44*0.3025 -> 18.09555 | F44: 23.08 | G44: =F44*0.3025 -> 6.9817 | H44: =D44+F44 -> 82.9 | I44: =H44*0.3025 -> 25.07725 | J44: 44.46 | K44: =J44*0.3025 -> 13.44915 | L44: =H44+J44 -> 127.36 | M44: =L44*0.3025 -> 38.5264
A45: D | B45: =E45 -> 25.69435 | C45: 88 | D45: 84.94 | E45: =D45*0.3025 -> 25.69435 | F45: 24.49 | G45: =F45*0.3025 -> 7.408225 | H45: =D45+F45 -> 109.43 | I45: =H45*0.3025 -> 33.102575 | J45: 63.13 | K45: =J45*0.3025 -> 19.096825 | L45: =H45+J45 -> 172.56 | M45: =L45*0.3025 -> 52.1994
A46: E | B46: =E46 -> 25.6278 | C46: 70 | D46: 84.72 | E46: =D46*0.3025 -> 25.6278 | F46: 23.8 | G46: =F46*0.3025 -> 7.1995 | H46: =D46+F46 -> 108.52 | I46: =H46*0.3025 -> 32.8273 | J46: 62.97 | K46: =J46*0.3025 -> 19.048425 | L46: =H46+J46 -> 171.49 | M46: =L46*0.3025 -> 51.875725
A47: F | B47: =E47 -> 25.6641 | C47: 5 | D47: 84.84 | E47: =D47*0.3025 -> 25.6641 | F47: 41.94 | G47: =F47*0.3025 -> 12.68685 | H47: =D47+F47 -> 126.78 | I47: =H47*0.3025 -> 38.35095 | J47: 63.05 | K47: =J47*0.3025 -> 19.072625 | L47: =H47+J47 -> 189.83 | M47: =L47*0.3025 -> 57.423575
A48: G | B48: =E48 -> 25.68225 | C48: 109 | D48: 84.9 | E48: =D48*0.3025 -> 25.68225 | F48: 26.45 | G48: =F48*0.3025 -> 8.001125 | H48: =D48+F48 -> 111.35 | I48: =H48*0.3025 -> 33.683375 | J48: 63.09 | K48: =J48*0.3025 -> 19.084725 | L48: =H48+J48 -> 174.44 | M48: =L48*0.3025 -> 52.7681
A49: H | B49: =E49 -> 25.697375 | C49: 45 | D49: 84.95 | E49: =D49*0.3025 -> 25.697375 | F49: 25.64 | G49: =F49*0.3025 -> 7.7561 | H49: =D49+F49 -> 110.59 | I49: =H49*0.3025 -> 33.453475 | J49: 63.13 | K49: =J49*0.3025 -> 19.096825 | L49: =H49+J49 -> 173.72 | M49: =L49*0.3025 -> 52.5503
A50: I | B50: =E50 -> 25.58545 | C50: 75 | D50: 84.58 | E50: =D50*0.3025 -> 25.58545 | F50: 25.83 | G50: =F50*0.3025 -> 7.813575 | H50: =D50+F50 -> 110.41 | I50: =H50*0.3025 -> 33.399025 | J50: 62.86 | K50: =J50*0.3025 -> 19.01515 | L50: =H50+J50 -> 173.27 | M50: =L50*0.3025 -> 52.414175
A51: J | B51: =E51 -> 35.080925 | C51: 71 | D51: 115.97 | E51: =D51*0.3025 -> 35.080925 | F51: 36.71 | G51: =F51*0.3025 -> 11.104775 | H51: =D51+F51 -> 152.68 | I51: =H51*0.3025 -> 46.1857 | J51: 86.19 | K51: =J51*0.3025 -> 26.072475 | L51: =H51+J51 -> 238.87 | M51: =L51*0.3025 -> 72.258175
A52: K | B52: =E52 -> 0 | E52: =D52*0.3025 -> 0 | G52: =F52*0.3025 -> 0 | H52: =D52+F52 -> 0 | I52: =H52*0.3025 -> 0 | K52: =J52*0.3025 -> 0 | L52: =H52+J52 -> 0 | M52: =L52*0.3025 -> 0
A53: L | B53: =E53 -> 0 | E53: =D53*0.3025 -> 0 | G53: =F53*0.3025 -> 0 | H53: =D53+F53 -> 0 | I53: =H53*0.3025 -> 0 | K53: =J53*0.3025 -> 0 | L53: =H53+J53 -> 0 | M53: =L53*0.3025 -> 0
A54: M | B54: =E54 -> 0 | E54: =D54*0.3025 -> 0 | G54: =F54*0.3025 -> 0 | H54: =D54+F54 -> 0 | I54: =H54*0.3025 -> 0 | K54: =J54*0.3025 -> 0 | L54: =H54+J54 -> 0 | M54: =L54*0.3025 -> 0
A55: N | B55: =E55 -> 0 | E55: =D55*0.3025 -> 0 | G55: =F55*0.3025 -> 0 | H55: =D55+F55 -> 0 | I55: =H55*0.3025 -> 0 | K55: =J55*0.3025 -> 0 | L55: =H55+J55 -> 0 | M55: =L55*0.3025 -> 0
A56: O | B56: =E56 -> 0 | E56: =D56*0.3025 -> 0 | G56: =F56*0.3025 -> 0 | H56: =D56+F56 -> 0 | I56: =H56*0.3025 -> 0 | K56: =J56*0.3025 -> 0 | L56: =H56+J56 -> 0 | M56: =L56*0.3025 -> 0
A57: 합계 | C57: =SUM(C42:C56) -> 644 | D57: =SUMPRODUCT($C42:$C56,D42:D56) -> 52314 | E57: =D57*0.3025 -> 15824.985 | F57: =SUMPRODUCT($C42:$C56,F42:F56) -> 16899.96 | G57: =F57*0.3025 -> 5112.2379 | H57: =SUMPRODUCT($C42:$C56,H42:H56) -> 69213.96 | I57: =H57*0.3025 -> 20937.223 | J57: =SUMPRODUCT($C42:$C56,J42:J56) -> 40143.39 | K57: =J57*0.3025 -> 12143.375 | L57: =SUMPRODUCT($C42:$C56,L42:L56) -> 109357.35 | M57: =L57*0.3025 -> 33080.598
A60: ■ | B60: 조합분양 | C60: 면적표
A61: 구분 | B61: 평형 | C61: 세대수 | D61: 전용면적(m2/평) | F61: 공용면적(m2/평) | H61: 공급면적(m2/평) | J61: 기타공용면적(m2/평) | L61: 계약면적(m2/평) | N61: 비고
A62: A | B62: =E62 -> 18.09555 | C62: 8 | D62: 59.82 | E62: =D62*0.3025 -> 18.09555 | F62: 23.84 | G62: =F62*0.3025 -> 7.2116 | H62: =D62+F62 -> 83.66 | I62: =H62*0.3025 -> 25.30715 | J62: 53.36 | K62: =J62*0.3025 -> 16.1414 | L62: =H62+J62 -> 137.02 | M62: =L62*0.3025 -> 41.44855
A63: B | B63: =E63 -> 18.14395 | C63: 8 | D63: 59.98 | E63: =D63*0.3025 -> 18.14395 | F63: 23.25 | G63: =F63*0.3025 -> 7.033125 | H63: =D63+F63 -> 83.23 | I63: =H63*0.3025 -> 25.177075 | J63: 44.57 | K63: =J63*0.3025 -> 13.482425 | L63: =H63+J63 -> 127.8 | M63: =L63*0.3025 -> 38.6595
A64: C | B64: =E64 -> 18.09555 | C64: 87 | D64: 59.82 | E64: =D64*0.3025 -> 18.09555 | F64: 23.08 | G64: =F64*0.3025 -> 6.9817 | H64: =D64+F64 -> 82.9 | I64: =H64*0.3025 -> 25.07725 | J64: 44.57 | K64: =J64*0.3025 -> 13.482425 | L64: =H64+J64 -> 127.47 | M64: =L64*0.3025 -> 38.559675
A65: D | B65: =E65 -> 25.69435 | C65: 108 | D65: 84.94 | E65: =D65*0.3025 -> 25.69435 | F65: 24.49 | G65: =F65*0.3025 -> 7.408225 | H65: =D65+F65 -> 109.43 | I65: =H65*0.3025 -> 33.102575 | J65: 63.13 | K65: =J65*0.3025 -> 19.096825 | L65: =H65+J65 -> 172.56 | M65: =L65*0.3025 -> 52.1994
A66: E | B66: =E66 -> 25.6278 | C66: 126 | D66: 84.72 | E66: =D66*0.3025 -> 25.6278 | F66: 23.8 | G66: =F66*0.3025 -> 7.1995 | H66: =D66+F66 -> 108.52 | I66: =H66*0.3025 -> 32.8273 | J66: 62.97 | K66: =J66*0.3025 -> 19.048425 | L66: =H66+J66 -> 171.49 | M66: =L66*0.3025 -> 51.875725
A67: F | B67: =E67 -> 25.6641 | C67: 14 | D67: 84.84 | E67: =D67*0.3025 -> 25.6641 | F67: 41.94 | G67: =F67*0.3025 -> 12.68685 | H67: =D67+F67 -> 126.78 | I67: =H67*0.3025 -> 38.35095 | J67: 63.05 | K67: =J67*0.3025 -> 19.072625 | L67: =H67+J67 -> 189.83 | M67: =L67*0.3025 -> 57.423575
A68: G | B68: =E68 -> 25.68225 | C68: 32 | D68: 84.9 | E68: =D68*0.3025 -> 25.68225 | F68: 26.45 | G68: =F68*0.3025 -> 8.001125 | H68: =D68+F68 -> 111.35 | I68: =H68*0.3025 -> 33.683375 | J68: 63.09 | K68: =J68*0.3025 -> 19.084725 | L68: =H68+J68 -> 174.44 | M68: =L68*0.3025 -> 52.7681
A69: H | B69: =E69 -> 25.697375 | C69: 149 | D69: 84.95 | E69: =D69*0.3025 -> 25.697375 | F69: 25.64 | G69: =F69*0.3025 -> 7.7561 | H69: =D69+F69 -> 110.59 | I69: =H69*0.3025 -> 33.453475 | J69: 63.09 | K69: =J69*0.3025 -> 19.084725 | L69: =H69+J69 -> 173.68 | M69: =L69*0.3025 -> 52.5382
A70: I | B70: =E70 -> 25.58545 | C70: 27 | D70: 84.58 | E70: =D70*0.3025 -> 25.58545 | F70: 25.83 | G70: =F70*0.3025 -> 7.813575 | H70: =D70+F70 -> 110.41 | I70: =H70*0.3025 -> 33.399025 | J70: 62.86 | K70: =J70*0.3025 -> 19.01515 | L70: =H70+J70 -> 173.27 | M70: =L70*0.3025 -> 52.414175
A71: J | B71: =E71 -> 35.080925 | C71: 28 | D71: 115.97 | E71: =D71*0.3025 -> 35.080925 | F71: 36.71 | G71: =F71*0.3025 -> 11.104775 | H71: =D71+F71 -> 152.68 | I71: =H71*0.3025 -> 46.1857 | J71: 86.19 | K71: =J71*0.3025 -> 26.072475 | L71: =H71+J71 -> 238.87 | M71: =L71*0.3025 -> 72.258175
A72: 합계 | C72: =SUM(C62:C71) -> 587 | D72: =SUMPRODUCT($C62:$C71,D62:D71) -> 48103.91 | E72: =D72*0.3025 -> 14551.433 | F72: =SUMPRODUCT($C62:$C71,F62:F71) -> 15007.61 | G72: =F72*0.3025 -> 4539.802 | H72: =SUMPRODUCT($C62:$C71,H62:H71) -> 63111.52 | I72: =H72*0.3025 -> 19091.235 | J72: =SUMPRODUCT($C62:$C71,J62:J71) -> 35825.82 | K72: =J72*0.3025 -> 10837.311 | L72: =SUMPRODUCT($C62:$C71,L62:L71) -> 98937.34 | M72: =L72*0.3025 -> 29928.545
A75: ■ | B75: 공공임대 | C75: 면적표
A76: 구분 | B76: 평형 | C76: 세대수 | D76: 전용면적(m2/평) | F76: 공용면적(m2/평) | H76: 공급면적(m2/평) | J76: 기타공용면적(m2/평) | L76: 계약면적(m2/평) | N76: 비고
A77: A | B77: =E77 -> 11.915475 | C77: 90 | D77: 39.39 | E77: =D77*0.3025 -> 11.915475 | F77: 25.41 | G77: =F77*0.3025 -> 7.686525 | H77: =D77+F77 -> 64.8 | I77: =H77*0.3025 -> 19.602 | J77: 35.14 | K77: =J77*0.3025 -> 10.62985 | L77: =H77+J77 -> 99.94 | M77: =L77*0.3025 -> 30.23185
A78: B | B78: =E78 -> 14.88905 | C78: 106 | D78: 49.22 | E78: =D78*0.3025 -> 14.88905 | F78: 31.31 | G78: =F78*0.3025 -> 9.471275 | H78: =D78+F78 -> 80.53 | I78: =H78*0.3025 -> 24.360325 | J78: 43.9 | K78: =J78*0.3025 -> 13.27975 | L78: =H78+J78 -> 124.43 | M78: =L78*0.3025 -> 37.640075
A79: C | B79: =E79 -> 16.4681 | C79: 56 | D79: 54.44 | E79: =D79*0.3025 -> 16.4681 | F79: 34.33 | G79: =F79*0.3025 -> 10.384825 | H79: =D79+F79 -> 88.77 | I79: =H79*0.3025 -> 26.852925 | J79: 48.56 | K79: =J79*0.3025 -> 14.6894 | L79: =H79+J79 -> 137.33 | M79: =L79*0.3025 -> 41.542325
A80: D | B80: =E80 -> 18.09555 | C80: 14 | D80: 59.82 | E80: =D80*0.3025 -> 18.09555 | F80: 38.16 | G80: =F80*0.3025 -> 11.5434 | H80: =D80+F80 -> 97.98 | I80: =H80*0.3025 -> 29.63895 | J80: 53.36 | K80: =J80*0.3025 -> 16.1414 | L80: =H80+J80 -> 151.34 | M80: =L80*0.3025 -> 45.78035
A81: 합계 | C81: =SUM(C77:C80) -> 266 | D81: =SUMPRODUCT($C77:$C80,D77:D80) -> 12648.54 | E81: =D81*0.3025 -> 3826.1833 | F81: =SUMPRODUCT($C77:$C80,F77:F80) -> 8062.48 | G81: =F81*0.3025 -> 2438.9002 | H81: =SUMPRODUCT($C77:$C80,H77:H80) -> 20711.02 | I81: =H81*0.3025 -> 6265.0836 | J81: =SUMPRODUCT($C77:$C80,J77:J80) -> 11282.4 | K81: =J81*0.3025 -> 3412.926 | L81: =SUMPRODUCT($C77:$C80,L77:L80) -> 31993.42 | M81: =L81*0.3025 -> 9678.0095
A82: 기본형건축비의 80% 가격에 공공기관에 판매 - '기본형건축비' 참고
A84: ■ | B84: =D22 -> 근생시설 | C84: 면적표
A85: 구 분 | C85: 층수 | D85: 전용면적(m2/평) | F85: 공용면적(m2/평) | H85: 공급면적(m2/평) | J85: 기타공용면적(m2/평) | L85: 계약면적(m2/평) | N85: 비고
A86: 1층 | B86: =M86 -> 819.93835 | C86: 1 | D86: 2710.54 | E86: =D86*0.3025 -> 819.93835 | F86: 0 | G86: =F86*0.3025 -> 0 | H86: =D86+F86 -> 2710.54 | I86: =H86*0.3025 -> 819.93835 | J86: 0 | K86: =J86*0.3025 -> 0 | L86: =H86+J86 -> 2710.54 | M86: =L86*0.3025 -> 819.93835
A87: 지하1층 | B87: =M87 -> 114.43575 | C87: 지하1층 | D87: 0 | E87: =D87*0.3025 -> 0 | F87: 0 | G87: =F87*0.3025 -> 0 | H87: =D87+F87 -> 0 | I87: =H87*0.3025 -> 0 | J87: 378.3 | K87: =J87*0.3025 -> 114.43575 | L87: =H87+J87 -> 378.3 | M87: =L87*0.3025 -> 114.43575
A88: 지하2층 | B88: =M88 -> 62.13955 | C88: 지하3층 | D88: 0 | E88: =D88*0.3025 -> 0 | F88: 0 | G88: =F88*0.3025 -> 0 | H88: =D88+F88 -> 0 | I88: =H88*0.3025 -> 0 | J88: 205.42 | K88: =J88*0.3025 -> 62.13955 | L88: =H88+J88 -> 205.42 | M88: =L88*0.3025 -> 62.13955
A89: 합계 | C89: =SUM(C86:C88) -> 1 | D89: =SUMPRODUCT(C86:C88,D86:D88) -> 2710.54 | E89: =D89*0.3025 -> 819.93835 | G89: =F89*0.3025 -> 0 | H89: =SUMPRODUCT($C86:$C88,H86:H88) -> 2710.54 | I89: =H89*0.3025 -> 819.93835 | J89: =J36 -> 0 | K89: =J89*0.3025 -> 0 | L89: =SUMPRODUCT($C86:$C88,L86:L88) -> 2710.54 | M89: =L89*0.3025 -> 819.93835
A92: ※ 인허가 및 설계과정에서 변경될 수 있음

Sheet 사업검토
B2: 사 업 명 | E2: =건축개요!C5 -> 래미안목동아델리체 | M2: =TODAY() -> 45993
M3: [ 참 고 용]
B4: 위 치 | E4: =건축개요!C6 -> 서울 양천구 신정동 1326 | H4: 토지평단가 | I4: =0 -> 0 | K4: 용적률 | L4: =건축개요!C14 -> 2.5674859 | O4: 지하면/연면적 | P4: =E12/E10 -> 0.36091558 | R4: 구 분 | S4: 일반분양 분양률 | T4: 근생시설 분양률 | U4: 전체 금액
B5: 용 도 지 역 | E5: =건축개요!C7 -> 도시지역, 제2종일반주거지역 | H5: 평균개별공시지가 | I5: 0 | K5: 건폐율 | L5: =건축개요!C12 -> 0.22373376 | O5: 건축비/토지비 | P5: =M75/M70 -> #DIV/0! | R5: 착공 | S5: 0.7 | T5: 0 | U5: =$M$22*S5+$M$54*T5 -> 4.7372884e+08 | W5: 아파트 계약금 중도금 잔금 비율: (10:60:30)
B6: 토지 면적 | C6: 매입면적 | E6: =건축개요!F9 -> 60663.8 | F6: ㎡ | G6: =E6*0.3025 -> 18350.8 | H6: 자기자본 | I6: =0 -> 0 | K6: 건축규모 | L6: =건축개요!C15 -> 지상 : 27층 | M6: =건축개요!D15 -> 지하 : 3층 | O6: 상가비/전체비 | P6: =M54/M58 -> 0.037710294 | R6: D+1 | S6: 0.1 | T6: 0 | U6: =$M$22*S6+$M$54*T6 -> 67675548 | W6: 근생시설 계약금 중도금 잔금 비율: (10:40:50)
C7: 기부채납면적 | E7: =건축개요!I9 -> 0 | F7: ㎡ | G7: =E7*0.3025 -> 0 | H7: Bridge Loan | I7: =M70*110% -> 0 | K7: 세대수 | L7: =G22+G38 -> 1231 | M7: 세대/실 | O7: 실부지/전체비 | P7: =E9/E6 -> 1 | R7: D+2 | S7: 0.1 | T7: 0 | U7: =$M$22*S7+$M$54*T7 -> 67675548 | W7: 아파트 중도금 1차~6차, 10%씩 들어옴
H8: PF Tr A | I8: =M168 -> 460000000 | K8: 사업기간 | L8: =L12+8 -> 48 | O8: 수익금/투자금 | P8: =M146/I6 -> #DIV/0! | R8: D+3 | S8: 0.1 | T8: 0.5 | U8: =$M$22*S8+$M$54*T8 -> 85622759
C9: 사업면적(대지면적) | E9: =E6-E7-E8 -> 60663.8 | F9: ㎡ | G9: =E9*0.3025 -> 18350.8 | K9: 건축비 | L9: 7000 | R9: D+4 | S9: 0 | T9: 0.5 | U9: =$M$22*S9+$M$54*T9 -> 17947211 | W9: 조합분양의 경우 (10:60:20), 10은 초기자본으로 사용
B10: 연 면 적 | C10: 계 | E10: =E11+E12 -> 243713.42 | F10: ㎡ | G10: =E10*0.3025 -> 73723.31 | H10: 총 PF금액 | I10: =SUM(I7:I9) -> 460000000 | K10: 공사비 지급율 | L10: 1 | R10: 준공 | S10: 0 | T10: 0 | U10: =$M$22*S10+$M$54*T10 -> 0
C11: 지상 | E11: =건축개요!E24 -> 155753.45 | F11: ㎡ | G11: =E11*0.3025 -> 47115.419 | H11: 토지비 확보율 | I11: 1 | K11: 공사기간 | L11: =U19&"년 "&U20& "월"&" ~" -> 2026년 4월 ~ | M11: =HLOOKUP(L12,Q16:BP20,4)&"년 "&HLOOKUP(L12,Q16:BP20,5)&"월" -> 2029년 7월 | R11: 계 | S11: =SUM(S5:S10) -> 1 | T11: =SUM(T5:T10) -> 1 | U11: =SUM(U5:U10) -> 7.1264991e+08
C12: 지하 | E12: =건축개요!E26 -> 87959.97 | F12: ㎡ | G12: =E12*0.3025 -> 26607.891 | H12: PF 수수료 | I12: 0.01 | L12: 40
H13: Tr A 이자율 | I13: 0.065 | K13: 중도금무이자율 | L13: 0
K14: 중도금 간격 | L14: =ROUNDUP(L12/6,0) -> 7 | O14: 중도금 간격 | BI14: =ROUNDUP((BI16-1)/$L$14,0) -> 6 | BJ14: =ROUNDUP((BJ16-1)/$L$14,0) -> 6 | BK14: =ROUNDUP((BK16-1)/$L$14,0) -> 6 | BL14: =ROUNDUP((BL16-1)/$L$14,0) -> 7 | BM14: =ROUNDUP((BM16-1)/$L$14,0) -> 7 | BN14: =ROUNDUP((BN16-1)/$L$14,0) -> 7 | BO14: =ROUNDUP((BO16-1)/$L$14,0) -> 7 | BP14: =ROUNDUP((BP16-1)/$L$14,0) -> 7
H15: 부가세 비율 | I15: 0.1 | K15: 일반분양 평균분양가 | L15: 42765 | O15: 중도금 입금월 | BI15: =IF(BH14=BI14,"",BI14) -> 6 | BJ15: =IF(BI14=BJ14,"",BJ14) | BK15: =IF(BJ14=BK14,"",BK14) | BL15: =IF(BK14=BL14,"",BL14) -> 7 | BM15: =IF(BL14=BM14,"",BM14) | BN15: =IF(BM14=BN14,"",BN14) | BO15: =IF(BN14=BO14,"",BO14) | BP15: =IF(BO14=BP14,"",BP14)
O16: 공사기간 | U16: 1 | V16: =U16+1 -> 2 | W16: =V16+1 -> 3 | X16: =W16+1 -> 4 | Y16: =X16+1 -> 5 | Z16: =Y16+1 -> 6 | AA16: =Z16+1 -> 7 | AB16: =AA16+1 -> 8 | AC16: =AB16+1 -> 9 | ... BP16: =BO16+1 -> 48
O17: 공정율 | P17: 0 | Q17: 0 | R17: 0 | S17: 0 | U17: =2.5% -> 0.025 | V17: 0.025 | W17: 0.025 | X17: 0.025 | Y17: 0.025 | Z17: 0.025 | AA17: 0.025 | AB17: 0.025 | AC17: 0.025 | AD17: 0.025 | AE17: 0.025 | AF17: 0.025 | AG17: 0.025 | AH17: 0.025 | AI17: 0.025 | AJ17: 0.025 | AK17: 0.025 | AL17: 0.025 | AM17: 0.025 | AN17: 0.025 | AO17: 0.025 | AP17: 0.025 | AQ17: 0.025 | AR17: 0.025 | AS17: 0.025 | AT17: 0.025 | AU17: 0.025 | AV17: 0.025 | AW17: 0.025 | AX17: 0.025 | AY17: 0.025 | AZ17: 0.025 | BA17: 0.025 | BB17: 0.025 | BC17: 0.025 | BD17: 0.025 | BE17: 0.025 | BF17: 0.025 | BG17: 0.025 | BH17: 0.025
O18: 누적공정율 | U18: =T18+U17 -> 0.025 | V18: =U18+V17 -> 0.05 | W18: =V18+W17 -> 0.075 | X18: =W18+X17 -> 0.1 | Y18: =X18+Y17 -> 0.125 | Z18: =Y18+Z17 -> 0.15 | AA18: =Z18+AA17 -> 0.175 | AB18: =AA18+AB17 -> 0.2 | ... BH18: =BG18+BH17 -> 1
M19: (단위 : 천원) | O19: 년 도 | P19: 2025 | Q19: =IF(Q20=1,(P19+1),P19) -> 2025 | R19: =IF(R20=1,(Q19+1),Q19) -> 2026 | S19: =IF(S20=1,(R19+1),R19) -> 2026 | T19: =IF(T20=1,(S19+1),S19) -> 2026 | U19: =IF(U20=1,(T19+1),T19) -> 2026 | V19: =IF(V20=1,(U19+1),U19) -> 2026 | W19: =IF(W20=1,(V19+1),V19) -> 2026 | X19: =IF(X20=1,(W19+1),W19) -> 2026 | ... BP19: =IF(BP20=1,(BO19+1),BO19) -> 2030
B20: 구 분 | G20: 내 역 | L20: 비율 | M20: 금 액 | P20: 11 | Q20: =MOD((P20),12)+1 -> 12 | R20: =MOD((Q20),12)+1 -> 1 | S20: =MOD((R20),12)+1 -> 2 | T20: =MOD((S20),12)+1 -> 3 | U20: =MOD((T20),12)+1 -> 4 | V20: =MOD((U20),12)+1 -> 5 | W20: =MOD((V20),12)+1 -> 6 | X20: =MOD((W20),12)+1 -> 7 | ... BP20: =MOD((BO20),12)+1 -> 3 | BQ20: 계 | BR20: 검 산 | BS20: 오차
L21: (%) | P21: 계약 | S21: PF | T21: 허가 | U21: 착공 | V21: d+1 | W21: d+2 | X21: d+3 | Y21: d+4 | AB21: 중도금 1차 | AH21: 중도금 2차 | AN21: 중도금 3차 | AT21: 중도금 4차 | AZ21: 중도금 5차 | BF21: 중도금 6차 | BH21: 준공 | BI21: 입주 | BJ21: 정산
B22: 매 출 | C22: 일반분양 | D22: 소 계 | E22: =SUMPRODUCT(E23:E37,G23:G37) -> 15824.985 | G22: =SUM(G23:G37) -> 644 | H22: 부가세 별도 | I22: 부가세 포함 | L22: =M22/M$69 -> 0.72179116 | M22: =SUM(M23:M37) -> 6.7675548e+08 | O22: =C22 -> 일반분양 | P22: =SUM(P23:P37) -> 0 | Q22: =SUM(Q23:Q37) -> 0 | R22: =SUM(R23:R37) -> 0 | S22: =SUM(S23:S37) -> 0 | T22: =SUM(T23:T37) -> 0 | U22: =SUM(U23:U37) -> 0 | V22: =SUM(V23:V37) -> 47372884 | W22: =SUM(W23:W37) -> 6767554.8 | ... BP22: =SUM(BP23:BP37) -> 0 | BQ22: =SUM(P22:BP22) -> 6.7675548e+08 | BR22: =+M22 -> 6.7675548e+08 | BS22: =BQ22-BR22 -> 0
D23: A | E23: =건축개요!B42 -> 18.09555 | F23: 평형 | G23: =건축개요!C42 -> 142 | H23: =IF(건축개요!D42>85,I23*(1-$I$15),I23) -> 42765 | I23: =L15 -> 42765 | J23: = 세대당 가격 | K23: =E23*I23 -> 773856.2 | L23: =M23/M$69 -> 0.11720021 | M23: =E23*G23*I23 -> 1.0988758e+08 | V23: =$M23*$S$5*10% -> 7692130.6 | W23: =$M23*$S$6*10% -> 1098875.8 | X23: =$M23*$S$7*10% -> 1098875.8 | Y23: =$M23*$S$8*10% -> 1098875.8 | AB23: =$M23*10% -> 10988758 | AH23: =$M23*10% -> 10988758 | AN23: =$M23*10% -> 10988758 | AT23: =$M23*10% -> 10988758 | AZ23: =$M23*10% -> 10988758 | BF23: =$M23*10% -> 10988758 | BI23: =$M23*30% -> 32966274 | BQ23: =SUM(P23:BP23) -> 1.0988758e+08 | BR23: =$M23 -> 1.0988758e+08 | BS23: =BQ23-BR23 -> 0
D24: B | E24: =건축개요!B43 -> 18.14395 | F24: 평형 | G24: =건축개요!C43 -> 19 | H24: =IF(건축개요!D43>85,I24*(1-$I$15),I24) -> 42765 | I24: =$I$23 -> 42765 | J24: = 세대당 가격 | K24: =E24*I24 -> 775926.02 | L24: =M24/M$69 -> 0.015723662 | M24: =E24*G24*I24 -> 14742594 | V24: =$M24*$S$5*10% -> 1031981.6 | W24: =$M24*$S$6*10% -> 147425.94 | X24: =$M24*$S$7*10% -> 147425.94 | Y24: =$M24*$S$8*10% -> 147425.94 | AB24: =$M24*10% -> 1474259.4 | AH24: =$M24*10% -> 1474259.4 | AN24: =$M24*10% -> 1474259.4 | AT24: =$M24*10% -> 1474259.4 | AZ24: =$M24*10% -> 1474259.4 | BF24: =$M24*10% -> 1474259.4 | BI24: =$M24*30% -> 4422778.3 | BQ24: =SUM(P24:BP24) -> 14742594 | BR24: =$M24 -> 14742594 | BS24: =BQ24-BR24 -> 0
D25: C | E25: =건축개요!B44 -> 18.09555 | F25: 평형 | G25: =건축개요!C44 -> 20 | H25: =IF(건축개요!D44>85,I25*(1-$I$15),I25) -> 42765 | I25: =$I$23 -> 42765 | J25: = 세대당 가격 | K25: =E25*I25 -> 773856.2 | L25: =M25/M$69 -> 0.016507072 | M25: =E25*G25*I25 -> 15477124 | V25: =$M25*$S$5*10% -> 1083398.7 | W25: =$M25*$S$6*10% -> 154771.24 | X25: =$M25*$S$7*10% -> 154771.24 | Y25: =$M25*$S$8*10% -> 154771.24 | AB25: =$M25*10% -> 1547712.4 | AH25: =$M25*10% -> 1547712.4 | AN25: =$M25*10% -> 1547712.4 | AT25: =$M25*10% -> 1547712.4 | AZ25: =$M25*10% -> 1547712.4 | BF25: =$M25*10% -> 1547712.4 | BI25: =$M25*30% -> 4643137.2 | BQ25: =SUM(P25:BP25) -> 15477124 | BR25: =$M25 -> 15477124 | BS25: =BQ25-BR25 -> 0
D26: D | E26: =건축개요!B45 -> 25.69435 | F26: 평형 | G26: =건축개요!C45 -> 88 | H26: =IF(건축개요!D45>85,I26*(1-$I$15),I26) -> 42765 | I26: =$I$23 -> 42765 | J26: = 세대당 가격 | K26: =E26*I26 -> 1098818.9 | L26: =M26/M$69 -> 0.10313084 | M26: =E26*G26*I26 -> 96696061 | V26: =$M26*$S$5*10% -> 6768724.3 | W26: =$M26*$S$6*10% -> 966960.61 | X26: =$M26*$S$7*10% -> 966960.61 | Y26: =$M26*$S$8*10% -> 966960.61 | AB26: =$M26*10% -> 9669606.1 | AH26: =$M26*10% -> 9669606.1 | AN26: =$M26*10% -> 9669606.1 | AT26: =$M26*10% -> 9669606.1 | AZ26: =$M26*10% -> 9669606.1 | BF26: =$M26*10% -> 9669606.1 | BI26: =$M26*30% -> 29008818 | BQ26: =SUM(P26:BP26) -> 96696061 | BR26: =$M26 -> 96696061 | BS26: =BQ26-BR26 -> 0
D27: E | E27: =건축개요!B46 -> 25.6278 | F27: 평형 | G27: =건축개요!C46 -> 70 | H27: =IF(건축개요!D46>85,I27*(1-$I$15),I27) -> 42765 | I27: =$I$23 -> 42765 | J27: = 세대당 가격 | K27: =E27*I27 -> 1095972.9 | L27: =M27/M$69 -> 0.081823418 | M27: =E27*G27*I27 -> 76718101 | V27: =$M27*$S$5*10% -> 5370267 | W27: =$M27*$S$6*10% -> 767181.01 | X27: =$M27*$S$7*10% -> 767181.01 | Y27: =$M27*$S$8*10% -> 767181.01 | AB27: =$M27*10% -> 7671810.1 | AH27: =$M27*10% -> 7671810.1 | AN27: =$M27*10% -> 7671810.1 | AT27: =$M27*10% -> 7671810.1 | AZ27: =$M27*10% -> 7671810.1 | BF27: =$M27*10% -> 7671810.1 | BI27: =$M27*30% -> 23015430 | BQ27: =SUM(P27:BP27) -> 76718101 | BR27: =$M27 -> 76718101 | BS27: =BQ27-BR27 -> 0
D28: F | E28: =건축개요!B47 -> 25.6641 | F28: 평형 | G28: =건축개요!C47 -> 5 | H28: =IF(건축개요!D47>85,I28*(1-$I$15),I28) -> 42765 | I28: =$I$23 -> 42765 | J28: = 세대당 가격 | K28: =E28*I28 -> 1097525.2 | L28: =M28/M$69 -> 0.0058528083 | M28: =E28*G28*I28 -> 5487626.2 | V28: =$M28*$S$5*10% -> 384133.83 | W28: =$M28*$S$6*10% -> 54876.262 | X28: =$M28*$S$7*10% -> 54876.262 | Y28: =$M28*$S$8*10% -> 54876.262 | AB28: =$M28*10% -> 548762.62 | AH28: =$M28*10% -> 548762.62 | AN28: =$M28*10% -> 548762.62 | AT28: =$M28*10% -> 548762.62 | AZ28: =$M28*10% -> 548762.62 | BF28: =$M28*10% -> 548762.62 | BI28: =$M28*30% -> 1646287.9 | BQ28: =SUM(P28:BP28) -> 5487626.2 | BR28: =$M28 -> 5487626.2 | BS28: =BQ28-BR28 -> 0
D29: G | E29: =건축개요!B48 -> 25.68225 | F29: 평형 | G29: =건축개요!C48 -> 109 | H29: =IF(건축개요!D48>85,I29*(1-$I$15),I29) -> 42765 | I29: =$I$23 -> 42765 | J29: = 세대당 가격 | K29: =E29*I29 -> 1098301.4 | L29: =M29/M$69 -> 0.12768145 | M29: =E29*G29*I29 -> 1.1971485e+08 | V29: =$M29*$S$5*10% -> 8380039.8 | W29: =$M29*$S$6*10% -> 1197148.5 | X29: =$M29*$S$7*10% -> 1197148.5 | Y29: =$M29*$S$8*10% -> 1197148.5 | AB29: =$M29*10% -> 11971485 | AH29: =$M29*10% -> 11971485 | AN29: =$M29*10% -> 11971485 | AT29: =$M29*10% -> 11971485 | AZ29: =$M29*10% -> 11971485 | BF29: =$M29*10% -> 11971485 | BI29: =$M29*30% -> 35914456 | BQ29: =SUM(P29:BP29) -> 1.1971485e+08 | BR29: =$M29 -> 1.1971485e+08 | BS29: =BQ29-BR29 -> 0
D30: H | E30: =건축개요!B49 -> 25.697375 | F30: 평형 | G30: =건축개요!C49 -> 45 | H30: =IF(건축개요!D49>85,I30*(1-$I$15),I30) -> 42765 | I30: =$I$23 -> 42765 | J30: = 세대당 가격 | K30: =E30*I30 -> 1098948.2 | L30: =M30/M$69 -> 0.052743571 | M30: =E30*G30*I30 -> 49452671 | V30: =$M30*$S$5*10% -> 3461687 | W30: =$M30*$S$6*10% -> 494526.71 | X30: =$M30*$S$7*10% -> 494526.71 | Y30: =$M30*$S$8*10% -> 494526.71 | AB30: =$M30*10% -> 4945267.1 | AH30: =$M30*10% -> 4945267.1 | AN30: =$M30*10% -> 4945267.1 | AT30: =$M30*10% -> 4945267.1 | AZ30: =$M30*10% -> 4945267.1 | BF30: =$M30*10% -> 4945267.1 | BI30: =$M30*30% -> 14835801 | BQ30: =SUM(P30:BP30) -> 49452671 | BR30: =$M30 -> 49452671 | BS30: =BQ30-BR30 -> 0
D31: I | E31: =건축개요!B50 -> 25.58545 | F31: 평형 | G31: =건축개요!C50 -> 75 | H31: =IF(건축개요!D50>85,I31*(1-$I$15),I31) -> 42765 | I31: =$I$23 -> 42765 | J31: = 세대당 가격 | K31: =E31*I31 -> 1094161.8 | L31: =M31/M$69 -> 0.087523077 | M31: =E31*G31*I31 -> 82062133 | V31: =$M31*$S$5*10% -> 5744349.3 | W31: =$M31*$S$6*10% -> 820621.33 | X31: =$M31*$S$7*10% -> 820621.33 | Y31: =$M31*$S$8*10% -> 820621.33 | AB31: =$M31*10% -> 8206213.3 | AH31: =$M31*10% -> 8206213.3 | AN31: =$M31*10% -> 8206213.3 | AT31: =$M31*10% -> 8206213.3 | AZ31: =$M31*10% -> 8206213.3 | BF31: =$M31*10% -> 8206213.3 | BI31: =$M31*30% -> 24618640 | BQ31: =SUM(P31:BP31) -> 82062133 | BR31: =$M31 -> 82062133 | BS31: =BQ31-BR31 -> 0
D32: J | E32: =건축개요!B51 -> 35.080925 | F32: 평형 | G32: =건축개요!C51 -> 71 | H32: =IF(건축개요!D51>85,I32*(1-$I$15),I32) -> 38488.5 | I32: =$I$23 -> 42765 | J32: = 세대당 가격 | K32: =E32*I32 -> 1500235.8 | L32: =M32/M$69 -> 0.11360505 | M32: =E32*G32*I32 -> 1.0651674e+08 | V32: =$M32*$S$5*10% -> 7456171.7 | W32: =$M32*$S$6*10% -> 1065167.4 | X32: =$M32*$S$7*10% -> 1065167.4 | Y32: =$M32*$S$8*10% -> 1065167.4 | AB32: =$M32*10% -> 10651674 | AH32: =$M32*10% -> 10651674 | AN32: =$M32*10% -> 10651674 | AT32: =$M32*10% -> 10651674 | AZ32: =$M32*10% -> 10651674 | BF32: =$M32*10% -> 10651674 | BI32: =$M32*30% -> 31955022 | BQ32: =SUM(P32:BP32) -> 1.0651674e+08 | BR32: =$M32 -> 1.0651674e+08 | BS32: =BQ32-BR32 -> 0
D33: K | E33: =건축개요!B52 -> 0 | F33: 평형 | G33: =건축개요!C52 -> 0 | H33: =IF(건축개요!D52>85,I33*(1-$I$15),I33) -> 42765 | I33: =$I$23 -> 42765 | J33: = 세대당 가격 | K33: =E33*I33 -> 0 | L33: =M33/M$69 -> 0 | M33: =E33*G33*I33 -> 0 | V33: =$M33*$S$5*10% -> 0 | W33: =$M33*$S$6*10% -> 0 | X33: =$M33*$S$7*10% -> 0 | Y33: =$M33*$S$8*10% -> 0 | AB33: =$M33*10% -> 0 | AH33: =$M33*10% -> 0 | AN33: =$M33*10% -> 0 | AT33: =$M33*10% -> 0 | AZ33: =$M33*10% -> 0 | BF33: =$M33*10% -> 0 | BI33: =$M33*30% -> 0 | BQ33: =SUM(P33:BP33) -> 0 | BR33: =$M33 -> 0 | BS33: =BQ33-BR33 -> 0
D34: L | E34: =건축개요!B53 -> 0 | F34: 평형 | G34: =건축개요!C53 -> 0 | H34: =IF(건축개요!D53>85,I34*(1-$I$15),I34) -> 42765 | I34: =$I$23 -> 42765 | J34: = 세대당 가격 | K34: =E34*I34 -> 0 | L34: =M34/M$69 -> 0 | M34: =E34*G34*I34 -> 0 | V34: =$M34*$S$5*10% -> 0 | W34: =$M34*$S$6*10% -> 0 | X34: =$M34*$S$7*10% -> 0 | Y34: =$M34*$S$8*10% -> 0 | AB34: =$M34*10% -> 0 | AH34: =$M34*10% -> 0 | AN34: =$M34*10% -> 0 | AT34: =$M34*10% -> 0 | AZ34: =$M34*10% -> 0 | BF34: =$M34*10% -> 0 | BI34: =$M34*30% -> 0 | BQ34: =SUM(P34:BP34) -> 0 | BR34: =$M34 -> 0 | BS34: =BQ34-BR34 -> 0
D35: M | E35: =건축개요!B54 -> 0 | F35: 평형 | G35: =건축개요!C54 -> 0 | H35: =IF(건축개요!D54>85,I35*(1-$I$15),I35) -> 42765 | I35: =$I$23 -> 42765 | J35: = 세대당 가격 | K35: =E35*I35 -> 0 | L35: =M35/M$69 -> 0 | M35: =E35*G35*I35 -> 0 | V35: =$M35*$S$5*10% -> 0 | W35: =$M35*$S$6*10% -> 0 | X35: =$M35*$S$7*10% -> 0 | Y35: =$M35*$S$8*10% -> 0 | AB35: =$M35*10% -> 0 | AH35: =$M35*10% -> 0 | AN35: =$M35*10% -> 0 | AT35: =$M35*10% -> 0 | AZ35: =$M35*10% -> 0 | BF35: =$M35*10% -> 0 | BI35: =$M35*30% -> 0 | BQ35: =SUM(P35:BP35) -> 0 | BR35: =$M35 -> 0 | BS35: =BQ35-BR35 -> 0
... D37: O | E37: =건축개요!B56 -> 0 | F37: 평형 | G37: =건축개요!C56 -> 0 | H37: =IF(건축개요!D56>85,I37*(1-$I$15),I37) -> 42765 | I37: =$I$23 -> 42765 | J37: = 세대당 가격 | K37: =E37*I37 -> 0 | L37: =M37/M$69 -> 0 | M37: =E37*G37*I37 -> 0 | V37: =$M37*$S$5*10% -> 0 | W37: =$M37*$S$6*10% -> 0 | X37: =$M37*$S$7*10% -> 0 | Y37: =$M37*$S$8*10% -> 0 | AB37: =$M37*10% -> 0 | AH37: =$M37*10% -> 0 | AN37: =$M37*10% -> 0 | AT37: =$M37*10% -> 0 | AZ37: =$M37*10% -> 0 | BF37: =$M37*10% -> 0 | BI37: =$M37*30% -> 0 | BQ37: =SUM(P37:BP37) -> 0 | BR37: =$M37 -> 0 | BS37: =BQ37-BR37 -> 0
D38: 소 계 | E38: =SUMPRODUCT(E39:E48,G39:G48) -> 14551.433 | G38: =SUM(G39:G48) -> 587 | K38: 시세가의 80% 가정 | L38: =M38/M$69 -> 0.22495094 | M38: =SUM(M39:M48) -> 2.1091527e+08 | O38: 조합분양 | P38: =SUM(P39:P48) -> 21091527 | Q38: =SUM(Q39:Q48) -> 0 | R38: =SUM(R39:R48) -> 0 | S38: =SUM(S39:S48) -> 0 | T38: =SUM(T39:T48) -> 0 | U38: =SUM(U39:U48) -> 0 | V38: =SUM(V39:V48) -> 21091527 | W38: =SUM(W39:W48) -> 0 | ... BP38: =SUM(BP39:BP48) -> 0 | BQ38: =SUM(P38:BP38) -> 2.1091527e+08 | BR38: =+M38 -> 2.1091527e+08 | BS38: =BQ38-BR38 -> 0
C39: 조합분양 | D39: A | E39: =건축개요!B62 -> 18.09555 | F39: 평형 | G39: =건축개요!C62 -> 8 | J39: = 세대당 가격 | K39: =E39*$L$15*0.8 -> 619084.96 | L39: =M39/M$69 -> 0.011948182 | M39: =E39*K39 -> 11202683 | P39: =$M39*10% -> 1120268.3 | V39: =$M39*10% -> 1120268.3 | AB39: =$M39*10% -> 1120268.3 | AH39: =$M39*10% -> 1120268.3 | AN39: =$M39*10% -> 1120268.3 | AT39: =$M39*10% -> 1120268.3 | AZ39: =$M39*10% -> 1120268.3 | BF39: =$M39*10% -> 1120268.3 | BI39: =$M39*20% -> 2240536.6 | BQ39: =SUM(P39:BP39) -> 11202683 | BR39: =$M39 -> 11202683 | BS39: =BQ39-BR39 -> 0
D40: B | E40: =건축개요!B63 -> 18.14395 | F40: 평형 | G40: =건축개요!C63 -> 8 | J40: = 세대당 가격 | K40: =E40*$L$15*0.8 -> 620740.82 | L40: =M40/M$69 -> 0.012012182 | M40: =E40*K40 -> 11262690 | P40: =$M40*10% -> 1126269 | V40: =$M40*10% -> 1126269 | AB40: =$M40*10% -> 1126269 | AH40: =$M40*10% -> 1126269 | AN40: =$M40*10% -> 1126269 | AT40: =$M40*10% -> 1126269 | AZ40: =$M40*10% -> 1126269 | BF40: =$M40*10% -> 1126269 | BI40: =$M40*20% -> 2252538.1 | BQ40: =SUM(P40:BP40) -> 11262690 | BR40: =$M40 -> 11262690 | BS40: =BQ40-BR40 -> 0
D41: C | E41: =건축개요!B64 -> 18.09555 | F41: 평형 | G41: =건축개요!C64 -> 87 | J41: = 세대당 가격 | K41: =E41*$L$15*0.8 -> 619084.96 | L41: =M41/M$69 -> 0.011948182 | M41: =E41*K41 -> 11202683 | P41: =$M41*10% -> 1120268.3 | V41: =$M41*10% -> 1120268.3 | AB41: =$M41*10% -> 1120268.3 | AH41: =$M41*10% -> 1120268.3 | AN41: =$M41*10% -> 1120268.3 | AT41: =$M41*10% -> 1120268.3 | AZ41: =$M41*10% -> 1120268.3 | BF41: =$M41*10% -> 1120268.3 | BI41: =$M41*20% -> 2240536.6 | BQ41: =SUM(P41:BP41) -> 11202683 | BR41: =$M41 -> 11202683 | BS41: =BQ41-BR41 -> 0
D42: D | E42: =건축개요!B65 -> 25.69435 | F42: 평형 | G42: =건축개요!C65 -> 108 | J42: = 세대당 가격 | K42: =E42*$L$15*0.8 -> 879055.1 | L42: =M42/M$69 -> 0.024089818 | M42: =E42*K42 -> 22586749 | P42: =$M42*10% -> 2258674.9 | V42: =$M42*10% -> 2258674.9 | AB42: =$M42*10% -> 2258674.9 | AH42: =$M42*10% -> 2258674.9 | AN42: =$M42*10% -> 2258674.9 | AT42: =$M42*10% -> 2258674.9 | AZ42: =$M42*10% -> 2258674.9 | BF42: =$M42*10% -> 2258674.9 | BI42: =$M42*20% -> 4517349.9 | BQ42: =SUM(P42:BP42) -> 22586749 | BR42: =$M42 -> 22586749 | BS42: =BQ42-BR42 -> 0
D43: E | E43: =건축개요!B66 -> 25.6278 | F43: 평형 | G43: =건축개요!C66 -> 126 | J43: = 세대당 가격 | K43: =E43*$L$15*0.8 -> 876778.29 | L43: =M43/M$69 -> 0.023965191 | M43: =E43*K43 -> 22469899 | P43: =$M43*10% -> 2246989.9 | V43: =$M43*10% -> 2246989.9 | AB43: =$M43*10% -> 2246989.9 | AH43: =$M43*10% -> 2246989.9 | AN43: =$M43*10% -> 2246989.9 | AT43: =$M43*10% -> 2246989.9 | AZ43: =$M43*10% -> 2246989.9 | BF43: =$M43*10% -> 2246989.9 | BI43: =$M43*20% -> 4493979.8 | BQ43: =SUM(P43:BP43) -> 22469899 | BR43: =$M43 -> 22469899 | BS43: =BQ43-BR43 -> 0
D44: F | E44: =건축개요!B67 -> 25.6641 | F44: 평형 | G44: =건축개요!C67 -> 14 | J44: = 세대당 가격 | K44: =E44*$L$15*0.8 -> 878020.19 | L44: =M44/M$69 -> 0.024033129 | M44: =E44*K44 -> 22533598 | P44: =$M44*10% -> 2253359.8 | V44: =$M44*10% -> 2253359.8 | AB44: =$M44*10% -> 2253359.8 | AH44: =$M44*10% -> 2253359.8 | AN44: =$M44*10% -> 2253359.8 | AT44: =$M44*10% -> 2253359.8 | AZ44: =$M44*10% -> 2253359.8 | BF44: =$M44*10% -> 2253359.8 | BI44: =$M44*20% -> 4506719.6 | BQ44: =SUM(P44:BP44) -> 22533598 | BR44: =$M44 -> 22533598 | BS44: =BQ44-BR44 -> 0
D45: G | E45: =건축개요!B68 -> 25.68225 | F45: 평형 | G45: =건축개요!C68 -> 32 | J45: = 세대당 가격 | K45: =E45*$L$15*0.8 -> 878641.14 | L45: =M45/M$69 -> 0.024067134 | M45: =E45*K45 -> 22565481 | P45: =$M45*10% -> 2256548.1 | V45: =$M45*10% -> 2256548.1 | AB45: =$M45*10% -> 2256548.1 | AH45: =$M45*10% -> 2256548.1 | AN45: =$M45*10% -> 2256548.1 | AT45: =$M45*10% -> 2256548.1 | AZ45: =$M45*10% -> 2256548.1 | BF45: =$M45*10% -> 2256548.1 | BI45: =$M45*20% -> 4513096.3 | BQ45: =SUM(P45:BP45) -> 22565481 | BR45: =$M45 -> 22565481 | BS45: =BQ45-BR45 -> 0
D46: H | E46: =건축개요!B69 -> 25.697375 | F46: 평형 | G46: =건축개요!C69 -> 149 | J46: = 세대당 가격 | K46: =E46*$L$15*0.8 -> 879158.59 | L46: =M46/M$69 -> 0.02409549 | M46: =E46*K46 -> 22592068 | P46: =$M46*10% -> 2259206.8 | V46: =$M46*10% -> 2259206.8 | AB46: =$M46*10% -> 2259206.8 | AH46: =$M46*10% -> 2259206.8 | AN46: =$M46*10% -> 2259206.8 | AT46: =$M46*10% -> 2259206.8 | AZ46: =$M46*10% -> 2259206.8 | BF46: =$M46*10% -> 2259206.8 | BI46: =$M46*20% -> 4518413.6 | BQ46: =SUM(P46:BP46) -> 22592068 | BR46: =$M46 -> 22592068 | BS46: =BQ46-BR46 -> 0
D47: I | E47: =건축개요!B70 -> 25.58545 | F47: 평형 | G47: =건축개요!C70 -> 27 | J47: = 세대당 가격 | K47: =E47*$L$15*0.8 -> 875329.42 | L47: =M47/M$69 -> 0.023886051 | M47: =E47*K47 -> 22395697 | P47: =$M47*10% -> 2239569.7 | V47: =$M47*10% -> 2239569.7 | AB47: =$M47*10% -> 2239569.7 | AH47: =$M47*10% -> 2239569.7 | AN47: =$M47*10% -> 2239569.7 | AT47: =$M47*10% -> 2239569.7 | AZ47: =$M47*10% -> 2239569.7 | BF47: =$M47*10% -> 2239569.7 | BI47: =$M47*20% -> 4479139.4 | BQ47: =SUM(P47:BP47) -> 22395697 | BR47: =$M47 -> 22395697 | BS47: =BQ47-BR47 -> 0
D48: J | E48: =건축개요!B71 -> 35.080925 | F48: 평형 | G48: =건축개요!C71 -> 28 | J48: = 세대당 가격 | K48: =E48*$L$15*0.8 -> 1200188.6 | L48: =M48/M$69 -> 0.04490558 | M48: =E48*K48 -> 42103726 | P48: =$M48*10% -> 4210372.6 | V48: =$M48*10% -> 4210372.6 | AB48: =$M48*10% -> 4210372.6 | AH48: =$M48*10% -> 4210372.6 | AN48: =$M48*10% -> 4210372.6 | AT48: =$M48*10% -> 4210372.6 | AZ48: =$M48*10% -> 4210372.6 | BF48: =$M48*10% -> 4210372.6 | BI48: =$M48*20% -> 8420745.3 | BQ48: =SUM(P48:BP48) -> 42103726 | BR48: =$M48 -> 42103726 | BS48: =BQ48-BR48 -> 0
C49: 공공임대 | D49: 소 계 | E49: =SUMPRODUCT(E50:E65,G50:G65) -> 3826.1834 | G49: =SUM(G50:G53) -> 266 | H49: 기본형건축비 입력(m2) | I49: 평당 기본형건축비 | L49: =M49/M$69 -> 0.030163642 | M49: =SUM(M50:M53) -> 28281601 | O49: 임대주택매각 | P49: =SUM(P50:P53) -> 0 | Q49: =SUM(Q50:Q53) -> 0 | R49: =SUM(R50:R53) -> 0 | S49: =SUM(S50:S53) -> 0 | T49: =SUM(T50:T53) -> 14140801 | U49: =SUM(U50:U53) -> 0 | V49: =SUM(V50:V53) -> 0 | W49: =SUM(W50:W53) -> 0 | ... BP49: =SUM(BP50:BP53) -> 0 | BQ49: =SUM(P49:BP49) -> 28281601 | BR49: =+M49 -> 28281601 | BS49: =BQ49-BR49 -> 0
D50: A | E50: =건축개요!B77 -> 11.915475 | F50: 평형 | G50: =건축개요!C77 -> 90 | H50: 2091 | I50: =H50/0.3025 -> 6912.3967 | J50: = 세대당 가격 | K50: =E50*I50 -> 82364.49 | L50: =M50/M$69 -> 0.0079060999 | M50: =E50*G50*I50 -> 7412804.1 | T50: =$M50*50% -> 3706402.1 | BF50: =$M50*30% -> 2223841.2 | BH50: =$M50*20% -> 1482560.8 | BQ50: =SUM(P50:BP50) -> 7412804.1 | BR50: =$M50 -> 7412804.1 | BS50: =BQ50-BR50 -> 0
D51: B | E51: =건축개요!B78 -> 14.88905 | F51: 평형 | G51: =건축개요!C78 -> 106 | H51: 2251 | I51: =H51/0.3025 -> 7441.3223 | J51: = 세대당 가격 | K51: =E51*I51 -> 110794.22 | L51: =M51/M$69 -> 0.012525721 | M51: =E51*G51*I51 -> 11744187 | T51: =$M51*50% -> 5872093.7 | BF51: =$M51*30% -> 3523256.2 | BH51: =$M51*20% -> 2348837.5 | BQ51: =SUM(P51:BP51) -> 11744187 | BR51: =$M51 -> 11744187 | BS51: =BQ51-BR51 -> 0
D52: C | E52: =건축개요!B79 -> 16.4681 | F52: 평형 | G52: =건축개요!C79 -> 56 | H52: 2348 | I52: =H52/0.3025 -> 7761.9835 | J52: = 세대당 가격 | K52: =E52*I52 -> 127825.12 | L52: =M52/M$69 -> 0.00763456 | M52: =E52*G52*I52 -> 7158206.7 | T52: =$M52*50% -> 3579103.4 | BF52: =$M52*30% -> 2147462 | BH52: =$M52*20% -> 1431641.3 | BQ52: =SUM(P52:BP52) -> 7158206.7 | BR52: =$M52 -> 7158206.7 | BS52: =BQ52-BR52 -> 0
D53: D | E53: =건축개요!B80 -> 18.09555 | F53: 평형 | G53: =건축개요!C80 -> 14 | H53: 2348 | I53: =H53/0.3025 -> 7761.9835 | J53: = 세대당 가격 | K53: =E53*I53 -> 140457.36 | L53: =M53/M$69 -> 0.0020972602 | M53: =E53*G53*I53 -> 1966403 | T53: =$M53*50% -> 983201.52 | BF53: =$M53*30% -> 589920.91 | BH53: =$M53*20% -> 393280.61 | BQ53: =SUM(P53:BP53) -> 1966403 | BR53: =$M53 -> 1966403 | BS53: =BQ53-BR53 -> 0
C54: 근생시설 | D54: 소 계 | E54: =SUM(E55:E56) -> 934.3741 | F54: =E54/세금!E151 -> 18.687482 | H54: 부가세 별도 | J54: 부가세 포함 | L54: =M54/M$69 -> 0.038283068 | M54: =SUM(M55:M57) -> 35894422 | O54: 근생시설 | P54: =SUM(P55:P57) -> 0 | Q54: =SUM(Q55:Q57) -> 0 | R54: =SUM(R55:R57) -> 0 | S54: =SUM(S55:S57) -> 0 | T54: =SUM(T55:T57) -> 0 | U54: =SUM(U55:U57) -> 0 | V54: =SUM(V55:V57) -> 0 | W54: =SUM(W55:W57) -> 0 | ... BP54: =SUM(BP55:BP57) -> 0 | BQ54: =SUM(P54:BP54) -> 35894422 | BR54: =+M54 -> 35894422 | BS54: =BQ54-BR54 -> 0
D55: =건축개요!A86 -> 1층 | E55: =건축개요!B86 -> 819.93835 | F55: 평형 | H55: 36020 | I55: 36020 | K55: =H55/(1-$I$15) -> 40022.222 | L55: =M55/M$69 -> 0.031499574 | M55: =E55*I55 -> 29534179 | Y55: =$M55*$T$9*10% -> 1476709 | Z55: =$M55*$T$9*10% -> 1476709 | AI55: =$M55*20%*0.5 -> 2953417.9 | AJ55: =$M55*20%*0.5 -> 2953417.9 | AU55: =$M55*20%*0.5 -> 2953417.9 | AV55: =$M55*20%*0.5 -> 2953417.9 | BI55: =$M55*50%*0.5 -> 7383544.8 | BJ55: =$M55*50%*0.5 -> 7383544.8 | BQ55: =SUM(P55:BP55) -> 29534179 | BR55: =$M55 -> 29534179 | BS55: =BQ55-BR55 -> 0
D56: =건축개요!A87 -> 지하1층 | E56: =건축개요!B87 -> 114.43575 | F56: 평형 | H56: 36020 | I56: 36020 | K56: =H56/(1-$I$15) -> 40022.222 | L56: =M56/M$69 -> 0.0043962786 | M56: =E56*I56 -> 4121975.7 | Y56: =$M56*$T$9*10% -> 206098.79 | Z56: =$M56*$T$9*10% -> 206098.79 | AI56: =$M56*20%*0.5 -> 412197.57 | AJ56: =$M56*20%*0.5 -> 412197.57 | AU56: =$M56*20%*0.5 -> 412197.57 | AV56: =$M56*20%*0.5 -> 412197.57 | BI56: =$M56*50%*0.5 -> 1030493.9 | BJ56: =$M56*50%*0.5 -> 1030493.9 | BQ56: =SUM(P56:BP56) -> 4121975.7 | BR56: =$M56 -> 4121975.7 | BS56: =BQ56-BR56 -> 0
D57: =건축개요!A88 -> 지하2층 | E57: =건축개요!B88 -> 62.13955 | F57: 평형 | H57: 36020 | I57: 36020 | K57: =H57/(1-$I$15) -> 40022.222 | L57: =M57/M$69 -> 0.0023872153 | M57: =E57*I57 -> 2238266.6 | Y57: =$M57*$T$9*10% -> 111913.33 | Z57: =$M57*$T$9*10% -> 111913.33 | AI57: =$M57*20%*0.5 -> 223826.66 | AJ57: =$M57*20%*0.5 -> 223826.66 | AU57: =$M57*20%*0.5 -> 223826.66 | AV57: =$M57*20%*0.5 -> 223826.66 | BI57: =$M57*50%*0.5 -> 559566.65 | BJ57: =$M57*50%*0.5 -> 559566.65 | BQ57: =SUM(P57:BP57) -> 2238266.6 | BR57: =$M57 -> 2238266.6 | BS57: =BQ57-BR57 -> 0
C58: 총 계 (A) | G58: =건축개요!E29 -> 73723.31 | H58: 평 X | I58: =IF(G58=0,"",M58/G58) -> 12911.07 | J58: 천원/평 | L58: =M58/M$69 -> 1.0151888 | M58: =M22+M38+M49+M54 -> 9.5184678e+08 | P58: =P22+P38+P49+P54 -> 21091527 | Q58: =Q22+Q38+Q49+Q54 -> 0 | R58: =R22+R38+R49+R54 -> 0 | S58: =S22+S38+S49+S54 -> 0 | T58: =T22+T38+T49+T54 -> 14140801 | U58: =U22+U38+U49+U54 -> 0 | V58: =V22+V38+V49+V54 -> 68464411 | W58: =W22+W38+W49+W54 -> 6767554.8 | ... BP58: =BP22+BP38+BP49+BP54 -> 0 | BQ58: =SUM(P58:BP58) -> 9.5184678e+08 | BR58: =+M58 -> 9.5184678e+08 | BS58: =BQ58-BR58 -> 0
C59: 부 가 가 치 세 (B) | G59: 주거 | H59: =M22-SUMPRODUCT(E23:E37,G23:G37,H23:H37) -> 10651674 | I59: ＋ | J59: 비주거 | K59: =M54*$I$15 -> 3589442.2 | L59: =M59/M$69 -> 0.015188812 | M59: =H59+K59 -> 14241116 | P59: =IF($G$22=0,P54*$I$15,P22*$H$59/$M$22*$I$15+P54*$I$15) -> 0 | Q59: =IF($G$22=0,Q54*$I$15,Q22*$H$59/$M$22*$I$15+Q54*$I$15) -> 0 | R59: =IF($G$22=0,R54*$I$15,R22*$H$59/$M$22*$I$15+R54*$I$15) -> 0 | S59: =IF($G$22=0,S54*$I$15,S22*$H$59/$M$22*$I$15+S54*$I$15) -> 0 | T59: =IF($G$22=0,T54*$I$15,T22*$H$59/$M$22*$I$15+T54*$I$15) -> 0 | U59: =IF($G$22=0,U54*$I$15,U22*$H$59/$M$22*$I$15+U54*$I$15) -> 0 | V59: =IF($G$22=0,V54*$I$15,V22*$H$59/$M$22+V54*$I$15) -> 745617.17 | W59: =IF($G$22=0,W54*$I$15,W22*$H$59/$M$22+W54*$I$15) -> 106516.74 | X59: =IF($G$22=0,X54*$I$15,X22*$H$59/$M$22+X54*$I$15) -> 106516.74 | Y59: =IF($G$22=0,Y54*$I$15,Y22*$H$59/$M$22+Y54*$I$15) -> 285988.85 | Z59: =IF($G$22=0,Z54*$I$15,Z22*$H$59/$M$22+Z54*$I$15) -> 179472.11 | AA59: =IF($G$22=0,AA54*$I$15,AA22*$H$59/$M$22+AA54*$I$15) -> 0 | AB59: =IF($G$22=0,AB54*$I$15,AB22*$H$59/$M$22+AB54*$I$15) -> 1065167.4 | AC59: =IF($G$22=0,AC54*$I$15,AC22*$H$59/$M$22+AC54*$I$15) -> 0 | ... BP59: =IF($G$22=0,BP54*$I$15,BP22*$H$59/$M$22+BP54*$I$15) -> 0 | BQ59: =SUM(P59:BP59) -> 14241116 | BR59: =+M59 -> 14241116 | BS59: =BQ59-BR59 -> 0
C60: 계 (A - B) | G60: =G10 -> 73723.31 | H60: 평 X | I60: =IF(G60=0,"",M60/G60) -> 12717.9 | J60: 천원/평 | L60: =M60/M$69 -> 1 | M60: =M58-M59 -> 9.3760567e+08 | P60: =P58-P59 -> 21091527 | Q60: =Q58-Q59 -> 0 | R60: =R58-R59 -> 0 | S60: =S58-S59 -> 0 | T60: =T58-T59 -> 14140801 | U60: =U58-U59 -> 0 | V60: =V58-V59 -> 67718794 | W60: =W58-W59 -> 6661038.1 | ... BP60: =BP58-BP59 -> 0 | BQ60: =SUM(P60:BP60) -> 9.3760567e+08 | BR60: =+M60 -> 9.3760567e+08 | BS60: =BQ60-BR60 -> 0
C61: 기타수입 ( C ) | E61: 발코니확장비 | F61: 발코니확장 | H61: 세대 X | I61: 20000 | J61: 천원/세대 | L61: =M61/M$69 -> 0 | M61: =SUM(P61:BP61) -> 0 | AA61: =$G61*$I61*10% -> 0 | BF61: =$G61*$I61*90% -> 0 | BQ61: =SUM(P61:BP61) -> 0 | BR61: =M61 -> 0 | BS61: =BQ61-BR61 -> 0
L62: =M62/M$69 -> 0 | M62: =SUM(P62:BP62) -> 0 | BQ62: =SUM(P62:BP62) -> 0 | BR62: =M62 -> 0 | BS62: =BQ62-BR62 -> 0
L63: =M63/M$69 -> 0 | M63: =SUM(P63:BP63) -> 0 | BQ63: =SUM(P63:BP63) -> 0 | BR63: =M63 -> 0 | BS63: =BQ63-BR63 -> 0
F64: 계 | L64: =M64/M$69 -> 0 | M64: =SUM(M61:M63) -> 0 | P64: =SUM(P61:P63) -> 0 | Q64: =SUM(Q61:Q63) -> 0 | R64: =SUM(R61:R63) -> 0 | S64: =SUM(S61:S63) -> 0 | T64: =SUM(T61:T63) -> 0 | U64: =SUM(U61:U63) -> 0 | V64: =SUM(V61:V63) -> 0 | W64: =SUM(W61:W63) -> 0 | ... BP64: =SUM(BP61:BP63) -> 0 | BQ64: =SUM(P64:BP64) -> 0 | BR64: =M64 -> 0 | BS64: =BQ64-BR64 -> 0
E65: 임대료 | F65: Lease-back | G65: =ROUNDDOWN(G66*I66,-3) -> 0 | H65: 천원 X | I65: 0 | J65: 월 | L65: =M65/M$69 -> 0 | M65: =G65*I65 -> 0 | Q65: =$G65 -> 0 | R65: =Q65 -> 0 | S65: =R65 -> 0 | BQ65: =SUM(P65:BP65) -> 0 | BR65: =M65 -> 0 | BS65: =BQ65-BR65 -> 0
G66: 0 | H66: 평 X | I66: 0 | J66: 천원/평 | L66: =M66/M$69 -> 0 | M66: 0 | BQ66: =SUM(P66:BP66) -> 0 | BR66: =M66 -> 0 | BS66: =BQ66-BR66 -> 0
F67: 계 | M67: =SUM(M65:M66) -> 0 | Q67: =SUM(Q65:Q66) -> 0 | R67: =SUM(R65:R66) -> 0 | S67: =SUM(S65:S66) -> 0 | T67: =SUM(T65:T66) -> 0 | U67: =SUM(U65:U66) -> 0 | V67: =SUM(V65:V66) -> 0 | W67: =SUM(W65:W66) -> 0 | X67: =SUM(X65:X66) -> 0 | ... BP67: =SUM(BP65:BP66) -> 0 | BQ67: =SUM(P67:BP67) -> 0 | BR67: =M67 -> 0 | BS67: =BQ67-BR67 -> 0
L68: =M68/M$69 -> 0 | M68: =SUM(M64:M66) -> 0 | P68: =P64+P67 -> 0 | Q68: =Q64+Q67 -> 0 | R68: =R64+R67 -> 0 | S68: =S64+S67 -> 0 | T68: =T64+T67 -> 0 | U68: =U64+U67 -> 0 | V68: =V64+V67 -> 0 | W68: =W64+W67 -> 0 | ... BP68: =BP64+BP67 -> 0 | BQ68: =SUM(P68:BP68) -> 0 | BR68: =M68 -> 0 | BS68: =BQ68-BR68 -> 0
C69: 총 계 ( A - B + C ) | G69: =G58 -> 73723.31 | H69: 평 | J69: 천원/평 | L69: =M69/M$69 -> 1 | M69: =M60+M68 -> 9.3760567e+08 | P69: =P60+P68 -> 21091527 | Q69: =Q60+Q68 -> 0 | R69: =R60+R68 -> 0 | S69: =S60+S68 -> 0 | T69: =T60+T68 -> 14140801 | U69: =U60+U68 -> 0 | V69: =V60+V68 -> 67718794 | W69: =W60+W68 -> 6661038.1 | ... BP69: =BP60+BP68 -> 0 | BQ69: =SUM(P69:BP69) -> 9.3760567e+08 | BR69: =+M69 -> 9.3760567e+08 | BS69: =BQ69-BR69 -> 0
B70: 지 출 | C70: 토 지 비 | E70: 부지매입비 | G70: =G6 -> 18350.8 | H70: 평 X | I70: =I4 -> 0 | J70: 천원/평 | L70: =M70/$M$69 -> 0 | M70: =$G70*I70 -> 0 | P70: =$M70*10% -> 0 | S70: =$M$70-SUM($P70:R70) -> 0 | BQ70: =SUM(P70:BP70) -> 0 | BR70: =M70 -> 0 | BS70: =BQ70-BR70 -> 0
E71: 취득세 / 등록세 | G71: =M70 -> 0 | H71: X | I71: =4.6% -> 0.046 | J71: 1 | L71: =M71/$M$69 -> 0 | M71: =G71*I71*J71 -> 0 | S71: =$M71 -> 0 | BQ71: =SUM(P71:BP71) -> 0 | BR71: =M71 -> 0 | BS71: =BQ71-BR71 -> 0
E72: 채 권 매 각 손 | G72: =토지조서!G661 -> 3.1341122e+08 | H72: X | I72: 0.11 | J72: X | K72: 0.031 | L72: =M72/$M$69 -> 0 | M72: =0 -> 0 | S72: =$M$72 -> 0 | BQ72: =SUM(P72:BP72) -> 0 | BR72: =M72 -> 0 | BS72: =BQ72-BR72 -> 0
E73: 법무사비용, 등기수수료 등 | G73: 법무사 수수료, 등기신청비용, 인지대 등 | L73: =M73/$M$69 -> 0 | M73: =ROUNDDOWN(토지조서!H38,-3) -> 0 | S73: =$M$73 -> 0 | BQ73: =SUM(P73:BP73) -> 0 | BR73: =M73 -> 0 | BS73: =BQ73-BR73 -> 0
E74: 소 계 | L74: =M74/$M$69 -> 0 | M74: =SUM(M70:M73) -> 0 | P74: =SUM(P70:P73) -> 0 | Q74: =SUM(Q70:Q73) -> 0 | R74: =SUM(R70:R73) -> 0 | S74: =SUM(S70:S73) -> 0 | T74: =SUM(T70:T73) -> 0 | U74: =SUM(U70:U73) -> 0 | V74: =SUM(V70:V73) -> 0 | W74: =SUM(W70:W73) -> 0 | ... BP74: =SUM(BP70:BP73) -> 0 | BQ74: =SUM(P74:BP74) -> 0 | BR74: =SUM(BR70:BR73) -> 0 | BS74: =BQ74-BR74 -> 0
C75: 공 사 비 | E75: 건 축 공 사 비 | G75: =$G$10 -> 73723.31 | H75: 평 X | I75: =$L$9 -> 7000 | J75: 천원/평 | L75: =M75/$M$69 -> 0.55040534 | M75: =G75*I75 -> 5.1606317e+08 | W75: =$M75/20 -> 25803158 | Y75: =$M75/20 -> 25803158 | AA75: =$M75/20 -> 25803158 | AC75: =$M75/20 -> 25803158 | AE75: =$M75/20 -> 25803158 | AG75: =$M75/20 -> 25803158 | AI75: =$M75/20 -> 25803158 | AK75: =$M75/20 -> 25803158 | AM75: =$M75/20 -> 25803158 | AO75: =$M75/20 -> 25803158 | AQ75: =$M75/20 -> 25803158 | AS75: =$M75/20 -> 25803158 | AU75: =$M75/20 -> 25803158 | AW75: =$M75/20 -> 25803158 | AY75: =$M75/20 -> 25803158 | BA75: =$M75/20 -> 25803158 | BC75: =$M75/20 -> 25803158 | BE75: =$M75/20 -> 25803158 | BG75: =$M75/20 -> 25803158 | BI75: =$M75/20 -> 25803158 | BQ75: =SUM(P75:BP75) -> 5.1606317e+08 | BR75: =M75 -> 5.1606317e+08 | BS75: =BQ75-BR75 -> 0
E76: 기타공사비 | G76: =$G$75 -> 73723.31 | H76: 평 X | I76: 800 | J76: 천원/평 | K76: 0 | L76: =M76/$M$69 -> 0.062903468 | M76: =G76*I76 -> 58978648 | AP76: =$M76*30% -> 17693594 | AS76: =$M76*70% -> 41285053 | BQ76: =SUM(P76:BP76) -> 58978648 | BR76: =M76 -> 58978648 | BS76: =BQ76-BR76 -> 0
E77: 인 입 분 담 금 | G77: =$G$75 -> 73723.31 | H77: 평 X | I77: 30 | J77: 천원/평 | L77: =M77/$M$69 -> 0.00235888 | M77: =G77*I77 -> 2211699.3 | AD77: =$M77 -> 2211699.3 | BF77: `` | BQ77: =SUM(P77:BP77) -> 2211699.3 | BR77: =M77 -> 2211699.3 | BS77: =BQ77-BR77 -> 0
E78: 기반시설공사비 | G78: =$G$75 -> 73723.31 | H78: 평 X | I78: 300 | J78: 천원/평 | L78: =M78/$M$69 -> 0.0235888 | M78: =G78*I78 -> 22116993 | U78: =$M78*20% -> 4423398.6 | V78: =$M78*80% -> 17693594 | BQ78: =SUM(P78:BP78) -> 22116993 | BR78: =M78 -> 22116993 | BS78: =BQ78-BR78 -> 0
E79: 미술장식품설치비 | G79: =E11 -> 155753.45 | H79: ㎡ X | I79: 3 | J79: 천원/㎡ | L79: =M79/$M$69 -> 0.00049835487 | M79: =G79*I79 -> 467260.35 | T79: =$M$79*10% -> 46726.035 | AQ79: =+$M$79*30% -> 140178.11 | BF79: =$M$79*60% -> 280356.21 | BQ79: =SUM(P79:BP79) -> 467260.35 | BR79: =M79 -> 467260.35 | BS79: =BQ79-BR79 -> 0
E80: 철거/부지조성공사비 | G80: =G6 -> 18350.8 | H80: 평 X | I80: 1000 | J80: 천원/평 | L80: =M80/$M$69 -> 0.01957198 | M80: =G80*I80 -> 18350800 | T80: =$M$80/2 -> 9175399.8 | V80: =$M$80/2 -> 9175399.8 | BQ80: =SUM(P80:BP80) -> 18350800 | BR80: =M80 -> 18350800 | BS80: =BQ80-BR80 -> 0
E81: 소 계 | L81: =M81/$M$69 -> 0.65932683 | M81: =SUM(M75:M80) -> 6.1818857e+08 | Q81: =SUM(Q75:Q80) -> 0 | R81: =SUM(R75:R80) -> 0 | S81: =SUM(S75:S80) -> 0 | T81: =SUM(T75:T80) -> 9222125.8 | U81: =SUM(U75:U80) -> 4423398.6 | V81: =SUM(V75:V80) -> 26868994 | W81: =SUM(W75:W80) -> 25803158 | X81: =SUM(X75:X80) -> 0 | ... BP81: =SUM(BP75:BP80) -> 0 | BQ81: =SUM(P81:BP81) -> 6.1818857e+08 | BR81: =M81 -> 6.1818857e+08 | BS81: =BQ81-BR81 -> 0
C82: 용 역 비 | E82: 건축설계비 | G82: =+G75 -> 73723.31 | H82: 평 X | I82: 100 | J82: 천원/평 | L82: =M82/$M$69 -> 0.0078629335 | M82: =G82*I82 -> 7372331 | P82: =$M82*20% -> 1474466.2 | R82: =$M82*20% -> 1474466.2 | T82: =$M82*20% -> 1474466.2 | V82: =$M82*10% -> 737233.1 | AH82: =$M82*10% -> 737233.1 | AT82: =$M82*10% -> 737233.1 | BH82: =$M82*10% -> 737233.1 | BQ82: =SUM(P82:BP82) -> 7372331 | BR82: =M82 -> 7372331 | BS82: =BQ82-BR82 -> 0
E83: 기타 설계비(현상 설계비 포함) | G83: =$G$82 -> 73723.31 | H83: 평 X | I83: 25 | J83: 천원/평 | L83: =M83/$M$69 -> 0.0019657334 | M83: =G83*I83 -> 1843082.7 | P83: =$M83*10% -> 184308.27 | R83: =$M83*50% -> 921541.37 | S83: =$M83*40% -> 737233.1 | BQ83: =SUM(P83:BP83) -> 1843082.7 | BR83: =M83 -> 1843082.7 | BS83: =BQ83-BR83 -> 0
E84: 기타 용역비 | G84: =$G$82 -> 73723.31 | H84: 평 X | I84: =30 -> 30 | J84: 천원/평 | L84: =M84/$M$69 -> 0.00058715941 | M84: =G6*I84 -> 550523.98 | Q84: =$M84*20% -> 110104.8 | R84: =$M84*20% -> 110104.8 | S84: =$M84-SUM($P84:R84) -> 330314.39 | BQ84: =SUM(P84:BP84) -> 550523.98 | BR84: =M84 -> 550523.98 | BS84: =BQ84-BR84 -> 0
E85: 환경영향평가 | G85: =$G$82 -> 73723.31 | H85: 평 X | I85: =5 -> 5 | J85: 천원/평 | L85: =M85/$M$69 -> 9.7859901e-05 | M85: =G6*I85 -> 91753.997 | Q85: =$M85*10% -> 9175.3998 | T85: =$M85*90% -> 82578.598 | BQ85: =SUM(P85:BP85) -> 91753.997 | BR85: =M85 -> 91753.997 | BS85: =BQ85-BR85 -> 0
E86: 건 축 감 리 비 | F86: CM | G86: =M81 -> 6.1818857e+08 | H86: 건축공사비 X | J86: 감리비요율 (1%) | L86: =M86/$M$69 -> 0.0065932683 | M86: =M81*1% -> 6181885.7 | U86: =$M$86*10% -> 618188.57 | Y86: =$M$86*10% -> 618188.57 | AC86: =$M$86*10% -> 618188.57 | AG86: =$M$86*10% -> 618188.57 | AK86: =$M$86*10% -> 618188.57 | AO86: =$M$86*10% -> 618188.57 | AS86: =$M$86*10% -> 618188.57 | AW86: =$M$86*10% -> 618188.57 | BA86: =$M$86*10% -> 618188.57 | BE86: =$M$86*10% -> 618188.57 | BQ86: =SUM(P86:BP86) -> 6181885.7 | BR86: =M86 -> 6181885.7 | BS86: =BQ86-BR86 -> 0
E87: PM용역비 | F87: Development Fee | G87: =M81 -> 6.1818857e+08 | H87: 건축공사비 X | J87: 0.03 | L87: =M87/$M$69 -> 0.019779805 | M87: =M81*J87 -> 18545657 | S87: =M87/($L$8-4) -> 421492.2 | T87: =S87 -> 421492.2 | U87: =T87 -> 421492.2 | V87: =U87 -> 421492.2 | W87: =V87 -> 421492.2 | X87: =W87 -> 421492.2 | Y87: =X87 -> 421492.2 | Z87: =Y87 -> 421492.2 | AA87: =Z87 -> 421492.2 | ... BJ87: =BI87 -> 421492.2 | BQ87: =SUM(P87:BP87) -> 18545657 | BR87: =M87 -> 18545657 | BS87: =BQ87-BR87 -> 0
F88: 기타 용역비 | H88: 개월 X | I88: 0 | J88: 천원/평 | L88: =M88/$M$69 -> 0 | M88: =($M$75+$M$80)*K88 -> 0 | BQ88: =SUM(P88:BP88) -> 0 | BR88: =M88 -> 0 | BS88: =BQ88-BR88 -> 0
F89: 별도 용역비 | H89: 개월 X | I89: 0 | J89: 천원/평 | L89: =M89/$M$69 -> 0 | M89: =($M$75+$M$80)*K89 -> 0 | BQ89: =SUM(P89:BP89) -> 0 | BR89: =M89 -> 0 | BS89: =BQ89-BR89 -> 0
E90: 소 계 | L90: =M90/$M$69 -> 0.036886759 | M90: =SUM(M82:M89) -> 34585234 | P90: =SUM(P82:P89) -> 1658774.5 | Q90: =SUM(Q82:Q89) -> 119280.2 | R90: =SUM(R82:R89) -> 2506112.4 | S90: =SUM(S82:S89) -> 1489039.7 | T90: =SUM(T82:T89) -> 1978537 | U90: =SUM(U82:U89) -> 1039680.8 | V90: =SUM(V82:V89) -> 1158725.3 | W90: =SUM(W82:W89) -> 421492.2 | ... BP90: =SUM(BP82:BP89) -> 0 | BQ90: =SUM(P90:BP90) -> 34585234 | BR90: =M90 -> 34585234 | BS90: =BQ90-BR90 -> 0
C91: 판 매 비 | D91: M / H 홍 보 관 | E91: 부 지 임 차 료 | G91: 150000 | H91: 천원 X | I91: 12 | J91: 월 | L91: =M91/$M$69 -> 0.0019197836 | M91: =G91*I91 -> 1800000 | T91: =$G91 -> 150000 | U91: =T91 -> 150000 | V91: =U91 -> 150000 | W91: =V91 -> 150000 | X91: =W91 -> 150000 | Y91: =X91 -> 150000 | Z91: =Y91 -> 150000 | AA91: =Z91 -> 150000 | AB91: =AA91 -> 150000 | ... AE91: =AD91 -> 150000 | BQ91: =SUM(P91:BP91) -> 1800000 | BR91: =M91 -> 1800000 | BS91: =BQ91-BR91 -> 0
E92: 중개수수료 등 제비용 | L92: =M92/$M$69 -> 0.00015998197 | M92: =G91 -> 150000 | T92: =$M92*100% -> 150000 | BQ92: =SUM(P92:BP92) -> 150000 | BR92: =M92 -> 150000 | BS92: =BQ92-BR92 -> 0
E93: 공 사 비 | G93: 50 | H93: 평 X | I93: 4500 | J93: 천원/평 | L93: =M93/$M$69 -> 0.00023997295 | M93: =G93*I93 -> 225000 | T93: =$M93*30% -> 67500 | U93: =$M93*30% -> 67500 | V93: =$M93*40% -> 90000 | BQ93: =SUM(P93:BP93) -> 225000 | BR93: =M93 -> 225000 | BS93: =BQ93-BR93 -> 0
E94: 기 타 | J94: 0 | K94: =I94*J94 -> 0 | L94: =M94/$M$69 -> 0 | M94: 0 | AG94: =$M94*30% -> 0 | AI94: =$M94*30% -> 0 | AK94: =$M94*40% -> 0 | BQ94: =SUM(P94:BP94) -> 0 | BR94: =M94 -> 0 | BS94: =BQ94-BR94 -> 0
E95: 소 계 | L95: =M95/$M$69 -> 0.0023197385 | M95: =SUM(M91:M94) -> 2175000 | Q95: =SUM(Q91:Q94) -> 0 | R95: =SUM(R91:R94) -> 0 | S95: =SUM(S91:S94) -> 0 | T95: =SUM(T91:T94) -> 367500 | U95: =SUM(U91:U94) -> 217500 | V95: =SUM(V91:V94) -> 240000 | W95: =SUM(W91:W94) -> 150000 | X95: =SUM(X91:X94) -> 150000 | ... BP95: =SUM(BP91:BP94) -> 0 | BQ95: =SUM(P95:BP95) -> 2175000 | BR95: =M95 -> 2175000 | BS95: =BQ95-BR95 -> 0
D96: 광고홍보비 | E96: 광 고 비 | G96: 신문, 잡지, 전단 등 매체광고 | L96: =M96/$M$69 -> 0.0063992787 | M96: =6000000 -> 6000000 | T96: =$M96*10% -> 600000 | U96: =$M96*50% -> 3000000 | V96: =$M96*40% -> 2400000 | BQ96: =SUM(P96:BP96) -> 6000000 | BR96: =M96 -> 6000000 | BS96: =BQ96-BR96 -> 0
E97: 제 작 비 | G97: 광고/인쇄물, 조형물, 판촉물 등 | L97: =M97/$M$69 -> 0.0010665465 | M97: =1000000 -> 1000000 | T97: =$M97*10% -> 100000 | U97: =$M97*50% -> 500000 | V97: =$M97*40% -> 400000 | BQ97: =SUM(P97:BP97) -> 1000000 | BR97: =M97 -> 1000000 | BS97: =BQ97-BR97 -> 0
E98: 기 타 | G98: 전시 모형 등 | L98: =M98/$M$69 -> 8.5323717e-05 | M98: 80000 | T98: =$M$98*50% -> 40000 | U98: =$M$98*50% -> 40000 | BQ98: =SUM(P98:BP98) -> 80000 | BR98: =M98 -> 80000 | BS98: =BQ98-BR98 -> 0
E99: 소 계 | L99: =M99/$M$69 -> 0.0075511489 | M99: =SUM(M96:M98) -> 7080000 | Q99: =SUM(Q96:Q98) -> 0 | R99: =SUM(R96:R98) -> 0 | S99: =SUM(S96:S98) -> 0 | T99: =SUM(T96:T98) -> 740000 | U99: =SUM(U96:U98) -> 3540000 | V99: =SUM(V96:V98) -> 2800000 | W99: =SUM(W96:W98) -> 0 | X99: =SUM(X96:X98) -> 0 | ... BP99: =SUM(BP96:BP98) -> 0 | BQ99: =SUM(P99:BP99) -> 7080000 | BR99: =M99 -> 7080000 | BS99: =BQ99-BR99 -> 0
D100: 영업비 | E100: M/H 오픈비용 | G100: =G93 -> 50 | H100: 평 X | I100: =M100/G100 -> 0 | J100: 천원/평 | L100: =M100/$M$69 -> 0 | M100: 0 | V100: =$M100*50% -> 0 | W100: =$M100*50% -> 0 | BQ100: =SUM(P100:BP100) -> 0 | BR100: =M100 -> 0 | BS100: =BQ100-BR100 -> 0
E101: M/H 운영비용 | G101: 12 | H101: 개월 X | I101: 20000 | J101: 천원/월 | L101: =M101/$M$69 -> 0.00025597115 | M101: =G101*I101 -> 240000 | T101: =$I101 -> 20000 | U101: =T101 -> 20000 | V101: =U101 -> 20000 | W101: =V101 -> 20000 | X101: =W101 -> 20000 | Y101: =X101 -> 20000 | Z101: =Y101 -> 20000 | AA101: =Z101 -> 20000 | AB101: =AA101 -> 20000 | ... AE101: =AD101 -> 20000 | BQ101: =SUM(P101:BP101) -> 240000 | BR101: =M101 -> 240000 | BS101: =BQ101-BR101 -> 0
E102: 분양대행수수료 | F102: =C22 -> 일반분양 | G102: =G22 -> 644 | H102: 세대 X | I102: 10000 | J102: 천원/세대 | K102: 0.01 | L102: =M102/$M$69 -> 0.0068685592 | M102: =G102*I102 -> 6440000 | P102: =P22*$K$102 -> 0 | Q102: =Q22*$K$102 -> 0 | R102: =R22*$K$102 -> 0 | S102: =S22*$K$102 -> 0 | T102: =T22*$K$102 -> 0 | U102: =U22*$K$102 -> 0 | V102: =$M$102*$S$5 -> 4508000 | W102: =$M$102*$S$6 -> 644000 | X102: =$M$102*$S$7 -> 644000 | Y102: =$M$102*$S$8 -> 644000 | Z102: =$M$102*$S$9 -> 0 | BQ102: =SUM(P102:BP102) -> 6440000 | BR102: =M102 -> 6440000 | BS102: =BQ102-BR102 -> 0
...

Sheet 개발-운영
B2: =사업검토!B2 -> 사 업 명 | I2: 작성일자 : | J2: =사업검토!L14 -> 7
I3: 출력일자 : | J3: =+TODAY() -> 45993
B4: ■ CASH-FLOW
Q5: (단위 : 평, 천원)
B6: 구 분 | E6: 계 | F6: Y+0 | G6: 1 | H6: =G6+1 -> 2 | I6: =H6+1 -> 3 | J6: =I6+1 -> 4 | K6: =J6+1 -> 5 | L6: =K6+1 -> 6 | M6: =L6+1 -> 7 | N6: =M6+1 -> 8 | O6: =N6+1 -> 9 | Q6: 비 고
F7: 개 발
F8: 39661 | G8: =F8+31 -> 39692 | H8: =G8+365.25 -> 40057.25 | I8: =H8+365.25 -> 40422.5 | J8: =I8+365.25 -> 40787.75 | K8: =J8+365.25 -> 41153 | L8: =K8+365.25 -> 41518.25 | M8: =L8+365.25 -> 41883.5 | N8: =M8+365.25 -> 42248.75 | O8: =N8+365.25 -> 42614
G9: =G8+364 -> 40056 | H9: =H8+364 -> 40421.25 | I9: =I8+364 -> 40786.5 | J9: =J8+364 -> 41151.75 | K9: =K8+364 -> 41517 | L9: =L8+364 -> 41882.25 | M9: =M8+364 -> 42247.5 | N9: =N8+364 -> 42612.75 | O9: =O8+364 -> 42978
B10: 매출 (A) | C10: =사업검토!#REF! -> #REF! | E10: =SUM(F10:M10) -> #REF! | F10: =SUM(사업검토!#REF!) -> #REF! | G10: =SUM(사업검토!#REF!) -> #REF! | H10: =SUM(사업검토!#REF!) -> #REF! | I10: =SUM(사업검토!#REF!) -> #REF! | J10: =SUM(사업검토!#REF!) -> #REF!
C11: =사업검토!#REF! -> #REF! | E11: =SUM(F11:M11) -> #REF! | F11: =SUM(사업검토!#REF!) -> #REF! | G11: =SUM(사업검토!#REF!) -> #REF! | H11: =SUM(사업검토!#REF!) -> #REF! | I11: =SUM(사업검토!#REF!) -> #REF! | J11: =SUM(사업검토!#REF!) -> #REF!
C12: =사업검토!C22 -> 일반분양 | E12: =SUM(F12:M12) -> #REF! | F12: =SUM(사업검토!AD22) -> 0 | G12: =SUM(사업검토!AE22:AR22) -> 1.353511e+08 | H12: =SUM(사업검토!AS22:BD22) -> 1.353511e+08 | I12: =SUM(사업검토!BE22:BP22) -> 2.7070219e+08 | J12: =SUM(사업검토!#REF!) -> #REF!
C13: =사업검토!C54 -> 근생시설 | E13: =SUM(F13:M13) -> #REF! | F13: =SUM(사업검토!AD54) -> 0 | G13: =SUM(사업검토!AE54:AR54) -> 7178884.3 | H13: =SUM(사업검토!AS54:BD54) -> 7178884.3 | I13: =SUM(사업검토!BE54:BP54) -> 17947211 | J13: =SUM(사업검토!#REF!) -> #REF!
C14: =사업검토!#REF! -> #REF! | E14: =SUM(F14:M14) -> #REF! | F14: =SUM(사업검토!#REF!) -> #REF! | G14: =SUM(사업검토!#REF!) -> #REF! | H14: =SUM(사업검토!#REF!) -> #REF! | I14: =SUM(사업검토!#REF!) -> #REF! | J14: =SUM(사업검토!#REF!) -> #REF!
C15: =사업검토!#REF! -> #REF! | E15: =SUM(F15:M15) -> #REF! | F15: =SUM(사업검토!#REF!) -> #REF! | G15: =SUM(사업검토!#REF!) -> #REF! | H15: =SUM(사업검토!#REF!) -> #REF! | I15: =SUM(사업검토!#REF!) -> #REF! | J15: =SUM(사업검토!#REF!) -> #REF!
C16: 소 계 | E16: =SUM(F16:M16) -> #REF! | F16: =SUM(사업검토!AD58) -> 0 | G16: =SUM(사업검토!AE58:AR58) -> 1.8471304e+08 | H16: =SUM(사업검토!AS58:BD58) -> 1.8471304e+08 | I16: =SUM(사업검토!BE58:BP58) -> 3.6606479e+08 | J16: =SUM(사업검토!#REF!) -> #REF!
B17: 부가가치세 (B) | E17: =SUM(F17:M17) -> #REF! | F17: =SUM(사업검토!AD59) -> 0 | G17: =SUM(사업검토!AE59:AR59) -> 2848223.2 | H17: =SUM(사업검토!AS59:BD59) -> 2848223.2 | I17: =SUM(사업검토!BE59:BP59) -> 6055390.6 | J17: =SUM(사업검토!#REF!) -> #REF!
B18: 기타 수입 (C) | E18: =SUM(F18:M18) -> 0 | F18: 0 | G18: 0 | H18: 0 | I18: 0 | J18: 0
B19: 총 계 (A-B+C) | E19: =SUM(F19:M19) -> #REF! | F19: =F16-F17+F18 -> 0 | G19: =G16-G17+G18 -> 1.8186481e+08 | H19: =H16-H17+H18 -> 1.8186481e+08 | I19: =I16-I17+I18 -> 3.600094e+08 | J19: =J16-J17+J18 -> #REF!
B20: 개발 원가 | C20: 토지비 | E20: =SUM(F20:M20) -> #REF! | F20: =-SUM(사업검토!AD74) -> 0 | G20: =-SUM(사업검토!AE74:AR74) -> 0 | H20: =-SUM(사업검토!AS74:BD74) -> 0 | I20: =-SUM(사업검토!BE74:BP74) -> 0 | J20: =-SUM(사업검토!#REF!) -> #REF! | Q20: 취등록세, 등기수수료 등 포함
C21: 공사비 | E21: =SUM(F21:M21) -> #REF! | F21: =-SUM(사업검토!AD81) -> -2211699.3 | G21: =-SUM(사업검토!AE81:AR81) -> -1.9845588e+08 | H21: =-SUM(사업검토!AS81:BD81) -> -1.96104e+08 | I21: =-SUM(사업검토!BE81:BP81) -> -77689831 | J21: =-SUM(사업검토!#REF!) -> #REF!
C22: 용역비 | E22: =SUM(F22:M22) -> #REF! | F22: =-SUM(사업검토!AD90) -> -421492.2 | G22: =-SUM(사업검토!AE90:AR90) -> -8492689.7 | H22: =-SUM(사업검토!AS90:BD90) -> -7649705.2 | I22: =-SUM(사업검토!BE90:BP90) -> -3884374.9 | J22: =-SUM(사업검토!#REF!) -> #REF!
C23: 판매비 | E23: =SUM(F23:M23) -> #REF! | F23: =-SUM(사업검토!AD107) -> -170000 | G23: =-SUM(사업검토!AE107:AR107) -> -600733.06 | H23: =-SUM(사업검토!AS107:BD107) -> -430733.06 | I23: =-SUM(사업검토!BE107:BP107) -> -1076832.7 | J23: =-SUM(사업검토!#REF!) -> #REF!
C24: 간접경비 및 이자 | E24: =SUM(F24:M24) -> #REF! | F24: =-SUM(사업검토!AD125) -> -532730.49 | G24: =-SUM(사업검토!AE125:AR125) -> -7458226.9 | H24: =-SUM(사업검토!AS125:BD125) -> -25880837 | I24: =-SUM(사업검토!BE125:BP125) -> -3196382.9 | J24: =-SUM(사업검토!#REF!) -> #REF!
C25: 예비비 | E25: =SUM(F25:N25) -> #REF! | F25: =-SUM(사업검토!AD126) -> 0 | G25: =-SUM(사업검토!AE126:AR126) -> -10000000 | H25: =-SUM(사업검토!AS126:BD126) -> 0 | I25: =-SUM(사업검토!BE126:BP126) -> 0 | J25: =-SUM(사업검토!#REF!) -> #REF!
C26: 소 계 | E26: =SUM(F26:N26) -> #REF! | F26: =-SUM(사업검토!AD153) -> -3335922 | G26: =-SUM(사업검토!AE153:AR153) -> -2.2500753e+08 | H26: =-SUM(사업검토!AS153:BD153) -> -2.3006528e+08 | I26: =-SUM(사업검토!BE153:BP153) -> -85847422 | J26: =-SUM(사업검토!#REF!) -> #REF!
C27: 금융비용 | E27: =SUM(F27:N27) -> #REF! | F27: =SUM(사업검토!AD142) -> 1969567.4 | G27: =SUM(사업검토!AE142:AR142) -> 23607291 | H27: =SUM(사업검토!AS142:BD142) -> 13757550 | I27: =SUM(사업검토!BE142:BP142) -> 3181786.6 | J27: =-SUM(사업검토!#REF!) -> #REF!
C28: 일반관리비 | E28: =SUM(F28:N28) -> #REF! | F28: =-SUM(사업검토!#REF!) -> #REF! | G28: =-SUM(사업검토!#REF!) -> #REF! | H28: =-SUM(사업검토!#REF!) -> #REF! | I28: =-SUM(사업검토!#REF!) -> #REF! | J28: =-SUM(사업검토!#REF!) -> #REF!
C29: 총 계 | E29: =E26+E27+E28 -> #REF! | F29: =F26+F27+F28 -> #REF! | G29: =G26+G27+G28 -> #REF! | H29: =H26+H27+H28 -> #REF! | I29: =I26+I27+I28 -> #REF! | J29: =J26+J27+J28 -> #REF!
B30: Loan | C30: 대출 | D30: 토지비 | E30: =SUM(F30:N30) -> #REF! | F30: =SUM(사업검토!#REF!) -> #REF! | G30: =SUM(사업검토!#REF!) -> #REF! | H30: =SUM(사업검토!#REF!) -> #REF! | I30: =SUM(사업검토!#REF!) -> #REF! | J30: =SUM(사업검토!#REF!) -> #REF! | Q30: 토지비 대출
D31: 사업비 | E31: =SUM(F31:N31) -> #REF! | F31: =SUM(사업검토!#REF!) -> #REF! | G31: =SUM(사업검토!#REF!) -> #REF! | H31: =SUM(사업검토!#REF!) -> #REF! | I31: =SUM(사업검토!#REF!) -> #REF! | J31: =SUM(사업검토!#REF!) -> #REF! | Q31: 공사비 및 기타 사업비 대출
D32: 소 계 | E32: =SUM(F32:N32) -> #REF! | F32: =F30+F31 -> #REF! | G32: =G30+G31 -> #REF! | H32: =H30+H31 -> #REF! | I32: =I30+I31 -> #REF! | J32: =J30+J31 -> #REF!
C33: 이자 대출 | D33: 토지비 이자 | E33: =SUM(F33:N33) -> #REF! | F33: =SUM(사업검토!#REF!) -> #REF! | G33: =SUM(사업검토!#REF!) -> #REF! | H33: =SUM(사업검토!#REF!) -> #REF! | I33: =SUM(사업검토!#REF!) -> #REF! | J33: =SUM(사업검토!#REF!) -> #REF!
D34: 사업비 이자 | E34: =SUM(F34:N34) -> #REF! | F34: =SUM(사업검토!#REF!) -> #REF! | G34: =SUM(사업검토!#REF!) -> #REF! | H34: =SUM(사업검토!#REF!) -> #REF! | I34: =SUM(사업검토!#REF!) -> #REF! | J34: =SUM(사업검토!#REF!) -> #REF!
D35: 소 계 | E35: =SUM(F35:N35) -> #REF! | F35: =F33+F34 -> #REF! | G35: =G33+G34 -> #REF! | H35: =H33+H34 -> #REF! | I35: =I33+I34 -> #REF! | J35: =J33+J34 -> #REF!
C36: 상환 | E36: =SUM(F36:N36) -> #REF! | F36: =SUM(사업검토!#REF!) -> #REF! | G36: =SUM(사업검토!#REF!) -> #REF! | H36: =SUM(사업검토!#REF!) -> #REF! | I36: =SUM(사업검토!#REF!) -> #REF!
B37: 자기자본 조달 | E37: =SUM(F37:N37) -> #REF! | F37: =SUM(사업검토!#REF!) -> #REF! | G37: =SUM(사업검토!#REF!) -> #REF! | H37: =SUM(사업검토!#REF!) -> #REF! | I37: =SUM(사업검토!#REF!) -> #REF! | J37: =SUM(사업검토!#REF!) -> #REF!
B38: CASH FLOW | E38: =SUM(F38:N38) -> #REF! | F38: =SUM(사업검토!AD146) -> -5305489.4 | G38: =SUM(사업검토!AE146:AR146) -> -66750009 | H38: =SUM(사업검토!AS146:BD146) -> -61958016 | I38: =SUM(사업검토!BE146:BP146) -> 2.7098019e+08 | J38: =SUM(사업검토!#REF!) -> #REF!
B40: IRR | E40: =IRR(F38:N38) -> #VALUE!
B42: ■ 민감도 분석
B44: 1) 매각가 | I44: 2) 공사비
B46: 매입가격(천원) | E46: 매각가 | I46: 매입가격(천원) | L46: 공사비
B47: =$E$40 -> #VALUE! | C47: =D47-500 -> 10000 | D47: =E47-500 -> 10500 | E47: 11000 | F47: =E47+500 -> 11500 | G47: =F47+500 -> 12000 | I47: =$E$40 -> #VALUE! | J47: =K47-500 -> 4000 | K47: =L47-500 -> 4500 | L47: 5000 | M47: =L47+500 -> 5500 | N47: =M47+500 -> 6000
B48: =B49-1000000 -> 15000000 | I48: =I49-1000000 -> 15000000
B49: =B50-1000000 -> 16000000 | I49: =I50-1000000 -> 16000000
B50: 17000000 | I50: 17000000
B51: =B50+1000000 -> 18000000 | I51: =I50+1000000 -> 18000000
B52: =B51+1000000 -> 19000000 | I52: =I51+1000000 -> 19000000
B54: ■ 운영 CASH-FLOW
B55: 1) 분석의 전제
B57: 총면적 | C57: 임료인상율 | D57: 공실율 | E57: 관리비용 | F57: 기타수입(월) | G57: 기타비용 | H57: Cap rate | I57: 전환율 | J57: 대출이자 | K57: 보증금이자
B58: =#REF! -> #REF! | C58: 0.05 | D58: 0.03 | E58: 0.7 | F58: 10000 | G58: 0.3 | H58: 0.05 | I58: 0.12 | J58: 0.065 | K58: 0.053
Q61: (단위 : 부가세별도, 평, 천원)
B62: 구 분 | F62: Y+0 | G62: 1 | H62: =G62+1 -> 2 | I62: =H62+1 -> 3 | J62: =I62+1 -> 4 | K62: =J62+1 -> 5 | L62: =K62+1 -> 6 | M62: =L62+1 -> 7 | N62: =M62+1 -> 8 | O62: =N62+1 -> 9 | Q62: 비 고
F63: 개 발 | I63: 운 영
F64: 39661 | G64: =F64+31 -> 39692 | H64: =G64+365.25 -> 40057.25 | I64: =H64+365.25 -> 40422.5 | J64: =I64+365.25 -> 40787.75 | K64: =J64+365.25 -> 41153 | L64: =K64+365.25 -> 41518.25 | M64: =L64+365.25 -> 41883.5 | N64: =M64+365.25 -> 42248.75 | O64: =N64+365.25 -> 42614
G65: =G64+364 -> 40056 | H65: =H64+364 -> 40421.25 | I65: =I64+364 -> 40786.5 | J65: =J64+364 -> 41151.75 | K65: =K64+364 -> 41517 | L65: =L64+364 -> 41882.25 | M65: =M64+364 -> 42247.5 | N65: =N64+364 -> 42612.75 | O65: =O64+364 -> 42978
B66: 보증금 | C66: 업무시설 | E66: =#REF! -> #REF! | F66: =F76*10 -> 650 | G66: =F66*(1+$C$58) -> 682.5 | H66: =G66*(1+$C$58) -> 716.625 | I66: =H66*(1+$C$58) -> 752.45625 | J66: =I66*(1+$C$58) -> 790.07906 | K66: =J66*(1+$C$58) -> 829.58302 | L66: =K66*(1+$C$58) -> 871.06217 | M66: =L66*(1+$C$58) -> 914.61527 | N66: =M66*(1+$C$58) -> 960.34604 | O66: =N66*(1+$C$58) -> 1008.3633
C67: 상 가 | D67: =#REF! -> #REF! | E67: =#REF! -> #REF!
D68: =#REF! -> #REF! | E68: =#REF! -> #REF!
D69: =#REF! -> #REF! | E69: =#REF! -> #REF!
D70: =#REF! -> #REF! | E70: =#REF! -> #REF!
D71: =#REF! -> #REF! | E71: =#REF! -> #REF! | F71: =F81*10 -> 1500 | G71: =F71*(1+$C$58) -> 1575 | H71: =G71*(1+$C$58) -> 1653.75 | I71: =H71*(1+$C$58) -> 1736.4375 | J71: =I71*(1+$C$58) -> 1823.2594 | K71: =J71*(1+$C$58) -> 1914.4223 | L71: =K71*(1+$C$58) -> 2010.1435 | M71: =L71*(1+$C$58) -> 2110.6506 | N71: =M71*(1+$C$58) -> 2216.1832 | O71: =N71*(1+$C$58) -> 2326.9923
D72: =#REF! -> #REF! | E72: =#REF! -> #REF! | F72: =F82*10 -> 500 | G72: =F72*(1+$C$58) -> 525 | H72: =G72*(1+$C$58) -> 551.25 | I72: =H72*(1+$C$58) -> 578.8125 | J72: =I72*(1+$C$58) -> 607.75313 | K72: =J72*(1+$C$58) -> 638.14078 | L72: =K72*(1+$C$58) -> 670.04782 | M72: =L72*(1+$C$58) -> 703.55021 | N72: =M72*(1+$C$58) -> 738.72772 | O72: =N72*(1+$C$58) -> 775.66411
D73: =#REF! -> #REF! | E73: =#REF! -> #REF!
D74: =#REF! -> #REF! | E74: =#REF! -> #REF!
C75: 소 계 | F75: =SUMPRODUCT($E66:$E74,F66:F74) -> #REF! | G75: =SUMPRODUCT($E66:$E74,G66:G74) -> #REF! | H75: =SUMPRODUCT($E66:$E74,H66:H74) -> #REF! | I75: =SUMPRODUCT($E66:$E74,I66:I74) -> #REF! | J75: =SUMPRODUCT($E66:$E74,J66:J74) -> #REF! | K75: =SUMPRODUCT($E66:$E74,K66:K74) -> #REF! | L75: =SUMPRODUCT($E66:$E74,L66:L74) -> #REF! | M75: =SUMPRODUCT($E66:$E74,M66:M74) -> #REF! | ... O75: =SUMPRODUCT($E66:$E74,O66:O74) -> #REF!
B76: 임대료(월) | C76: 업무시설 | E76: =E66 -> #REF! | F76: 65 | G76: =F76*(1+$C$58) -> 68.25 | H76: =G76*(1+$C$58) -> 71.6625 | I76: =H76*(1+$C$58) -> 75.245625 | J76: =I76*(1+$C$58) -> 79.007906 | K76: =J76*(1+$C$58) -> 82.958302 | L76: =K76*(1+$C$58) -> 87.106217 | M76: =L76*(1+$C$58) -> 91.461527 | N76: =M76*(1+$C$58) -> 96.034604 | O76: =N76*(1+$C$58) -> 100.83633
C77: 상 가 | D77: =D67 -> #REF! | E77: =E67 -> #REF!
D78: =D68 -> #REF! | E78: =E68 -> #REF!
D79: =D69 -> #REF! | E79: =E69 -> #REF!
D80: =D70 -> #REF! | E80: =E70 -> #REF!
D81: =D71 -> #REF! | E81: =E71 -> #REF! | F81: 150 | G81: =F81*(1+$C$58) -> 157.5 | H81: =G81*(1+$C$58) -> 165.375 | I81: =H81*(1+$C$58) -> 173.64375 | J81: =I81*(1+$C$58) -> 182.32594 | K81: =J81*(1+$C$58) -> 191.44223 | L81: =K81*(1+$C$58) -> 201.01435 | M81: =L81*(1+$C$58) -> 211.06506 | N81: =M81*(1+$C$58) -> 221.61832 | O81: =N81*(1+$C$58) -> 232.69923
D82: =D72 -> #REF! | E82: =E72 -> #REF! | F82: 50 | G82: =F82*(1+$C$58) -> 52.5 | H82: =G82*(1+$C$58) -> 55.125 | I82: =H82*(1+$C$58) -> 57.88125 | J82: =I82*(1+$C$58) -> 60.775313 | K82: =J82*(1+$C$58) -> 63.814078 | L82: =K82*(1+$C$58) -> 67.004782 | M82: =L82*(1+$C$58) -> 70.355021 | N82: =M82*(1+$C$58) -> 73.872772 | O82: =N82*(1+$C$58) -> 77.566411
D83: =D73 -> #REF! | E83: =E73 -> #REF!
D84: =D74 -> #REF! | E84: =E74 -> #REF!
C85: 소 계 | F85: =SUMPRODUCT($E76:$E84,F76:F84) -> #REF! | G85: =SUMPRODUCT($E76:$E84,G76:G84) -> #REF! | H85: =SUMPRODUCT($E76:$E84,H76:H84) -> #REF! | I85: =SUMPRODUCT($E76:$E84,I76:I84) -> #REF! | J85: =SUMPRODUCT($E76:$E84,J76:J84) -> #REF! | K85: =SUMPRODUCT($E76:$E84,K76:K84) -> #REF! | L85: =SUMPRODUCT($E76:$E84,L76:L84) -> #REF! | M85: =SUMPRODUCT($E76:$E84,M76:M84) -> #REF! | ... O85: =SUMPRODUCT($E76:$E84,O76:O84) -> #REF!
B86: 관리비(월) | C86: 업무시설 | E86: =E76 -> #REF! | F86: 27 | G86: =F86*(1+$C$58) -> 28.35 | H86: =G86*(1+$C$58) -> 29.7675 | I86: =H86*(1+$C$58) -> 31.255875 | J86: =I86*(1+$C$58) -> 32.818669 | K86: =J86*(1+$C$58) -> 34.459602 | L86: =K86*(1+$C$58) -> 36.182582 | M86: =L86*(1+$C$58) -> 37.991711 | N86: =M86*(1+$C$58) -> 39.891297 | O86: =N86*(1+$C$58) -> 41.885862
C87: 상 가 | E87: =SUM(E77:E84) -> #REF! | F87: 15 | G87: =F87*(1+$C$58) -> 15.75 | H87: =G87*(1+$C$58) -> 16.5375 | I87: =H87*(1+$C$58) -> 17.364375 | J87: =I87*(1+$C$58) -> 18.232594 | K87: =J87*(1+$C$58) -> 19.144223 | L87: =K87*(1+$C$58) -> 20.101435 | M87: =L87*(1+$C$58) -> 21.106506 | N87: =M87*(1+$C$58) -> 22.161832 | O87: =N87*(1+$C$58) -> 23.269923
C88: 소 계 | F88: =SUMPRODUCT($E86:$E87,F86:F87) -> #REF! | G88: =SUMPRODUCT($E86:$E87,G86:G87) -> #REF! | H88: =SUMPRODUCT($E86:$E87,H86:H87) -> #REF! | I88: =SUMPRODUCT($E86:$E87,I86:I87) -> #REF! | J88: =SUMPRODUCT($E86:$E87,J86:J87) -> #REF! | K88: =SUMPRODUCT($E86:$E87,K86:K87) -> #REF! | L88: =SUMPRODUCT($E86:$E87,L86:L87) -> #REF! | M88: =SUMPRODUCT($E86:$E87,M86:M87) -> #REF! | ... O88: =SUMPRODUCT($E86:$E87,O86:O87) -> #REF!
B89: 전세 환산가 | C89: 업무시설 | E89: =E66 -> #REF! | F89: =F76*12/$I$58+F66 -> 7150 | G89: =F89*(1+$C$58) -> 7507.5 | H89: =G89*(1+$C$58) -> 7882.875 | I89: =H89*(1+$C$58) -> 8277.0188 | J89: =I89*(1+$C$58) -> 8690.8697 | K89: =J89*(1+$C$58) -> 9125.4132 | L89: =K89*(1+$C$58) -> 9581.6838 | M89: =L89*(1+$C$58) -> 10060.768 | N89: =M89*(1+$C$58) -> 10563.806 | O89: =N89*(1+$C$58) -> 11091.997
C90: 상 가 | D90: =D67 -> #REF! | E90: =E67 -> #REF! | F90: =F77*12/$I$58+F67 -> 0 | G90: =F90*(1+$C$58) -> 0 | H90: =G90*(1+$C$58) -> 0 | I90: =H90*(1+$C$58) -> 0 | J90: =I90*(1+$C$58) -> 0 | K90: =J90*(1+$C$58) -> 0 | L90: =K90*(1+$C$58) -> 0 | M90: =L90*(1+$C$58) -> 0 | N90: =M90*(1+$C$58) -> 0 | O90: =N90*(1+$C$58) -> 0
D91: =D68 -> #REF! | E91: =E68 -> #REF! | F91: =F78*12/$I$58+F68 -> 0 | G91: =F91*(1+$C$58) -> 0 | H91: =G91*(1+$C$58) -> 0 | I91: =H91*(1+$C$58) -> 0 | J91: =I91*(1+$C$58) -> 0 | K91: =J91*(1+$C$58) -> 0 | L91: =K91*(1+$C$58) -> 0 | M91: =L91*(1+$C$58) -> 0 | N91: =M91*(1+$C$58) -> 0 | O91: =N91*(1+$C$58) -> 0
D92: =D69 -> #REF! | E92: =E69 -> #REF! | F92: =F79*12/$I$58+F69 -> 0 | G92: =F92*(1+$C$58) -> 0 | H92: =G92*(1+$C$58) -> 0 | I92: =H92*(1+$C$58) -> 0 | J92: =I92*(1+$C$58) -> 0 | K92: =J92*(1+$C$58) -> 0 | L92: =K92*(1+$C$58) -> 0 | M92: =L92*(1+$C$58) -> 0 | N92: =M92*(1+$C$58) -> 0 | O92: =N92*(1+$C$58) -> 0
D93: =D70 -> #REF! | E93: =E70 -> #REF! | F93: =F80*12/$I$58+F70 -> 0 | G93: =F93*(1+$C$58) -> 0 | H93: =G93*(1+$C$58) -> 0 | I93: =H93*(1+$C$58) -> 0 | J93: =I93*(1+$C$58) -> 0 | K93: =J93*(1+$C$58) -> 0 | L93: =K93*(1+$C$58) -> 0 | M93: =L93*(1+$C$58) -> 0 | N93: =M93*(1+$C$58) -> 0 | O93: =N93*(1+$C$58) -> 0
D94: =D71 -> #REF! | E94: =E71 -> #REF! | F94: =F81*12/$I$58+F71 -> 16500 | G94: =F94*(1+$C$58) -> 17325 | H94: =G94*(1+$C$58) -> 18191.25 | I94: =H94*(1+$C$58) -> 19100.812 | J94: =I94*(1+$C$58) -> 20055.853 | K94: =J94*(1+$C$58) -> 21058.646 | L94: =K94*(1+$C$58) -> 22111.578 | M94: =L94*(1+$C$58) -> 23217.157 | N94: =M94*(1+$C$58) -> 24378.015 | O94: =N94*(1+$C$58) -> 25596.916
D95: =D72 -> #REF! | E95: =E72 -> #REF! | F95: =F82*12/$I$58+F72 -> 5500 | G95: =F95*(1+$C$58) -> 5775 | H95: =G95*(1+$C$58) -> 6063.75 | I95: =H95*(1+$C$58) -> 6366.9375 | J95: =I95*(1+$C$58) -> 6685.2844 | K95: =J95*(1+$C$58) -> 7019.5486 | L95: =K95*(1+$C$58) -> 7370.526 | M95: =L95*(1+$C$58) -> 7739.0523 | N95: =M95*(1+$C$58) -> 8126.0049 | O95: =N95*(1+$C$58) -> 8532.3052
D96: =D73 -> #REF! | E96: =E73 -> #REF! | F96: =F83*12/$I$58+F73 -> 0 | G96: =F96*(1+$C$58) -> 0 | H96: =G96*(1+$C$58) -> 0 | I96: =H96*(1+$C$58) -> 0 | J96: =I96*(1+$C$58) -> 0 | K96: =J96*(1+$C$58) -> 0 | L96: =K96*(1+$C$58) -> 0 | M96: =L96*(1+$C$58) -> 0 | N96: =M96*(1+$C$58) -> 0 | O96: =N96*(1+$C$58) -> 0
D97: =D74 -> #REF! | E97: =E74 -> #REF! | F97: =F84*12/$I$58+F74 -> 0 | G97: =F97*(1+$C$58) -> 0 | H97: =G97*(1+$C$58) -> 0 | I97: =H97*(1+$C$58) -> 0 | J97: =I97*(1+$C$58) -> 0 | K97: =J97*(1+$C$58) -> 0 | L97: =K97*(1+$C$58) -> 0 | M97: =L97*(1+$C$58) -> 0 | N97: =M97*(1+$C$58) -> 0 | O97: =N97*(1+$C$58) -> 0
C98: 소 계 | F98: =SUMPRODUCT($E89:$E97,F89:F97) -> #REF! | G98: =SUMPRODUCT($E89:$E97,G89:G97) -> #REF! | H98: =SUMPRODUCT($E89:$E97,H89:H97) -> #REF! | I98: =SUMPRODUCT($E89:$E97,I89:I97) -> #REF! | J98: =SUMPRODUCT($E89:$E97,J89:J97) -> #REF! | K98: =SUMPRODUCT($E89:$E97,K89:K97) -> #REF! | L98: =SUMPRODUCT($E89:$E97,L89:L97) -> #REF! | M98: =SUMPRODUCT($E89:$E97,M89:M97) -> #REF! | ... O98: =SUMPRODUCT($E89:$E97,O89:O97) -> #REF!
B100: 운용 기간 (월수) | H100: 0 | I100: 1 | J100: 12 | K100: =J100 -> 12 | L100: =K100 -> 12 | M100: =L100 -> 12 | N100: =M100 -> 12 | O100: =N100 -> 12
B101: 임대 수익(년) | C101: 업무시설 | E101: =E66 -> #REF! | H101: =$E101*H$100 -> #REF! | I101: =$E101*I$100 -> #REF! | J101: =$E101*J$100 -> #REF! | K101: =$E101*K$100 -> #REF! | L101: =$E101*L$100 -> #REF! | M101: =$E101*M$100 -> #REF! | N101: =$E101*N$100 -> #REF! | O101: =$E101*O$100 -> #REF!
C102: 상가 | D102: =D67 -> #REF! | E102: =E67 -> #REF! | H102: =$E102*H$100 -> #REF! | I102: =$E102*I$100 -> #REF! | J102: =$E102*J$100 -> #REF! | K102: =$E102*K$100 -> #REF! | L102: =$E102*L$100 -> #REF! | M102: =$E102*M$100 -> #REF! | N102: =$E102*N$100 -> #REF! | O102: =$E102*O$100 -> #REF!
D103: =D68 -> #REF! | E103: =E68 -> #REF! | H103: =$E103*H$100 -> #REF! | I103: =$E103*I$100 -> #REF! | J103: =$E103*J$100 -> #REF! | K103: =$E103*K$100 -> #REF! | L103: =$E103*L$100 -> #REF! | M103: =$E103*M$100 -> #REF! | N103: =$E103*N$100 -> #REF! | O103: =$E103*O$100 -> #REF!
D104: =D69 -> #REF! | E104: =E69 -> #REF! | H104: =$E104*H$100 -> #REF! | I104: =$E104*I$100 -> #REF! | J104: =$E104*J$100 -> #REF! | K104: =$E104*K$100 -> #REF! | L104: =$E104*L$100 -> #REF! | M104: =$E104*M$100 -> #REF! | N104: =$E104*N$100 -> #REF! | O104: =$E104*O$100 -> #REF!
D105: =D70 -> #REF! | E105: =E70 -> #REF! | H105: =$E105*H$100 -> #REF! | I105: =$E105*I$100 -> #REF! | J105: =$E105*J$100 -> #REF! | K105: =$E105*K$100 -> #REF! | L105: =$E105*L$100 -> #REF! | M105: =$E105*M$100 -> #REF! | N105: =$E105*N$100 -> #REF! | O105: =$E105*O$100 -> #REF!
D106: =D71 -> #REF! | E106: =E71 -> #REF! | H106: =$E106*H$100 -> #REF! | I106: =$E106*I$100 -> #REF! | J106: =$E106*J$100 -> #REF! | K106: =$E106*K$100 -> #REF! | L106: =$E106*L$100 -> #REF! | M106: =$E106*M$100 -> #REF! | N106: =$E106*N$100 -> #REF! | O106: =$E106*O$100 -> #REF!
D107: =D72 -> #REF! | E107: =E72 -> #REF! | H107: =$E107*H$100 -> #REF! | I107: =$E107*I$100 -> #REF! | J107: =$E107*J$100 -> #REF! | K107: =$E107*K$100 -> #REF! | L107: =$E107*L$100 -> #REF! | M107: =$E107*M$100 -> #REF! | N107: =$E107*N$100 -> #REF! | O107: =$E107*O$100 -> #REF!
D108: =D73 -> #REF! | E108: =E73 -> #REF! | H108: =$E108*H$100 -> #REF! | I108: =$E108*I$100 -> #REF! | J108: =$E108*J$100 -> #REF! | K108: =$E108*K$100 -> #REF! | L108: =$E108*L$100 -> #REF! | M108: =$E108*M$100 -> #REF! | N108: =$E108*N$100 -> #REF! | O108: =$E108*O$100 -> #REF!
D109: =D74 -> #REF! | E109: =E74 -> #REF! | H109: =$E109*H$100 -> #REF! | I109: =$E109*I$100 -> #REF! | J109: =$E109*J$100 -> #REF! | K109: =$E109*K$100 -> #REF! | L109: =$E109*L$100 -> #REF! | M109: =$E109*M$100 -> #REF! | N109: =$E109*N$100 -> #REF! | O109: =$E109*O$100 -> #REF!
C110: 소 계 | E110: =SUM(E101:E109) -> #REF! | H110: =SUM(H101:H109) -> #REF! | I110: =SUM(I101:I109) -> #REF! | J110: =SUM(J101:J109) -> #REF! | K110: =SUM(K101:K109) -> #REF! | L110: =SUM(L101:L109) -> #REF! | M110: =SUM(M101:M109) -> #REF! | N110: =SUM(N101:N109) -> #REF! | O110: =SUM(O101:O109) -> #REF!
...

Sheet English
B1: ■ CASH-FLOW
Q2: (㎡, KRW1,000)
E3: Total | F3: Y+0 | G3: 1 | H3: =G3+1 -> 2 | I3: =H3+1 -> 3 | J3: =I3+1 -> 4 | K3: =J3+1 -> 5 | L3: =K3+1 -> 6 | M3: =L3+1 -> 7 | N3: =M3+1 -> 8 | O3: =N3+1 -> 9 | Q3: Remark
F4: Development | J4: Operation
F5: 39661 | G5: =F5+31 -> 39692 | H5: =G5+365.25 -> 40057.25 | I5: =H5+365.25 -> 40422.5 | J5: =I5+365.25 -> 40787.75 | K5: =J5+365.25 -> 41153 | L5: =K5+365.25 -> 41518.25 | M5: =L5+365.25 -> 41883.5 | N5: =M5+365.25 -> 42248.75 | O5: =N5+365.25 -> 42614
G6: =G5+364 -> 40056 | H6: =H5+364 -> 40421.25 | I6: =I5+364 -> 40786.5 | J6: =J5+364 -> 41151.75 | K6: =K5+364 -> 41517 | L6: =L5+364 -> 41882.25 | M6: =M5+364 -> 42247.5 | N6: =N5+364 -> 42612.75 | O6: =O5+364 -> 42978
B7: Revenue (A) | C7: =사업검토!#REF! -> #REF! | E7: =SUM(F7:M7) -> #REF! | F7: =SUM(사업검토!#REF!) -> #REF! | G7: =SUM(사업검토!#REF!) -> #REF! | H7: =SUM(사업검토!#REF!) -> #REF! | I7: =SUM(사업검토!#REF!) -> #REF! | J7: =SUM(사업검토!#REF!) -> #REF!
C8: =사업검토!#REF! -> #REF! | E8: =SUM(F8:M8) -> #REF! | F8: =SUM(사업검토!#REF!) -> #REF! | G8: =SUM(사업검토!#REF!) -> #REF! | H8: =SUM(사업검토!#REF!) -> #REF! | I8: =SUM(사업검토!#REF!) -> #REF! | J8: =SUM(사업검토!#REF!) -> #REF!
C9: Office | E9: 2.1572021e+08 | F9: 0 | G9: 0 | H9: 0 | I9: 2.1572021e+08 | J9: 0
C10: Retail | E10: 43200911 | F10: 0 | G10: 0 | H10: 0 | I10: 43200911 | J10: 0
C11: =사업검토!#REF! -> #REF! | E11: 0 | F11: 0 | G11: 0 | H11: 0 | I11: 0 | J11: 0
C12: =사업검토!#REF! -> #REF! | E12: 0 | F12: 0 | G12: 0 | H12: 0 | I12: 0 | J12: 0
C13: Sub Total | E13: 2.5892112e+08 | F13: 0 | G13: 0 | H13: 0 | I13: 2.5892112e+08 | J13: 0
B14: VAT (B) | E14: 12946056 | F14: 0 | G14: 0 | H14: 0 | I14: 12946056 | J14: 0
B15: Other Revenue (C) | E15: 0 | F15: 0 | G15: 0 | H15: 0 | I15: 0 | J15: 0
B16: Total (A-B+C) | E16: 2.4597507e+08 | F16: 0 | G16: 0 | H16: 0 | I16: 2.4597507e+08 | J16: 0
B17: Cost | C17: Land | E17: -1.2430759e+08 | F17: -9636122.1 | G17: -1.1467147e+08 | H17: 0 | I17: 0 | J17: 0 | Q17: Acquisition Cost, Appraisal, Broker Fee
C18: Construction Hard Cost | E18: -52413867 | F18: 0 | G18: -6390637.3 | H18: -23204511 | I18: -22818719 | J18: 0 | Q18: Demolition
C19: Construction Soft Cost | E19: -2200829.6 | F19: -129460.56 | G19: -1359335.9 | H19: -291286.26 | I19: -420746.83 | J19: 0 | Q19: A&E
C20: Selling Expense | E20: -2459750.7 | F20: 0 | G20: 0 | H20: 0 | I20: -2459750.7 | J20: 0
C21: Others & Interest on Loan | E21: -36520221 | F21: -2702.7027 | G21: -11100428 | H21: -9820607.6 | I21: -15596483 | J21: 0 | Q21: Interest, Tax. Others
C22: Contingency | E22: -1000000 | F22: -27027.027 | G22: -324324.32 | H22: -324324.32 | I22: -324324.32 | J22: 0
C23: Sub Total | E23: -2.1890226e+08 | F23: -9795312.4 | G23: -1.3384619e+08 | H23: -33640729 | I23: -41620023 | J23: 0
C24: Gap Financing | E24: -7146350.7 | F24: -30610.351 | G24: -1358269 | H24: -2365453.3 | I24: -3392018.1 | J24: 0
C25: Operating Expense | E25: -3689626 | F25: -99719.622 | G25: -1196635.5 | H25: -1196635.5 | I25: -1196635.5 | J25: 0
C26: Total | E26: -2.2973824e+08 | F26: -9925642.3 | G26: -1.364011e+08 | H26: -37202818 | I26: -46208677 | J26: 0
B27: Loan | C27: Loan | D27: Land | E27: 1.0328388e+08 | F27: 0 | G27: 1.0328388e+08 | H27: 0 | I27: 0 | J27: 0
D28: Financing | E28: 52218533 | F28: 0 | G28: 16203520 | H28: 17670384 | I28: 18344629 | J28: 0
D29: Sub Total | E29: 1.5550241e+08 | F29: 0 | G29: 1.194874e+08 | H29: 17670384 | I29: 18344629 | J29: 0
C30: Interest Payment | D30: Land | E30: 0 | F30: 0 | G30: 0 | H30: 0 | I30: 0 | J30: 0
D31: Financing | E31: 0 | F31: 0 | G31: 0 | H31: 0 | I31: 0 | J31: 0
D32: Sub Total | E32: 0 | F32: 0 | G32: 0 | H32: 0 | I32: 0 | J32: 0
C33: Repayment | E33: -1.5550241e+08 | F33: 0 | G33: 0 | H33: 0 | I33: -1.5550241e+08
B34: Equity | E34: -67578576 | F34: -9925642.3 | G34: -16913700 | H34: -19532434 | I34: -21206799 | J34: 0
B35: CASH FLOW | E35: 16236832 | F35: -9925642.3 | G35: -16913700 | H35: -19532434 | I35: 62608609 | J35: 0
B37: IRR | E37: =IRR(F35:N35) -> 0.17703792
B39: ■ 민감도 분석
B41: 1) 매각가 | I41: 2) 공사비
B43: 매입가격(천원) | E43: 매각가 | I43: 매입가격(천원) | L43: 공사비
B44: =$E$37 -> 0.17703792 | C44: =D44-500 -> 10000 | D44: =E44-500 -> 10500 | E44: 11000 | F44: =E44+500 -> 11500 | G44: =F44+500 -> 12000 | I44: =$E$37 -> 0.17703792 | J44: =K44-500 -> 4000 | K44: =L44-500 -> 4500 | L44: 5000 | M44: =L44+500 -> 5500 | N44: =M44+500 -> 6000
B45: =B46-1000000 -> 15000000 | I45: =I46-1000000 -> 15000000
B46: =B47-1000000 -> 16000000 | I46: =I47-1000000 -> 16000000
B47: 17000000 | I47: 17000000 | T47: 1) Assumptions
B48: =B47+1000000 -> 18000000 | I48: =I47+1000000 -> 18000000
B49: =B48+1000000 -> 19000000 | I49: =I48+1000000 -> 19000000 | T49: GFA | U49: Structure | V49: Escalation | W49: Vacancy | X49: Cap rate
T50: =$B$55/0.3025 -> #REF! | U50: B7, 20F | V50: 0.05 | W50: 0.03 | X50: 0.05 | AA50: (㎡, KRW1,000)
B51: ■ 운영 CASH-FLOW | T51: Office Monthly Rent (㎡) | U51: Y+0 | V51: 1 | W51: =V51+1 -> 2 | X51: =W51+1 -> 3 | Y51: =X51+1 -> 4 | Z51: NOI (Expected) | AA51: Asset Price (Expected)
B52: 1) 분석의 전제 | U52: 20 | V52: =U52*(1+$V$50) -> 21 | W52: =V52*(1+$V$50) -> 22.05 | X52: =W52*(1+$V$50) -> 23.1525 | Y52: =X52*(1+$V$50) -> 24.310125 | Z52: 8250000 | AA52: =Z52/X50 -> 165000000
B54: 총면적 | C54: 임료인상율 | D54: 공실율 | E54: 관리비용 | F54: 기타수입(월) | G54: 기타비용 | H54: Cap rate | I54: 전환율 | J54: 대출이자 | K54: 보증금이자 | Z54: =Y52*T50*12 -> #REF!
B55: =#REF! -> #REF! | C55: 0.05 | D55: 0.03 | E55: 0.7 | F55: 10000 | G55: 0.3 | H55: 0.05 | I55: 0.12 | J55: 0.065 | K55: 0.053
Q58: (단위 : 부가세별도, 평, 천원)
E59: Total | F59: Y+0 | G59: 1 | H59: =G59+1 -> 2 | I59: =H59+1 -> 3 | J59: =I59+1 -> 4 | K59: =J59+1 -> 5 | L59: =K59+1 -> 6 | M59: =L59+1 -> 7 | N59: =M59+1 -> 8 | O59: =N59+1 -> 9 | Q59: 비 고
F60: Development | J60: Operation
F61: 39661 | G61: =F61+31 -> 39692 | H61: =G61+365.25 -> 40057.25 | I61: =H61+365.25 -> 40422.5 | J61: =I61+365.25 -> 40787.75 | K61: =J61+365.25 -> 41153 | L61: =K61+365.25 -> 41518.25 | M61: =L61+365.25 -> 41883.5 | N61: =M61+365.25 -> 42248.75 | O61: =N61+365.25 -> 42614
G62: =G61+364 -> 40056 | H62: =H61+364 -> 40421.25 | I62: =I61+364 -> 40786.5 | J62: =J61+364 -> 41151.75 | K62: =K61+364 -> 41517 | L62: =L61+364 -> 41882.25 | M62: =M61+364 -> 42247.5 | N62: =N61+364 -> 42612.75 | O62: =O61+364 -> 42978
B63: 보증금 | C63: 업무시설 | E63: =#REF! -> #REF! | F63: =F73*10 -> 650 | G63: =F63*(1+$C$55) -> 682.5 | H63: =G63*(1+$C$55) -> 716.625 | I63: =H63*(1+$C$55) -> 752.45625 | J63: =I63*(1+$C$55) -> 790.07906 | K63: =J63*(1+$C$55) -> 829.58302 | L63: =K63*(1+$C$55) -> 871.06217 | M63: =L63*(1+$C$55) -> 914.61527 | N63: =M63*(1+$C$55) -> 960.34604 | O63: =N63*(1+$C$55) -> 1008.3633
C64: 상 가 | D64: =#REF! -> #REF! | E64: =#REF! -> #REF!
D65: =#REF! -> #REF! | E65: =#REF! -> #REF!
D66: =#REF! -> #REF! | E66: =#REF! -> #REF!
D67: =#REF! -> #REF! | E67: =#REF! -> #REF!
D68: =#REF! -> #REF! | E68: =#REF! -> #REF! | F68: =F78*10 -> 1500 | G68: =F68*(1+$C$55) -> 1575 | H68: =G68*(1+$C$55) -> 1653.75 | I68: =H68*(1+$C$55) -> 1736.4375 | J68: =I68*(1+$C$55) -> 1823.2594 | K68: =J68*(1+$C$55) -> 1914.4223 | L68: =K68*(1+$C$55) -> 2010.1435 | M68: =L68*(1+$C$55) -> 2110.6506 | N68: =M68*(1+$C$55) -> 2216.1832 | O68: =N68*(1+$C$55) -> 2326.9923
D69: =#REF! -> #REF! | E69: =#REF! -> #REF! | F69: =F79*10 -> 500 | G69: =F69*(1+$C$55) -> 525 | H69: =G69*(1+$C$55) -> 551.25 | I69: =H69*(1+$C$55) -> 578.8125 | J69: =I69*(1+$C$55) -> 607.75313 | K69: =J69*(1+$C$55) -> 638.14078 | L69: =K69*(1+$C$55) -> 670.04782 | M69: =L69*(1+$C$55) -> 703.55021 | N69: =M69*(1+$C$55) -> 738.72772 | O69: =N69*(1+$C$55) -> 775.66411
D70: =#REF! -> #REF! | E70: =#REF! -> #REF!
D71: =#REF! -> #REF! | E71: =#REF! -> #REF!
C72: 소 계 | F72: =SUMPRODUCT($E63:$E71,F63:F71) -> #REF! | G72: =SUMPRODUCT($E63:$E71,G63:G71) -> #REF! | H72: =SUMPRODUCT($E63:$E71,H63:H71) -> #REF! | I72: =SUMPRODUCT($E63:$E71,I63:I71) -> #REF! | J72: =SUMPRODUCT($E63:$E71,J63:J71) -> #REF! | K72: =SUMPRODUCT($E63:$E71,K63:K71) -> #REF! | L72: =SUMPRODUCT($E63:$E71,L63:L71) -> #REF! | M72: =SUMPRODUCT($E63:$E71,M63:M71) -> #REF! | ... O72: =SUMPRODUCT($E63:$E71,O63:O71) -> #REF!
B73: 임대료(월) | C73: 업무시설 | E73: =E63 -> #REF! | F73: 65 | G73: =F73*(1+$C$55) -> 68.25 | H73: =G73*(1+$C$55) -> 71.6625 | I73: =H73*(1+$C$55) -> 75.245625 | J73: =I73*(1+$C$55) -> 79.007906 | K73: =J73*(1+$C$55) -> 82.958302 | L73: =K73*(1+$C$55) -> 87.106217 | M73: =L73*(1+$C$55) -> 91.461527 | N73: =M73*(1+$C$55) -> 96.034604 | O73: =N73*(1+$C$55) -> 100.83633
C74: 상 가 | D74: =D64 -> #REF! | E74: =E64 -> #REF!
D75: =D65 -> #REF! | E75: =E65 -> #REF!
D76: =D66 -> #REF! | E76: =E66 -> #REF!
D77: =D67 -> #REF! | E77: =E67 -> #REF!
D78: =D68 -> #REF! | E78: =E68 -> #REF! | F78: 150 | G78: =F78*(1+$C$55) -> 157.5 | H78: =G78*(1+$C$55) -> 165.375 | I78: =H78*(1+$C$55) -> 173.64375 | J78: =I78*(1+$C$55) -> 182.32594 | K78: =J78*(1+$C$55) -> 191.44223 | L78: =K78*(1+$C$55) -> 201.01435 | M78: =L78*(1+$C$55) -> 211.06506 | N78: =M78*(1+$C$55) -> 221.61832 | O78: =N78*(1+$C$55) -> 232.69923
D79: =D69 -> #REF! | E79: =E69 -> #REF! | F79: 50 | G79: =F79*(1+$C$55) -> 52.5 | H79: =G79*(1+$C$55) -> 55.125 | I79: =H79*(1+$C$55) -> 57.88125 | J79: =I79*(1+$C$55) -> 60.775313 | K79: =J79*(1+$C$55) -> 63.814078 | L79: =K79*(1+$C$55) -> 67.004782 | M79: =L79*(1+$C$55) -> 70.355021 | N79: =M79*(1+$C$55) -> 73.872772 | O79: =N79*(1+$C$55) -> 77.566411
D80: =D70 -> #REF! | E80: =E70 -> #REF!
D81: =D71 -> #REF! | E81: =E71 -> #REF!
C82: 소 계 | F82: =SUMPRODUCT($E73:$E81,F73:F81) -> #REF! | G82: =SUMPRODUCT($E73:$E81,G73:G81) -> #REF! | H82: =SUMPRODUCT($E73:$E81,H73:H81) -> #REF! | I82: =SUMPRODUCT($E73:$E81,I73:I81) -> #REF! | J82: =SUMPRODUCT($E73:$E81,J73:J81) -> #REF! | K82: =SUMPRODUCT($E73:$E81,K73:K81) -> #REF! | L82: =SUMPRODUCT($E73:$E81,L73:L81) -> #REF! | M82: =SUMPRODUCT($E73:$E81,M73:M81) -> #REF! | ... O82: =SUMPRODUCT($E73:$E81,O73:O81) -> #REF!
B83: 관리비(월) | C83: 업무시설 | E83: =E73 -> #REF! | F83: 27 | G83: =F83*(1+$C$55) -> 28.35 | H83: =G83*(1+$C$55) -> 29.7675 | I83: =H83*(1+$C$55) -> 31.255875 | J83: =I83*(1+$C$55) -> 32.818669 | K83: =J83*(1+$C$55) -> 34.459602 | L83: =K83*(1+$C$55) -> 36.182582 | M83: =L83*(1+$C$55) -> 37.991711 | N83: =M83*(1+$C$55) -> 39.891297 | O83: =N83*(1+$C$55) -> 41.885862
C84: 상 가 | E84: =SUM(E74:E81) -> #REF! | F84: 15 | G84: =F84*(1+$C$55) -> 15.75 | H84: =G84*(1+$C$55) -> 16.5375 | I84: =H84*(1+$C$55) -> 17.364375 | J84: =I84*(1+$C$55) -> 18.232594 | K84: =J84*(1+$C$55) -> 19.144223 | L84: =K84*(1+$C$55) -> 20.101435 | M84: =L84*(1+$C$55) -> 21.106506 | N84: =M84*(1+$C$55) -> 22.161832 | O84: =N84*(1+$C$55) -> 23.269923
C85: 소 계 | F85: =SUMPRODUCT($E83:$E84,F83:F84) -> #REF! | G85: =SUMPRODUCT($E83:$E84,G83:G84) -> #REF! | H85: =SUMPRODUCT($E83:$E84,H83:H84) -> #REF! | I85: =SUMPRODUCT($E83:$E84,I83:I84) -> #REF! | J85: =SUMPRODUCT($E83:$E84,J83:J84) -> #REF! | K85: =SUMPRODUCT($E83:$E84,K83:K84) -> #REF! | L85: =SUMPRODUCT($E83:$E84,L83:L84) -> #REF! | M85: =SUMPRODUCT($E83:$E84,M83:M84) -> #REF! | ... O85: =SUMPRODUCT($E83:$E84,O83:O84) -> #REF!
B86: 전세 환산가 | C86: 업무시설 | E86: =E63 -> #REF! | F86: =F73*12/$I$55+F63 -> 7150 | G86: =F86*(1+$C$55) -> 7507.5 | H86: =G86*(1+$C$55) -> 7882.875 | I86: =H86*(1+$C$55) -> 8277.0188 | J86: =I86*(1+$C$55) -> 8690.8697 | K86: =J86*(1+$C$55) -> 9125.4132 | L86: =K86*(1+$C$55) -> 9581.6838 | M86: =L86*(1+$C$55) -> 10060.768 | N86: =M86*(1+$C$55) -> 10563.806 | O86: =N86*(1+$C$55) -> 11091.997
C87: 상 가 | D87: =D64 -> #REF! | E87: =E64 -> #REF! | F87: =F74*12/$I$55+F64 -> 0 | G87: =F87*(1+$C$55) -> 0 | H87: =G87*(1+$C$55) -> 0 | I87: =H87*(1+$C$55) -> 0 | J87: =I87*(1+$C$55) -> 0 | K87: =J87*(1+$C$55) -> 0 | L87: =K87*(1+$C$55) -> 0 | M87: =L87*(1+$C$55) -> 0 | N87: =M87*(1+$C$55) -> 0 | O87: =N87*(1+$C$55) -> 0
D88: =D65 -> #REF! | E88: =E65 -> #REF! | F88: =F75*12/$I$55+F65 -> 0 | G88: =F88*(1+$C$55) -> 0 | H88: =G88*(1+$C$55) -> 0 | I88: =H88*(1+$C$55) -> 0 | J88: =I88*(1+$C$55) -> 0 | K88: =J88*(1+$C$55) -> 0 | L88: =K88*(1+$C$55) -> 0 | M88: =L88*(1+$C$55) -> 0 | N88: =M88*(1+$C$55) -> 0 | O88: =N88*(1+$C$55) -> 0
D89: =D66 -> #REF! | E89: =E66 -> #REF! | F89: =F76*12/$I$55+F66 -> 0 | G89: =F89*(1+$C$55) -> 0 | H89: =G89*(1+$C$55) -> 0 | I89: =H89*(1+$C$55) -> 0 | J89: =I89*(1+$C$55) -> 0 | K89: =J89*(1+$C$55) -> 0 | L89: =K89*(1+$C$55) -> 0 | M89: =L89*(1+$C$55) -> 0 | N89: =M89*(1+$C$55) -> 0 | O89: =N89*(1+$C$55) -> 0
D90: =D67 -> #REF! | E90: =E67 -> #REF! | F90: =F77*12/$I$55+F67 -> 0 | G90: =F90*(1+$C$55) -> 0 | H90: =G90*(1+$C$55) -> 0 | I90: =H90*(1+$C$55) -> 0 | J90: =I90*(1+$C$55) -> 0 | K90: =J90*(1+$C$55) -> 0 | L90: =K90*(1+$C$55) -> 0 | M90: =L90*(1+$C$55) -> 0 | N90: =M90*(1+$C$55) -> 0 | O90: =N90*(1+$C$55) -> 0
D91: =D68 -> #REF! | E91: =E68 -> #REF! | F91: =F78*12/$I$55+F68 -> 16500 | G91: =F91*(1+$C$55) -> 17325 | H91: =G91*(1+$C$55) -> 18191.25 | I91: =H91*(1+$C$55) -> 19100.812 | J91: =I91*(1+$C$55) -> 20055.853 | K91: =J91*(1+$C$55) -> 21058.646 | L91: =K91*(1+$C$55) -> 22111.578 | M91: =L91*(1+$C$55) -> 23217.157 | N91: =M91*(1+$C$55) -> 24378.015 | O91: =N91*(1+$C$55) -> 25596.916
D92: =D69 -> #REF! | E92: =E69 -> #REF! | F92: =F79*12/$I$55+F69 -> 5500 | G92: =F92*(1+$C$55) -> 5775 | H92: =G92*(1+$C$55) -> 6063.75 | I92: =H92*(1+$C$55) -> 6366.9375 | J92: =I92*(1+$C$55) -> 6685.2844 | K92: =J92*(1+$C$55) -> 7019.5486 | L92: =K92*(1+$C$55) -> 7370.526 | M92: =L92*(1+$C$55) -> 7739.0523 | N92: =M92*(1+$C$55) -> 8126.0049 | O92: =N92*(1+$C$55) -> 8532.3052
D93: =D70 -> #REF! | E93: =E70 -> #REF! | F93: =F80*12/$I$55+F70 -> 0 | G93: =F93*(1+$C$55) -> 0 | H93: =G93*(1+$C$55) -> 0 | I93: =H93*(1+$C$55) -> 0 | J93: =I93*(1+$C$55) -> 0 | K93: =J93*(1+$C$55) -> 0 | L93: =K93*(1+$C$55) -> 0 | M93: =L93*(1+$C$55) -> 0 | N93: =M93*(1+$C$55) -> 0 | O93: =N93*(1+$C$55) -> 0
D94: =D71 -> #REF! | E94: =E71 -> #REF! | F94: =F81*12/$I$55+F71 -> 0 | G94: =F94*(1+$C$55) -> 0 | H94: =G94*(1+$C$55) -> 0 | I94: =H94*(1+$C$55) -> 0 | J94: =I94*(1+$C$55) -> 0 | K94: =J94*(1+$C$55) -> 0 | L94: =K94*(1+$C$55) -> 0 | M94: =L94*(1+$C$55) -> 0 | N94: =M94*(1+$C$55) -> 0 | O94: =N94*(1+$C$55) -> 0
C95: 소 계 | F95: =SUMPRODUCT($E86:$E94,F86:F94) -> #REF! | G95: =SUMPRODUCT($E86:$E94,G86:G94) -> #REF! | H95: =SUMPRODUCT($E86:$E94,H86:H94) -> #REF! | I95: =SUMPRODUCT($E86:$E94,I86:I94) -> #REF! | J95: =SUMPRODUCT($E86:$E94,J86:J94) -> #REF! | K95: =SUMPRODUCT($E86:$E94,K86:K94) -> #REF! | L95: =SUMPRODUCT($E86:$E94,L86:L94) -> #REF! | M95: =SUMPRODUCT($E86:$E94,M86:M94) -> #REF! | ... O95: =SUMPRODUCT($E86:$E94,O86:O94) -> #REF!
B97: 운용 기간 (월수) | H97: 0 | I97: 1 | J97: 12 | K97: =J97 -> 12 | L97: =K97 -> 12 | M97: =L97 -> 12 | N97: =M97 -> 12 | O97: =N97 -> 12
B98: 임대 수익(년) | C98: 업무시설 | E98: =E63 -> #REF! | H98: =$E98*H$97 -> #REF! | I98: =$E98*I$97 -> #REF! | J98: =$E98*J$97 -> #REF! | K98: =$E98*K$97 -> #REF! | L98: =$E98*L$97 -> #REF! | M98: =$E98*M$97 -> #REF! | N98: =$E98*N$97 -> #REF! | O98: =$E98*O$97 -> #REF!
C99: 상가 | D99: =D64 -> #REF! | E99: =E64 -> #REF! | H99: =$E99*H$97 -> #REF! | I99: =$E99*I$97 -> #REF! | J99: =$E99*J$97 -> #REF! | K99: =$E99*K$97 -> #REF! | L99: =$E99*L$97 -> #REF! | M99: =$E99*M$97 -> #REF! | N99: =$E99*N$97 -> #REF! | O99: =$E99*O$97 -> #REF!
D100: =D65 -> #REF! | E100: =E65 -> #REF! | H100: =$E100*H$97 -> #REF! | I100: =$E100*I$97 -> #REF! | J100: =$E100*J$97 -> #REF! | K100: =$E100*K$97 -> #REF! | L100: =$E100*L$97 -> #REF! | M100: =$E100*M$97 -> #REF! | N100: =$E100*N$97 -> #REF! | O100: =$E100*O$97 -> #REF!
D101: =D66 -> #REF! | E101: =E66 -> #REF! | H101: =$E101*H$97 -> #REF! | I101: =$E101*I$97 -> #REF! | J101: =$E101*J$97 -> #REF! | K101: =$E101*K$97 -> #REF! | L101: =$E101*L$97 -> #REF! | M101: =$E101*M$97 -> #REF! | N101: =$E101*N$97 -> #REF! | O101: =$E101*O$97 -> #REF!
D102: =D67 -> #REF! | E102: =E67 -> #REF! | H102: =$E102*H$97 -> #REF! | I102: =$E102*I$97 -> #REF! | J102: =$E102*J$97 -> #REF! | K102: =$E102*K$97 -> #REF! | L102: =$E102*L$97 -> #REF! | M102: =$E102*M$97 -> #REF! | N102: =$E102*N$97 -> #REF! | O102: =$E102*O$97 -> #REF!
D103: =D68 -> #REF! | E103: =E68 -> #REF! | H103: =$E103*H$97 -> #REF! | I103: =$E103*I$97 -> #REF! | J103: =$E103*J$97 -> #REF! | K103: =$E103*K$97 -> #REF! | L103: =$E103*L$97 -> #REF! | M103: =$E103*M$97 -> #REF! | N103: =$E103*N$97 -> #REF! | O103: =$E103*O$97 -> #REF!
D104: =D69 -> #REF! | E104: =E69 -> #REF! | H104: =$E104*H$97 -> #REF! | I104: =$E104*I$97 -> #REF! | J104: =$E104*J$97 -> #REF! | K104: =$E104*K$97 -> #REF! | L104: =$E104*L$97 -> #REF! | M104: =$E104*M$97 -> #REF! | N104: =$E104*N$97 -> #REF! | O104: =$E104*O$97 -> #REF!
D105: =D70 -> #REF! | E105: =E70 -> #REF! | H105: =$E105*H$97 -> #REF! | I105: =$E105*I$97 -> #REF! | J105: =$E105*J$97 -> #REF! | K105: =$E105*K$97 -> #REF! | L105: =$E105*L$97 -> #REF! | M105: =$E105*M$97 -> #REF! | N105: =$E105*N$97 -> #REF! | O105: =$E105*O$97 -> #REF!
D106: =D71 -> #REF! | E106: =E71 -> #REF! | H106: =$E106*H$97 -> #REF! | I106: =$E106*I$97 -> #REF! | J106: =$E106*J$97 -> #REF! | K106: =$E106*K$97 -> #REF! | L106: =$E106*L$97 -> #REF! | M106: =$E106*M$97 -> #REF! | N106: =$E106*N$97 -> #REF! | O106: =$E106*O$97 -> #REF!
C107: 소 계 | E107: =SUM(E98:E106) -> #REF! | H107: =SUM(H98:H106) -> #REF! | I107: =SUM(I98:I106) -> #REF! | J107: =SUM(J98:J106) -> #REF! | K107: =SUM(K98:K106) -> #REF! | L107: =SUM(L98:L106) -> #REF! | M107: =SUM(M98:M106) -> #REF! | N107: =SUM(N98:N106) -> #REF! | O107: =SUM(O98:O106) -> #REF!
B108: 임대료 총액(년) | H108: =SUMPRODUCT(H73:H81,H98:H106) -> #REF! | I108: =SUMPRODUCT(I73:I81,I98:I106) -> #REF! | J108: =SUMPRODUCT(J73:J81,J98:J106) -> #REF! | K108: =SUMPRODUCT(K73:K81,K98:K106) -> #REF! | L108: =SUMPRODUCT(L73:L81,L98:L106) -> #REF! | M108: =SUMPRODUCT(M73:M81,M98:M106) -> #REF! | N108: =SUMPRODUCT(N73:N81,N98:N106) -> #REF! | O108: =SUMPRODUCT(O73:O81,O98:O106) -> #REF!
...

Sheet 개발부담금
A1: ■ 개발부담금
B3: - 토지로부터 발생되는 개발이익을 환수하여 이를 적정하게 배분함으로써 토지에 대한 투기 방지
B4: - 택지개발사업, 공업단지조성사업, 관광단지조성사업, 유통단지조성사업, 온천개발사업 화룸터미널개발사업 골프장개발사업 등 30개 사업
B5: - 주택사업, 도시환경정비사업
B6: - 사업승인시부터 부고대상임을 고지, 준공후 3개월내 부과, 부과후 6개월내 납부
B8: 개발부담금 = 토지개발이익(사업종료시점지가 - 사업개시시점 지가 - 개발비용 - 정상 지가 상승분) × 부과율 25%
B10: 결정금액 | C10: =0 -> 0
B12: □ 면적
B13: 구 분 | C13: 면 적
B14: 시행면적 | C14: =사업검토!E6 -> 60663.8 | D14: =C14*0.3025 -> 18350.8
B15: 기부채납 (기존공공용지 및 공원부지) | C15: =사업검토!E7 -> 0 | D15: =C15*0.3025 -> 0
B16: 제척면적(기부채납에 포함) | C16: =사업검토!E8 -> 0 | D16: =C16*0.3025 -> 0
B17: 대지면적 | C17: =사업검토!E9 -> 60663.8 | D17: =C17*0.3025 -> 18350.8
B19: □ 사업종료시점 지가 = 현재지가 + 개발후 지가상승분
B21: 구 분 | C21: 금 액 | D21: 비 고
B22: 사업개시시점 지가 | C22: =C43*C14 -> 0 | D22: 현재 지가
B23: 인근지역 공시지가 | C23: =C54 -> 0
C24: =C23/0.3025 -> 0
B25: 개발후 지가 상승분 | C25: =C22*(AVERAGE(E41:E42)*C35/12) -> 0 | D25: 현재지가 X 지가 평균 상승률 X 기간(년)
B26: 사업종료시점 지가 | C26: =C22+C25 -> 0
B28: 구 분 | C28: 금 액 | D28: 비 고
B29: 개발비용 (철거비, 토지조성비 등) | C29: =사업검토!M80*1000 -> 18350799500
B30: 기부채납 (공원 및 공공용지 등) | C30: =C15*C41 -> 0
B32: 구 분 | C32: 금 액 | D32: 비 고
B33: 정상 지가 상승분 | C33: =C22*(AVERAGE(F52)*C35/12) -> #DIV/0! | D33: 현재지가 X 인근지역 평균 상승률 X 기간(년)
B35: 공사기간 | C35: =사업검토!L12 -> 40
B36: 대상지 평균 상승률 | C36: =E48 -> #DIV/0!
B37: 인근지역 공시지가 변동율 | C37: =F52 -> #DIV/0!
B39: □ 지구내 공시지가
B40: 년도 | C40: 공시지가(원/㎡) | D40: 증감(원) | E40: 변동율 | F40: 비고
B41: 46753 | C41: =C42*(1+$E$42) -> 0 | D41: =C41-C42 -> 0 | E41: 0
B42: 46388 | C42: =C43*(1+$E$42) -> 0 | D42: =C42-C43 -> 0 | E42: 0
B43: 46023 | D43: =C43-C44 -> 0 | E43: 0 | F43: 착공 | H43: =C43*40% -> 0
B44: 45658 | D44: =C44-C45 -> 0 | E44: =((C44/C45)-1) -> #DIV/0! | H44: =C44*40% -> 0
B45: 45292 | D45: =C45-C46 -> 0 | E45: =((C45/C46)-1) -> #DIV/0! | H45: =C45*40% -> 0
B46: 44927 | D46: =C46-C47 -> 0 | E46: =((C46/C47)-1) -> #DIV/0! | H46: =C46*40% -> 0
B47: 44562 | H47: =C47*40% -> 0
D48: 평균변동율 | E48: =SUM(E43:E46)/4 -> #DIV/0!
B50: □ 인근지역 공시지가
B51: 년도 | C51: 공시지가(원/㎡) | D51: 증감(원) | E51: 변동율 | F51: 비고
B52: 46753 | C52: =C53*(1+$F$54) -> #DIV/0! | D52: =C52-C53 -> #DIV/0! | E52: =D52/C53 -> #DIV/0! | F52: =AVERAGE(E52:E53) -> #DIV/0!
B53: 46388 | C53: =C54*(1+$F$54) -> #DIV/0! | D53: =C53-C54 -> #DIV/0! | E53: =D53/C54 -> #DIV/0!
B54: 46023 | C54: 0 | D54: =C54-C55 -> 0 | E54: =D54/C55 -> #DIV/0! | F54: =AVERAGE(E54:E57) -> #DIV/0! | H54: =C54*40% -> 0
B55: 45658 | C55: 0 | D55: =C55-C56 -> 0 | E55: =D55/C56 -> #DIV/0! | H55: =C55*40% -> 0
B56: 45292 | C56: 0 | D56: =C56-C57 -> 0 | E56: =D56/C57 -> #DIV/0! | H56: =C56*40% -> 0
B57: 44927 | C57: 0 | D57: =C57-C58 -> 0 | E57: =D57/C58 -> #DIV/0! | H57: =C57*40% -> 0
B58: 44562 | C58: 0 | H58: =C58*40% -> 0
D59: 평균변동율 | E59: =SUM(E54:E57)/4 -> #DIV/0!
A62: ■ 기반시설부담금
B64: 기반시설부담금 = [기반시설표준시설비용 + 지역별용지환산계수 X 건축물별 기반시설유발계수 X 개별공시지가 시, 군, 구 평균/㎡] X [건축허가면적 - 부속용도면적 - 기초공제면적(200㎡)] X 부담율 - 공제액
B66: 결정금액 | D66: =IF(D93<0,0,D93) -> 6.2529978e+10
B68: 구 분 | D68: 금 액 | E68: 비 고
B69: 대지면적 | D69: =사업검토!E9 -> 60663.8 | E69: 국토교통부 고시 제2025 - 398호
D70: =D69*0.3025 -> 18350.8
B71: 1. 기반시설표준시설비용 | D71: 81000
B72: 2. 기반시설에 대한 용지비용 | C72: 개별공시지가 | D72: =토지조서!E5*1000 -> 8636250
D73: =D72/0.3025 -> 28549587
D74: =D69*D72 -> 523907742750
C75: 지역별 용지환산계수 | D75: 0.3 | E75: 주거지역 : 0.3 상업지역 : 0.1 공업지역 : 0.2 녹지 및 비도시지역 : 0.4 | F75: *국계법 68조, 서울특별시 도시계획 조례
C76: 건축물별 기반시설유발계수 | D76: 0.7 | E76: 별표 참조
B77: 3. 산정연면적 | C77: 기존건축물 연면적 | D77: 0 | E77: 기존건축물을 철거하고 동일용도의 건축물을 신축하는 경우에 증가된 연면적에 대하여 부과
C78: 지상층 | D78: =사업검토!E11 -> 155753.45
C79: 지하층 | D79: =사업검토!E12 -> 87959.97
C80: 소 계 | D80: =D78+D79 -> 243713.42
C81: 부속용도면적 | D81: =건축개요!J37 -> 0 | E81: 주차장, 기계/전기실 등
C82: 기초공제면적 | D82: 200
C83: 산정연면적 | D83: =D80-D81-D82-D77 -> 243513.42
B84: 4. 부담율 | D84: 0.2 | E84: 20% ~ 25% 이내 조례에서 결정 | F84: 국계법 제68조
B85: 공제전 기반시설부담금 | D85: =(D71+D75*D76*D72)*D83*D84 -> 9.2272714e+10
B86: 5. 공제액 | C86: 공공시설 부담금 | D86: =사업검토!M77*1000 -> 2.2116993e+09 | E86: 인입분담금 예상금액
C87: 자체기반시설 토지비 (기부체납용지비용) | D87: =사업검토!E7 -> 0
C88: 자체기반시설설치비용 (기부체납용지 조성비) | D88: =사업검토!M78*1000 -> 2.2116993e+10
C89: 과밀부담금의 10% | D89: =사업검토!M119*1000*10% -> 0
C90: 광역교통시설부담금의 10% | D90: =사업검토!M120*1000*10% -> 0
C91: 학교용지부담금 | D91: =사업검토!M121*1000 -> 5.4140439e+09 | F91: 대지면적당
C92: 소 계 | D92: =SUM(D86:D91) -> 2.9742736e+10 | F92: =D93/D69 -> 1030762.6
B93: 기반시설부담금 | D93: =(D71+D75*D76*D72)*D83*D84-D92 -> 6.2529978e+10 | E93: =D93/(D78*0.3025) -> 1327165.9 | F93: =F92/D72 -> 0.11935303
A95: ▣ 별표3. 건축물별 기반시설유발계수
B96: 구분 | C96: 용도별 | D96: 기반시설유발계수 | E96: 비고
B97: 주거 | C97: 단독주택 | D97: 0.7
C98: 공동주택 | D98: 0.7
B99: 상업/업무 | C99: 제1종 근린생활시설 | D99: 1.3
C100: 제2종 근린생활시설 | D100: 1.6
C101: 판매시설 | D101: 1.3
C102: 업무시설 | D102: 0.7
C103: 숙박시설 | D103: 1
B104: 기타 | C104: 문화 및 집회시설 | D104: 1.4
C105: 종교시설 | D105: 1.4
C106: 운수시설 | D106: 1.4
C107: 의료시설 | D107: 0.9
C108: 교육연구시설 | D108: 0.7
C109: 노유자시설 | D109: 0.7
C110: 수련시설 | D110: 0.7
C111: 운동시설 | D111: 0.7
C112: 위락시설 | D112: 2.1
C113: 창고시설 | D113: 0.5
C114: 위험물저장 및 처리시설 | D114: 0.7
C115: 자동차관련시설 | D115: 0.7
C116: 동물 및 식물관련시설 | D116: 0.7
... C122: 관광휴게시설 | D122: 1.9
...

Sheet 토지조서
A1: 토지조서
G2: (천원)
A3: 연번 | B3: 지번 | C3: 면적 | E3: 공시지가 | G3: 시가표준 | H3: 수수료 | L3: 작성 예시
C4: ㎡ | D4: 평 | E4: ㎡당 | F4: 평당가 | L4: 연번 | M4: 지번 | N4: 면적 | P4: 공시지가 | R4: 시가표준 | S4: 수수료
A5: 1 | B5: 1189-1 | C5: 106.1 | D5: =C5*0.3025 -> 32.09525 | E5: =(6909000*1.25)/1000 -> 8636.25 | F5: =E5/0.3025 -> 28549.587 | G5: =C5*E5 -> 916306.12 | H5: =C680 -> 761 | N5: ㎡ | O5: 평 | P5: ㎡당 | Q5: 평당가
A6: 2 | B6: 1189-2 | C6: 129.3 | D6: =C6*0.3025 -> 39.11325 | E6: =(6835000*1.25)/1000 -> 8543.75 | F6: =E6/0.3025 -> 28243.802 | G6: =C6*E6 -> 1104706.9 | H6: =C72 -> 89.2 | L6: 1 | M6: 680-24 | N6: 1489.5㎡ | O6: 450.57 | P6: 11170 | Q6: 36926 | R6: 16637715 | S6: 4897
A7: 3 | B7: 1189-3 | C7: 120.2 | D7: =C7*0.3025 -> 36.3605 | E7: =(3676000*1.25)/1000 -> 4595 | F7: =E7/0.3025 -> 15190.083 | G7: =C7*E7 -> 552319 | H7: =C87 -> 89
A8: 4 | B8: 1189-4 | C8: 109.6 | D8: =C8*0.3025 -> 33.154 | E8: =(3572000*1.25)/1000 -> 4465 | F8: =E8/0.3025 -> 14760.331 | G8: =C8*E8 -> 489364 | H8: =C102 -> 91.9
A9: 5 | B9: 1189-5 | C9: 93.5 | D9: =C9*0.3025 -> 28.28375 | E9: =(4710000*1.25)/1000 -> 5887.5 | F9: =E9/0.3025 -> 19462.81 | G9: =C9*E9 -> 550481.25 | H9: =C117 -> 87.5
A10: 6 | B10: 1189-6 | C10: 90.3 | D10: =C10*0.3025 -> 27.31575 | E10: =(3640000*1.25)/1000 -> 4550 | F10: =E10/0.3025 -> 15041.322 | G10: =C10*E10 -> 410865 | H10: =C132 -> 91
A11: 7 | B11: 1189-7 | C11: 86.2 | D11: =C11*0.3025 -> 26.0755 | E11: =(3640000*1.25)/1000 -> 4550 | F11: =E11/0.3025 -> 15041.322 | G11: =C11*E11 -> 392210 | H11: =C147 -> 85.7
A12: 8 | B12: 1189-8 | C12: 89.1 | D12: =C12*0.3025 -> 26.95275 | E12: =(3640000*1.25)/1000 -> 4550 | F12: =E12/0.3025 -> 15041.322 | G12: =C12*E12 -> 405405 | H12: =C162 -> 90.9
A13: 9 | B13: 1189-9 | C13: 87.4 | D13: =C13*0.3025 -> 26.4385 | E13: =(3640000*1.25)/1000 -> 4550 | F13: =E13/0.3025 -> 15041.322 | G13: =C13*E13 -> 397670 | H13: =C177 -> 88.3
A14: 10 | B14: 1189-10 | C14: 102.1 | D14: =C14*0.3025 -> 30.88525 | E14: =(6835000*1.25)/1000 -> 8543.75 | F14: =E14/0.3025 -> 28243.802 | G14: =C14*E14 -> 872316.88 | H14: =C192 -> 90.1
A15: 11 | B15: 1189-11 | C15: 103.7 | D15: =C15*0.3025 -> 31.36925 | E15: =(6835000*1.25)/1000 -> 8543.75 | F15: =E15/0.3025 -> 28243.802 | G15: =C15*E15 -> 885986.88 | H15: =C207 -> 175.6
A16: 12 | B16: 1189-12 | C16: 96.3 | D16: =C16*0.3025 -> 29.13075 | E16: =(3712000*1.25)/1000 -> 4640 | F16: =E16/0.3025 -> 15338.843 | G16: =C16*E16 -> 446832 | H16: =C222 -> 88.5
A17: 13 | B17: 1189-13 | C17: 92.3 | D17: =C17*0.3025 -> 27.92075 | E17: =(3712000*1.25)/1000 -> 4640 | F17: =E17/0.3025 -> 15338.843 | G17: =C17*E17 -> 428272 | H17: =C237 -> 88.9
A18: 14 | B18: 1189-14 | C18: 90.7 | D18: =C18*0.3025 -> 27.43675 | E18: =(3712000*1.25)/1000 -> 4640 | F18: =E18/0.3025 -> 15338.843 | G18: =C18*E18 -> 420848 | H18: =C253 -> 89.4
A19: 15 | B19: 1189-15 | C19: 90.2 | D19: =C19*0.3025 -> 27.2855 | E19: =(3712000*1.25)/1000 -> 4640 | F19: =E19/0.3025 -> 15338.843 | G19: =C19*E19 -> 418528 | H19: =C268 -> 87.5
A20: 16 | B20: 1189-16 | C20: 89.6 | D20: =C20*0.3025 -> 27.104 | E20: =(3712000*1.25)/1000 -> 4640 | F20: =E20/0.3025 -> 15338.843 | G20: =C20*E20 -> 415744 | H20: =C283 -> 88.7
A21: 17 | B21: 1189-17 | C21: 85 | D21: =C21*0.3025 -> 25.7125 | E21: =(3712000*1.25)/1000 -> 4640 | F21: =E21/0.3025 -> 15338.843 | G21: =C21*E21 -> 394400 | H21: =C298 -> 88.2
A22: 18 | B22: 1189-18 | C22: 89.3 | D22: =C22*0.3025 -> 27.01325 | E22: =(3712000*1.25)/1000 -> 4640 | F22: =E22/0.3025 -> 15338.843 | G22: =C22*E22 -> 414352 | H22: =C313 -> 89.7
A23: 19 | B23: 1189-19 | C23: 109.2 | D23: =C23*0.3025 -> 33.033 | E23: =(3608000*1.25)/1000 -> 4510 | F23: =E23/0.3025 -> 14909.091 | G23: =C23*E23 -> 492492 | H23: =C328 -> 86.5
A24: 20 | B24: 1189-20 | C24: 94 | D24: =C24*0.3025 -> 28.435 | E24: =(3608000*1.25)/1000 -> 4510 | F24: =E24/0.3025 -> 14909.091 | G24: =C24*E24 -> 423940 | H24: =C343 -> 90.8
A25: 21 | B25: 1189-21 | C25: 142 | D25: =C25*0.3025 -> 42.955 | E25: =(1201000*1.25)/1000 -> 1501.25 | F25: =E25/0.3025 -> 4962.8099 | G25: =C25*E25 -> 213177.5 | H25: =C358 -> 87.8
A26: 22 | B26: 1188-1 | C26: 166.2 | D26: =C26*0.3025 -> 50.2755 | E26: =(3629000*1.25)/1000 -> 4536.25 | F26: =E26/0.3025 -> 14995.868 | G26: =C26*E26 -> 753924.75 | H26: =C373 -> 90.3
A27: 23 | B27: 1188-2 | C27: 85.9 | D27: =C27*0.3025 -> 25.98475 | E27: =(3640000*1.25)/1000 -> 4550 | F27: =E27/0.3025 -> 15041.322 | G27: =C27*E27 -> 390845 | H27: =C388 -> 89.4
A28: 24 | B28: 1188-3 | C28: 87.9 | D28: =C28*0.3025 -> 26.58975 | E28: =(3640000*1.25)/1000 -> 4550 | F28: =E28/0.3025 -> 15041.322 | G28: =C28*E28 -> 399945 | H28: =C403 -> 87.5
A29: 25 | B29: 1188-4 | C29: 87.2 | D29: =C29*0.3025 -> 26.378 | E29: =(3640000*1.25)/1000 -> 4550 | F29: =E29/0.3025 -> 15041.322 | G29: =C29*E29 -> 396760 | H29: =C418 -> 88.1
A30: 26 | B30: 1188-5 | C30: 87 | D30: =C30*0.3025 -> 26.3175 | E30: =(3640000*1.25)/1000 -> 4550 | F30: =E30/0.3025 -> 15041.322 | G30: =C30*E30 -> 395850 | H30: =C433 -> 87.6
A31: 27 | B31: 1188-6 | C31: 91.5 | D31: =C31*0.3025 -> 27.67875 | E31: =(3640000*1.25)/1000 -> 4550 | F31: =E31/0.3025 -> 15041.322 | G31: =C31*E31 -> 416325 | H31: =C448 -> 89.7
A32: 28 | B32: 1188-7 | C32: 89.8 | D32: =C32*0.3025 -> 27.1645 | E32: =(3640000*1.25)/1000 -> 4550 | F32: =E32/0.3025 -> 15041.322 | G32: =C32*E32 -> 408590 | H32: =C463 -> 89.6
A33: 29 | B33: 1188-8 | C33: 88.6 | D33: =C33*0.3025 -> 26.8015 | E33: =(3640000*1.25)/1000 -> 4550 | F33: =E33/0.3025 -> 15041.322 | G33: =C33*E33 -> 403130 | H33: =C478 -> 91
A34: 30 | B34: 1188-9 | C34: 87.5 | D34: =C34*0.3025 -> 26.46875 | E34: =(3640000*1.25)/1000 -> 4550 | F34: =E34/0.3025 -> 15041.322 | G34: =C34*E34 -> 398125 | H34: =C493 -> 92.1
A35: 31 | B35: 1188-10 | C35: 86.5 | D35: =C35*0.3025 -> 26.16625 | E35: =(3640000*1.25)/1000 -> 4550 | F35: =E35/0.3025 -> 15041.322 | G35: =C35*E35 -> 393575 | H35: =C508 -> 90.6
A36: 32 | B36: 1188-11 | C36: 91.2 | D36: =C36*0.3025 -> 27.588 | E36: =(3640000*1.25)/1000 -> 4550 | F36: =E36/0.3025 -> 15041.322 | G36: =C36*E36 -> 414960 | H36: =C509 -> 88.5
A37: 33 | B37: 1188-12 | C37: 84.9 | D37: =C37*0.3025 -> 25.68225 | E37: =(6835000*1.25)/1000 -> 8543.75 | F37: =E37/0.3025 -> 28243.802 | G37: =C37*E37 -> 725364.38 | H37: =C510 -> 90.6
A38: 34 | B38: 1188-13 | C38: 82.4 | D38: =C38*0.3025 -> 24.926 | E38: =(6835000*1.25)/1000 -> 8543.75 | F38: =E38/0.3025 -> 28243.802 | G38: =C38*E38 -> 704005 | H38: =C511 -> 86.8
A39: 35 | B39: 1188-14 | C39: 88.9 | D39: =C39*0.3025 -> 26.89225 | E39: =(3570000*1.25)/1000 -> 4462.5 | F39: =E39/0.3025 -> 14752.066 | G39: =C39*E39 -> 396716.25 | H39: =C498 -> 497.4
A40: 36 | B40: 1188-15 | C40: 88.7 | D40: =C40*0.3025 -> 26.83175 | E40: =(3712000*1.25)/1000 -> 4640 | F40: =E40/0.3025 -> 15338.843 | G40: =C40*E40 -> 411568 | H40: =C513 -> 176.5
A41: 37 | B41: 1188-16 | C41: 90.1 | D41: =C41*0.3025 -> 27.25525 | E41: =(3712000*1.25)/1000 -> 4640 | F41: =E41/0.3025 -> 15338.843 | G41: =C41*E41 -> 418064 | H41: =C514 -> 89.3
A42: 38 | B42: 1188-17 | C42: 88.9 | D42: =C42*0.3025 -> 26.89225 | E42: =(3712000*1.25)/1000 -> 4640 | F42: =E42/0.3025 -> 15338.843 | G42: =C42*E42 -> 412496 | H42: =C515 -> 87.1
A43: 39 | B43: 1188-18 | C43: 89.4 | D43: =C43*0.3025 -> 27.0435 | E43: =(3712000*1.25)/1000 -> 4640 | F43: =E43/0.3025 -> 15338.843 | G43: =C43*E43 -> 414816 | H43: =C516 -> 89
A44: 40 | B44: 1188-19 | C44: 89.4 | D44: =C44*0.3025 -> 27.0435 | E44: =(3712000*1.25)/1000 -> 4640 | F44: =E44/0.3025 -> 15338.843 | G44: =C44*E44 -> 414816 | H44: =C503 -> 89.1
A45: 41 | B45: 1188-20 | C45: 91.6 | D45: =C45*0.3025 -> 27.709 | E45: =(3712000*1.25)/1000 -> 4640 | F45: =E45/0.3025 -> 15338.843 | G45: =C45*E45 -> 425024 | H45: =C518 -> 88.3
A46: 42 | B46: 1188-21 | C46: 91.5 | D46: =C46*0.3025 -> 27.67875 | E46: =(3712000*1.25)/1000 -> 4640 | F46: =E46/0.3025 -> 15338.843 | G46: =C46*E46 -> 424560 | H46: =C519 -> 88.8
A47: 43 | B47: 1188-22 | C47: 91.9 | D47: =C47*0.3025 -> 27.79975 | E47: =(3712000*1.25)/1000 -> 4640 | F47: =E47/0.3025 -> 15338.843 | G47: =C47*E47 -> 426416 | H47: =C520 -> 88.8
A48: 44 | B48: 1188-23 | C48: 95.7 | D48: =C48*0.3025 -> 28.94925 | E48: =(3712000*1.25)/1000 -> 4640 | F48: =E48/0.3025 -> 15338.843 | G48: =C48*E48 -> 444048 | H48: =C521 -> 87
A49: 45 | B49: 1187-1 | C49: 103.6 | D49: =C49*0.3025 -> 31.339 | E49: =(3556000*1.25)/1000 -> 4445 | F49: =E49/0.3025 -> 14694.215 | G49: =C49*E49 -> 460502 | H49: =C508 -> 90.6
A50: 46 | B50: 1187-2 | C50: 89.7 | D50: =C50*0.3025 -> 27.13425 | E50: =(3640000*1.25)/1000 -> 4550 | F50: =E50/0.3025 -> 15041.322 | G50: =C50*E50 -> 408135 | H50: =C523 -> 88.6
A51: 47 | B51: 1187-3 | C51: 88.3 | D51: =C51*0.3025 -> 26.71075 | E51: =(3640000*1.25)/1000 -> 4550 | F51: =E51/0.3025 -> 15041.322 | G51: =C51*E51 -> 401765 | H51: =C524 -> 87
A52: 48 | B52: 1187-4 | C52: 85.6 | D52: =C52*0.3025 -> 25.894 | E52: =(3640000*1.25)/1000 -> 4550 | F52: =E52/0.3025 -> 15041.322 | G52: =C52*E52 -> 389480 | H52: =C525 -> 88.7
A53: 49 | B53: 1187-5 | C53: 86.9 | D53: =C53*0.3025 -> 26.28725 | E53: =(3640000*1.25)/1000 -> 4550 | F53: =E53/0.3025 -> 15041.322 | G53: =C53*E53 -> 395395 | H53: =C526 -> 91.2
A54: 50 | B54: 1187-6 | C54: 87.5 | D54: =C54*0.3025 -> 26.46875 | E54: =(3640000*1.25)/1000 -> 4550 | F54: =E54/0.3025 -> 15041.322 | G54: =C54*E54 -> 398125 | H54: =C513 -> 176.5
A55: 51 | B55: 1187-7 | C55: 85.8 | D55: =C55*0.3025 -> 25.9545 | E55: =(3640000*1.25)/1000 -> 4550 | F55: =E55/0.3025 -> 15041.322 | G55: =C55*E55 -> 390390 | H55: =C528 -> 103
A56: 52 | B56: 1187-8 | C56: 85.7 | D56: =C56*0.3025 -> 25.92425 | E56: =(3640000*1.25)/1000 -> 4550 | F56: =E56/0.3025 -> 15041.322 | G56: =C56*E56 -> 389935 | H56: =C529 -> 91.9
A57: 53 | B57: 1187-9 | C57: 88 | D57: =C57*0.3025 -> 26.62 | E57: =(3640000*1.25)/1000 -> 4550 | F57: =E57/0.3025 -> 15041.322 | G57: =C57*E57 -> 400400 | H57: =C530 -> 87.8
A58: 54 | B58: 1187-10 | C58: 86.3 | D58: =C58*0.3025 -> 26.10575 | E58: =(3640000*1.25)/1000 -> 4550 | F58: =E58/0.3025 -> 15041.322 | G58: =C58*E58 -> 392665 | H58: =C531 -> 89.4
A59: 55 | B59: 1187-11 | C59: 88.8 | D59: =C59*0.3025 -> 26.862 | E59: =(3640000*1.25)/1000 -> 4550 | F59: =E59/0.3025 -> 15041.322 | G59: =C59*E59 -> 404040 | H59: =C518 -> 88.3
A60: 56 | B60: 1187-12 | C60: 85.4 | D60: =C60*0.3025 -> 25.8335 | E60: =(6835000*1.25)/1000 -> 8543.75 | F60: =E60/0.3025 -> 28243.802 | G60: =C60*E60 -> 729636.25 | H60: =C533 -> 87.1
A61: 57 | B61: 1187-13 | C61: 71.3 | D61: =C61*0.3025 -> 21.56825 | E61: =(6835000*1.25)/1000 -> 8543.75 | F61: =E61/0.3025 -> 28243.802 | G61: =C61*E61 -> 609169.38 | H61: =C534 -> 87
A62: 58 | B62: 1187-14 | C62: 74.2 | D62: =C62*0.3025 -> 22.4455 | E62: =(6835000*1.25)/1000 -> 8543.75 | F62: =E62/0.3025 -> 28243.802 | G62: =C62*E62 -> 633946.25 | H62: =C535 -> 89.4
A63: 59 | B63: 1187-15 | C63: 91 | D63: =C63*0.3025 -> 27.5275 | E63: =(3712000*1.25)/1000 -> 4640 | F63: =E63/0.3025 -> 15338.843 | G63: =C63*E63 -> 422240 | H63: =C536 -> 89.4
A64: 60 | B64: 1187-16 | C64: 92.1 | D64: =C64*0.3025 -> 27.86025 | E64: =(3712000*1.25)/1000 -> 4640 | F64: =E64/0.3025 -> 15338.843 | G64: =C64*E64 -> 427344 | H64: =C523 -> 88.6
A65: 61 | B65: 1187-17 | C65: 91.9 | D65: =C65*0.3025 -> 27.79975 | E65: =(3712000*1.25)/1000 -> 4640 | F65: =E65/0.3025 -> 15338.843 | G65: =C65*E65 -> 426416 | H65: =C538 -> 86.7
A66: 62 | B66: 1187-18 | C66: 89.6 | D66: =C66*0.3025 -> 27.104 | E66: =(3712000*1.25)/1000 -> 4640 | F66: =E66/0.3025 -> 15338.843 | G66: =C66*E66 -> 415744 | H66: =C539 -> 86.4
A67: 63 | B67: 1187-19 | C67: 89.1 | D67: =C67*0.3025 -> 26.95275 | E67: =(3712000*1.25)/1000 -> 4640 | F67: =E67/0.3025 -> 15338.843 | G67: =C67*E67 -> 413424 | H67: =C540 -> 87.9
A68: 64 | B68: 1187-20 | C68: 90 | D68: =C68*0.3025 -> 27.225 | E68: =(3712000*1.25)/1000 -> 4640 | F68: =E68/0.3025 -> 15338.843 | G68: =C68*E68 -> 417600 | H68: =C541 -> 90.6
A69: 65 | B69: 1187-21 | C69: 91.1 | D69: =C69*0.3025 -> 27.55775 | E69: =(3712000*1.25)/1000 -> 4640 | F69: =E69/0.3025 -> 15338.843 | G69: =C69*E69 -> 422704 | H69: =C528 -> 103
A70: 66 | B70: 1187-22 | C70: 90.5 | D70: =C70*0.3025 -> 27.37625 | E70: =(3712000*1.25)/1000 -> 4640 | F70: =E70/0.3025 -> 15338.843 | G70: =C70*E70 -> 419920 | H70: =C543 -> 89.1
A71: 67 | B71: 1187-23 | C71: 88.9 | D71: =C71*0.3025 -> 26.89225 | E71: =(3712000*1.25)/1000 -> 4640 | F71: =E71/0.3025 -> 15338.843 | G71: =C71*E71 -> 412496 | H71: =C544 -> 88.3
A72: 68 | B72: 1187-24 | C72: 89.2 | D72: =C72*0.3025 -> 26.983 | E72: =(3712000*1.25)/1000 -> 4640 | F72: =E72/0.3025 -> 15338.843 | G72: =C72*E72 -> 413888 | H72: =C545 -> 89.9
A73: 69 | B73: 1187-25 | C73: 89.2 | D73: =C73*0.3025 -> 26.983 | E73: =(3712000*1.25)/1000 -> 4640 | F73: =E73/0.3025 -> 15338.843 | G73: =C73*E73 -> 413888 | H73: =C546 -> 87.9
A74: 70 | B74: 1187-26 | C74: 84.5 | D74: =C74*0.3025 -> 25.56125 | E74: =(3712000*1.25)/1000 -> 4640 | F74: =E74/0.3025 -> 15338.843 | G74: =C74*E74 -> 392080 | H74: =C533 -> 87.1
A75: 71 | B75: 1187-27 | C75: 82.2 | D75: =C75*0.3025 -> 24.8655 | E75: =(3556000*1.25)/1000 -> 4445 | F75: =E75/0.3025 -> 14694.215 | G75: =C75*E75 -> 365379 | H75: =C548 -> 91.2
A76: 72 | B76: 1186-1 | C76: 42.2 | D76: =C76*0.3025 -> 12.7655 | E76: =(3556000*1.25)/1000 -> 4445 | F76: =E76/0.3025 -> 14694.215 | G76: =C76*E76 -> 187579 | H76: =C549 -> 72.1
A77: 73 | B77: 1186-2 | C77: 85.2 | D77: =C77*0.3025 -> 25.773 | E77: =(3640000*1.25)/1000 -> 4550 | F77: =E77/0.3025 -> 15041.322 | G77: =C77*E77 -> 387660 | H77: =C550 -> 52.9
A78: 74 | B78: 1186-3 | C78: 89.4 | D78: =C78*0.3025 -> 27.0435 | E78: =(3640000*1.25)/1000 -> 4550 | F78: =E78/0.3025 -> 15041.322 | G78: =C78*E78 -> 406770 | H78: =C551 -> 87
A79: 75 | B79: 1186-4 | C79: 88.3 | D79: =C79*0.3025 -> 26.71075 | E79: =(3640000*1.25)/1000 -> 4550 | F79: =E79/0.3025 -> 15041.322 | G79: =C79*E79 -> 401765 | H79: =C538 -> 86.7
A80: 76 | B80: 1186-5 | C80: 88 | D80: =C80*0.3025 -> 26.62 | E80: =(3640000*1.25)/1000 -> 4550 | F80: =E80/0.3025 -> 15041.322 | G80: =C80*E80 -> 400400 | H80: =C553 -> 88
A81: 77 | B81: 1186-6 | C81: 89.9 | D81: =C81*0.3025 -> 27.19475 | E81: =(3640000*1.25)/1000 -> 4550 | F81: =E81/0.3025 -> 15041.322 | G81: =C81*E81 -> 409045 | H81: =C554 -> 89.5
A82: 78 | B82: 1186-7 | C82: 86.9 | D82: =C82*0.3025 -> 26.28725 | E82: =(3640000*1.25)/1000 -> 4550 | F82: =E82/0.3025 -> 15041.322 | G82: =C82*E82 -> 395395 | H82: =C555 -> 90.2
A83: 79 | B83: 1186-8 | C83: 90.7 | D83: =C83*0.3025 -> 27.43675 | E83: =(3640000*1.25)/1000 -> 4550 | F83: =E83/0.3025 -> 15041.322 | G83: =C83*E83 -> 412685 | H83: =C556 -> 88.4
A84: 80 | B84: 1186-9 | C84: 89.6 | D84: =C84*0.3025 -> 27.104 | E84: =(3640000*1.25)/1000 -> 4550 | F84: =E84/0.3025 -> 15041.322 | G84: =C84*E84 -> 407680 | H84: =C543 -> 89.1
A85: 81 | B85: 1186-10 | C85: 88.3 | D85: =C85*0.3025 -> 26.71075 | E85: =(3640000*1.25)/1000 -> 4550 | F85: =E85/0.3025 -> 15041.322 | G85: =C85*E85 -> 401765 | H85: =C558 -> 90.4
A86: 82 | B86: 1186-11 | C86: 89.3 | D86: =C86*0.3025 -> 27.01325 | E86: =(3640000*1.25)/1000 -> 4550 | F86: =E86/0.3025 -> 15041.322 | G86: =C86*E86 -> 406315 | H86: =C559 -> 89.7
A87: 83 | B87: 1186-12 | C87: 89 | D87: =C87*0.3025 -> 26.9225 | E87: =(3640000*1.25)/1000 -> 4550 | F87: =E87/0.3025 -> 15041.322 | G87: =C87*E87 -> 404950 | H87: =C560 -> 88.9
A88: 84 | B88: 1186-13 | C88: 90 | D88: =C88*0.3025 -> 27.225 | E88: =(3640000*1.25)/1000 -> 4550 | F88: =E88/0.3025 -> 15041.322 | G88: =C88*E88 -> 409500 | H88: =C561 -> 90.2
A89: 85 | B89: 1186-15 | C89: 162 | D89: =C89*0.3025 -> 49.005 | E89: =(6835000*1.25)/1000 -> 8543.75 | F89: =E89/0.3025 -> 28243.802 | G89: =C89*E89 -> 1384087.5 | H89: =C548 -> 91.2
A90: 86 | B90: 1186-16 | C90: 84.8 | D90: =C90*0.3025 -> 25.652 | E90: =(7350000*1.25)/1000 -> 9187.5 | F90: =E90/0.3025 -> 30371.901 | G90: =C90*E90 -> 779100 | H90: =C563 -> 89.5
A91: 87 | B91: 1186-17 | C91: 90 | D91: =C91*0.3025 -> 27.225 | E91: =(3712000*1.25)/1000 -> 4640 | F91: =E91/0.3025 -> 15338.843 | G91: =C91*E91 -> 417600 | H91: =C564 -> 91.5
A92: 88 | B92: 1186-18 | C92: 90.9 | D92: =C92*0.3025 -> 27.49725 | E92: =(3712000*1.25)/1000 -> 4640 | F92: =E92/0.3025 -> 15338.843 | G92: =C92*E92 -> 421776 | H92: =C565 -> 85.3
A93: 89 | B93: 1186-19 | C93: 89.8 | D93: =C93*0.3025 -> 27.1645 | E93: =(3712000*1.25)/1000 -> 4640 | F93: =E93/0.3025 -> 15338.843 | G93: =C93*E93 -> 416672 | H93: =C566 -> 83.5
A94: 90 | B94: 1186-20 | C94: 91.7 | D94: =C94*0.3025 -> 27.73925 | E94: =(3712000*1.25)/1000 -> 4640 | F94: =E94/0.3025 -> 15338.843 | G94: =C94*E94 -> 425488 | H94: =C553 -> 88
A95: 91 | B95: 1186-21 | C95: 90.2 | D95: =C95*0.3025 -> 27.2855 | E95: =(3712000*1.25)/1000 -> 4640 | F95: =E95/0.3025 -> 15338.843 | G95: =C95*E95 -> 418528 | H95: =C568 -> 88.1
A96: 92 | B96: 1186-22 | C96: 89.2 | D96: =C96*0.3025 -> 26.983 | E96: =(3712000*1.25)/1000 -> 4640 | F96: =E96/0.3025 -> 15338.843 | G96: =C96*E96 -> 413888 | H96: =C569 -> 88.5
A97: 93 | B97: 1186-23 | C97: 89.7 | D97: =C97*0.3025 -> 27.13425 | E97: =(3712000*1.25)/1000 -> 4640 | F97: =E97/0.3025 -> 15338.843 | G97: =C97*E97 -> 416208 | H97: =C570 -> 89
A98: 94 | B98: 1186-24 | C98: 89.2 | D98: =C98*0.3025 -> 26.983 | E98: =(3712000*1.25)/1000 -> 4640 | F98: =E98/0.3025 -> 15338.843 | G98: =C98*E98 -> 413888 | H98: =C571 -> 87.9
A99: 95 | B99: 1186-25 | C99: 92.1 | D99: =C99*0.3025 -> 27.86025 | E99: =(3712000*1.25)/1000 -> 4640 | F99: =E99/0.3025 -> 15338.843 | G99: =C99*E99 -> 427344 | H99: =C558 -> 90.4
A100: 96 | B100: 1186-26 | C100: 89.5 | D100: =C100*0.3025 -> 27.07375 | E100: =(3712000*1.25)/1000 -> 4640 | F100: =E100/0.3025 -> 15338.843 | G100: =C100*E100 -> 415280 | H100: =C573 -> 90.3
...

Sheet 세금
A2: ■ | B2: 토지취득과세 | E2: 중과세의 경우
B3: 취득세 | C3: 취득가액의 | D3: 0.04 | E3: 사치성재산*, 과밀억제권역 5년 미만 법인의 토지 취득 : 12% (3배)
B4: 농어촌특별세 | C4: 취득가액의 | D4: 0.002 | E4: 좌동
B5: 교육세 | C5: 취득가액의 | D5: 0.004 | E5: 좌동
B6: 일반세율 | C6: 취득가액의 | D6: =SUM(D3:D5) -> 0.046
B7: * 사치성 재산 : 별장, 골프장, 고급오락장, 고급주택, 고급선박
B8: 유무유흥주점 : 카바레, 나이트 크럽, 고고크럽, 디스코 클럽, 룸쌀롱 (객실 2이상)
B9: 요정영업장소 (유흥접객원이 있는 경우)
B10: 특수목욕장 중 증기탕
B12: 토지매입비 | C12: =사업검토!M70 -> 0 | D12: 천원
B13: 결정세액 | C13: =C12*D6 -> 0 | D13: 천원
A16: ■ | B16: 토지보유과세
B18: 면적 | C18: ㎡ | D18: 평 | E18: 과세기준일 : 매년 6월1일
C19: =토지조서!C38 -> 82.4 | D19: =토지조서!D38 -> 24.926 | E19: 납부일 : 매년 9월
B20: 공시지가(천원) | C20: =토지조서!E38 -> 8543.75 | D20: =토지조서!F38 -> 28243.802 | E20: - 7월 : 재산세(건축물) + 재산세(주택) 1/2
B21: 시가표준액 | C21: =PRODUCT(C19:C20) -> 704005 | D21: =PRODUCT(D19:D20) -> 704005 | E21: - 9월 : 재산세(토지) + 재산세(주택) 1/2
A23: 1) | B23: 재산세
B25: 재산세 = 과세표준(시가표준액 X 공정시장가액비율) X 세율
B27: 구 분 | C27: 금액(천원) | D27: 비고
B28: 시가표준액 | C28: =C21 -> 704005 | D28: 별도합산과세
B29: 공정시장가액 비율 | C29: 0.7
B30: 과세표준 | C30: =C28*C29 -> 492803.5
B31: 세율 | C31: 0.004 | D31: 280만+10억원 초과금액 0.4%
B32: 재산세액 | C32: =2800+(C30-1000000)*4/1000 -> 771.214
B33: 공제 제산세액
B34: 결정세액 | C34: =C32-C33 -> 771.214
A36: 2) | B36: 종합부동산세
B38: 종합부동산세 = 과세표준(시가표준액 X 공정시장가액비율) X 세율
B40: 구 분 | C40: 금액(천원) | D40: 비고
B41: 시가표준액 | C41: =C21 -> 704005
B42: 공제금액 | C42: 8000000 | D42: 별도합산
B43: 공정시장가액 비율 | C43: 0.6
B44: 과세표준 | C44: =(C41-C42)*C43 -> -4377597
B45: 세율 | C45: 200억원 이하 0.5%
C46: 400억원 이하 0.6% | D46: 누진공제 2,000만원
C47: 600억원 초과 0.7% | D47: 누진공제 6,000만원
B48: 종합부동산세액 | C48: =IF(C44<20000000,C44*0.5%,(IF(C44<40000000,C44*0.6%-20000,C44*0.7%-60000))) -> -21887.985
B49: 공제 제산세액 | C49: =C34*C30*C29*C31/C32 -> 1379.8498 | D49: 국세청 참고
B50: 결정세액 | C50: =IF((C48-C49)<E460,0,(C48-C49)) -> 0
A85: ■ | B85: 채권매각손 | D85: 구분(주거전용이외:1, 주거전용:0)
B86: 1. 소유권이전시(둘중하나만) | D86: 0
B87: - 주거전용이외 건축물(토지분 매입시 주거전용이외 건축물 매입금액 적용)
B88: 결정 채권액(천원) | C88: 개별공시지가(원) | D88: 시가표준액 | E88: 매 입 금 액 | F88: 매 입 비
B89: =MAX(F89:F91)/1000 -> 384.46875 | C89: =C20*1000 -> 8543750 | D89: 50000000 | E89: 0.025 | F89: =IF($C$93<D89,IF($C$93<5000000,0,$C$93*E89),0) -> 192234.38
B90: 할인 매입비(천원) | C90: 적용비율* | D90: 100000000 | E90: 0.04 | F90: =IF($C$93<D90,IF($C$93<5000000,0,$C$93*E90),0) -> 307575
B91: =IF(D86=1,B89*B113,0) -> 0 | C91: 0.9 | D91: 상기 초과 | E91: 0.05 | F91: =IF($C$93<5000000,0,$C$93*E91) -> 384468.75
C92: 시가표준액 | E92: *매입금액 : 특별시, 광역시 기준
C93: =C91*C89 -> 7689375
C94: * 지방세법 제111조제2항제1호
B96: - 주거전용 건축물(토지분 매입시 주거전용이외 건축물 매입금액 적용)
B97: 결정 채권액(천원) | C97: 개별공시지가(원) | D97: 시가표준액 | E97: 매 입 금 액 | F97: 매 입 비
B98: =MAX(F98:F103)/1000 -> 538.25625 | C98: =C20*1000 -> 8543750 | D98: 5000000 | E98: 0.02 | F98: =IF($C$102<D98,IF($C$102<500000,0,$C$102*E98),0) -> 0
B99: 할인 매입비(천원) | C99: 적용비율* | D99: 20000000 | E99: 0.035 | F99: =IF($C$93<D99,IF($C$93<5000000,0,$C$93*E99),0) -> 269128.12
B100: =IF(D86=0,B98*B113,0) -> 107.65125 | C100: 0.9 | D100: 30000000 | E100: 0.04 | F100: =IF($C$93<D100,IF($C$93<5000000,0,$C$93*E100),0) -> 307575
B101: 채권매각손 | C101: 시가표준액 | D101: 40000000 | E101: 0.05 | F101: =IF($C$93<D101,IF($C$93<5000000,0,$C$93*E101),0) -> 384468.75
B102: =B91+B100 -> 107.65125 | C102: =C100*C98 -> 7689375 | D102: 50000000 | E102: 0.06 | F102: =IF($C$93<D102,IF($C$93<5000000,0,$C$93*E102),0) -> 461362.5
C103: * 지방세법 제111조제2항제1호 | D103: 상기 초과 | E103: 0.07 | F103: =IF($C$93<5000000,0,$C$93*E103) -> 538256.25
E104: *매입금액 : 특별시, 광역시 기준
B106: 2. 건축허가시(셋중하나만)
B107: - 주거전용건축물(공동주택, APT)
B108: 결정 채권액(천원) | C108: 주거전용면적(㎡) | D108: 세 대 수 | E108: 주거전용면적(평) | F108: 기 준 (㎡) | G108: 매입금액(㎡당) | H108: 매 입 비(원)
B109: =SUM(H109:H115)/1000 -> 9.4332605e+08 | C109: =건축개요!D43 -> 59.98 | D109: =건축개요!C43 -> 19 | E109: =C109*0.3025 -> 18.14395 | F109: 100 | G109: 300 | H109: =IF($C$109<F109,IF($C$109<85,0,$C$109*G109*$D$109),0)+ IF($C$110<F109,IF($C$110<85,0,$C$110*G109*$D$110),0)+ IF($C$111<F109,IF($C$111<85,0,$C$111*G109*$D$111),0)+ IF($C$112<F109,IF($C$112<85,0,$C$112*G109*$D$112),0)+ IF($C$113<F109,IF($C$113<85,0,$C$113*G109*$D$113),0)+ IF($C$114<F109,IF($C$114<85,0,$C$114*G109*$D$114),0)+ IF($C$115<F109,IF($C$115<85,0,$C$115*G109*$D$115),0)+ IF($C$116<F109,IF($C$116<85,0,$C$116*G109*$D$116),0) -> 0
B110: 할인 매입비(천원) | C110: =건축개요!D44 -> 59.82 | D110: =건축개요!C44 -> 20 | E110: =C110*0.3025 -> 18.09555 | F110: 132 | G110: 1000 | H110: =IF($C$109<F110,IF($C$109<F109,0,$C$109*G110*$D$109),0)+ IF($C$110<F110,IF($C$110<F109,0,$C$110*G110*$D$110),0)+ IF($C$111<F110,IF($C$111<F109,0,$C$111*G110*$D$111),0)+ IF($C$112<F110,IF($C$112<F109,0,$C$112*G110*$D$112),0)+ IF($C$113<F110,IF($C$113<F109,0,$C$113*G110*$D$113),0)+ IF($C$114<F110,IF($C$114<F109,0,$C$114*G110*$D$114),0)+ IF($C$115<F110,IF($C$115<F109,0,$C$115*G110*$D$115),0)+ IF($C$116<F110,IF($C$116<F109,0,$C$116*G110*$D$116),0) -> 0
B111: =B109*B113 -> 1.8866521e+08 | C111: =건축개요!D45 -> 84.94 | D111: =건축개요!C45 -> 88 | E111: =C111*0.3025 -> 25.69435 | F111: 165 | G111: 2000 | H111: =IF($C$109<F111,IF($C$109<F110,0,$C$109*G111*$D$109),0)+ IF($C$110<F111,IF($C$110<F110,0,$C$110*G111*$D$110),0)+ IF($C$111<F111,IF($C$111<F110,0,$C$111*G111*$D$111),0)+ IF($C$112<F111,IF($C$112<F110,0,$C$112*G111*$D$112),0)+ IF($C$113<F111,IF($C$113<F110,0,$C$113*G111*$D$113),0)+ IF($C$114<F111,IF($C$114<F110,0,$C$114*G111*$D$114),0)+ IF($C$115<F111,IF($C$115<F110,0,$C$115*G111*$D$115),0)+ IF($C$116<F111,IF($C$116<F110,0,$C$116*G111*$D$116),0) -> 0
B112: 할 인 율 | C112: =건축개요!D57 -> 52314 | D112: =건축개요!C57 -> 644 | E112: =C112*0.3025 -> 15824.985 | F112: 231 | G112: 4000 | H112: =IF($C$109<F112,IF($C$109<F111,0,$C$109*G112*$D$109),0)+ IF($C$110<F112,IF($C$110<F111,0,$C$110*G112*$D$110),0)+ IF($C$111<F112,IF($C$111<F111,0,$C$111*G112*$D$111),0)+ IF($C$112<F112,IF($C$112<F111,0,$C$112*G112*$D$112),0)+ IF($C$113<F112,IF($C$113<F111,0,$C$113*G112*$D$113),0)+ IF($C$114<F112,IF($C$114<F111,0,$C$114*G112*$D$114),0)+ IF($C$115<F112,IF($C$115<F111,0,$C$115*G112*$D$115),0)+ IF($C$116<F112,IF($C$116<F111,0,$C$116*G112*$D$116),0) -> 0
B113: 0.2 | C113: =건축개요!D58 -> 0 | D113: =건축개요!C58 -> 0 | E113: =C113*0.3025 -> 0 | F113: 330 | G113: 10000 | H113: =IF($C$109<F113,IF($C$109<F112,0,$C$109*G113*$D$109),0)+ IF($C$110<F113,IF($C$110<F112,0,$C$110*G113*$D$110),0)+ IF($C$111<F113,IF($C$111<F112,0,$C$111*G113*$D$111),0)+ IF($C$112<F113,IF($C$112<F112,0,$C$112*G113*$D$112),0)+ IF($C$113<F113,IF($C$113<F112,0,$C$113*G113*$D$113),0)+ IF($C$114<F113,IF($C$114<F112,0,$C$114*G113*$D$114),0)+ IF($C$115<F113,IF($C$115<F112,0,$C$115*G113*$D$115),0)+ IF($C$116<F113,IF($C$116<F112,0,$C$116*G113*$D$116),0) -> 0
C114: =건축개요!D82 -> 0 | D114: =건축개요!C82 -> 0 | E114: =C114*0.3025 -> 0 | F114: 660 | G114: 17000 | H114: =IF($C$109<F114,IF($C$109<F113,0,$C$109*G114*$D$109),0)+ IF($C$110<F114,IF($C$110<F113,0,$C$110*G114*$D$110),0)+ IF($C$111<F114,IF($C$111<F113,0,$C$111*G114*$D$111),0)+ IF($C$112<F114,IF($C$112<F113,0,$C$112*G114*$D$112),0)+ IF($C$113<F114,IF($C$113<F113,0,$C$113*G114*$D$113),0)+ IF($C$114<F114,IF($C$114<F113,0,$C$114*G114*$D$114),0)+ IF($C$115<F114,IF($C$115<F113,0,$C$115*G114*$D$115),0)+ IF($C$116<F114,IF($C$116<F113,0,$C$116*G114*$D$116),0) -> 0
C115: =건축개요!D83 -> 0 | D115: =건축개요!C83 -> 0 | E115: =C115*0.3025 -> 0 | F115: 상기 초과 | G115: 28000 | H115: =IF($C$109<F114,0,$C$109*G115*$D$109)+ IF($C$110<F114,0,$C$110*G115*$D$110)+ IF($C$111<F114,0,$C$111*G115*$D$111)+ IF($C$112<F114,0,$C$112*G115*$D$112)+ IF($C$113<F114,0,$C$113*G115*$D$113)+ IF($C$114<F114,0,$C$114*G115*$D$114)+ IF($C$115<F114,0,$C$115*G115*$D$115)+ IF($C$116<F114,0,$C$116*G115*$D$116) -> 9.4332605e+11
C116: =건축개요!D84 -> 0 | D116: 0 | E116: =C116*0.3025 -> 0
D127: * 가정 : 주택은행 고시
E129: 구조
B130: - 주거전용이외 건축물 | E130: 철근 및 철골조
B131: 결정 채권액(천원) | C131: 면 적(㎡) | D131: 면 적(평) | E131: 구 분 | F131: 매입금액(원/㎡) | G131: 매 입 비(원)
B132: =SUM(G132:G135)/1000 -> 0 | C132: =건축개요!D115 -> 0 | D132: =C132*0.3025 -> 0 | E132: 극장,영화관,주점 | F132: 4000 | G132: =IF(E132=$E$130,$C$132*F132,0) -> 0 | H132: ex) 본 사업성 검토시 항목에 포함안 됨
B133: 할인 매입비(천원) | E133: 철근 및 철골조 | F133: 1300 | G133: =IF(E133=$E$130,$C$132*F133,0) -> 0
B134: =B132*B113 -> 0 | E134: 연와조 및 석조 | F134: 1000 | G134: =IF(E134=$E$130,$C$132*F134,0) -> 0
E135: 시멘트벽돌및 블록조 | F135: 600 | G135: =IF(E135=$E$130,$C$132*F135,0) -> 0
B137: - 혼합된 건물(주거 + 비주거)
B138: 할인 매입비(천원)
B139: =SUM(B111,B134) -> 1.8866521e+08
A142: ■ | B142: 등기수수료
B143: 구분 | C143: 금액 | E143: 비고
B144: 등기수수료 | C144: 18 | D144: 천원/회
B145: 이전등기시 | C145: 10 | D145: 회 | E145: 가정
B146: 보존등기시 | C146: 10 | D146: 회 | E146: 가정
B147: 총세대수 | C147: =SUM(C148:C151) -> 644 | D147: 세대
B148: 아파트 | C148: =사업검토!G22 -> 644 | D148: 세대
B149: 오피스텔 | C149: - | D149: 실
B150: 오피스 | C150: - | D150: 실 | E150: 50
B151: 상가 | C151: =사업검토!F69 -> 0 | D151: 실 | E151: 50
B152: 이전등기수수료 | C152: =C145*C144 -> 180 | D152: 천원
B153: 보전등기수수료 | C153: =C144*C146*C147 -> 115920 | D153: 천원
A155: ■ | B155: 건축허가수수료
B156: 결 정 수 수 료 (천원) | C156: 건축면적(㎡) | D156: 건 축 면 적(㎡) | E156: 수 수 료 (원) | F156: 비 고
B157: 810 | C157: =C160/0.3025 -> #REF! | D157: 200 | E157: 9400 | F157: =IF(C157<D157,9400,0) -> #REF!
D158: 1000 | E158: 20000 | F158: =IF($C$157<D158,IF($C$157<D157,0,20000),0) -> #REF!
C159: 건축연면적(평) | D159: 5000 | E159: 54000 | F159: =IF($C$157<D159,IF($C$157<D158,0,54000),0) -> #REF!
C160: =사업검토!#REF! -> #REF! | D160: 10000 | E160: 100000 | F160: =IF($C$157<D160,IF($C$157<D159,0,100000),0) -> #REF!
D161: 30000 | E161: 200000 | F161: =IF($C$157<D161,IF($C$157<D160,0,200000),0) -> #REF!
D162: 100000 | E162: 410000 | F162: =IF($C$157<D162,IF($C$157<D161,0,410000),0) -> #REF!
...
